Workbook
Name Quota: Inputs!$C$5
Name CovTarget: Inputs!$C$7
Name GPTarget: Inputs!$C$9
Name AgeThresh: Inputs!$C$11
Name RiskThresh: Inputs!$C$13
Name DashTitle: Inputs!$C$15
Name DashSub: Inputs!$C$17
Name RepPrefix1: Inputs!$C$22
Name RepName1: Inputs!$C$23
Name RepPrefix2: Inputs!$C$25
Name RepName2: Inputs!$C$26
Name RepPrefix3: Inputs!$C$28
Name RepName3: Inputs!$C$29
Name RepPrefix4: Inputs!$C$31
Name RepName4: Inputs!$C$32
Name RepPrefix5: Inputs!$C$34
Name RepName5: Inputs!$C$35
Name RepPrefix6: Inputs!$C$37
Name RepName6: Inputs!$C$38

Sheet Dashboard
B2: =DashTitle | H2: =UPPER(TEXT(TODAY(),"DDDD, DD MMMM YYYY"))
B3: =DashSub | H3: =RepName1&" · "&RepName2&" · "&RepName3
B5: ='Per-Rep Detail'!H11 | D5: ='Per-Rep Detail'!I11 | F5: =IFERROR('Per-Rep Detail'!I11/'Per-Rep Detail'!H11,0) | H5: ='Per-Rep Detail'!K11 | J5: ='Per-Rep Detail'!D11 | L5: ='Per-Rep Detail'!G11
B6: TOTAL TCV | D6: TOTAL GP | F6: GP MARGIN | H6: WEIGHTED PIPE | J6: ACTIVE OPPS | L6: WIN RATE
B8: REP LEADERBOARD | H8: STAGE BREAKDOWN
B9: REP | C9: TCV | D9: GP | E9: GP% | F9: WTD PIPE | H9: STAGE | I9: OPPS | J9: TCV | K9: WTD | L9: PROB | N9: Δ vs Quota
B10: =RepName3 | C10: =(SUMIFS('Home-Conversion'!H4:H202,'Home-Conversion'!G4:G202,"<>Closed Lost",'Home-Conversion'!G4:G202,"<>")) | D10: =(SUMIFS('Home-Conversion'!I4:I202,'Home-Conversion'!G4:G202,"<>Closed Lost",'Home-Conversion'!G4:G202,"<>")) | E10: =IFERROR((SUMIFS('Home-Conversion'!I4:I202,'Home-Conversion'!G4:G202,"<>Closed Lost",'Home-Conversion'!G4:G202,"<>"))/(SUMIFS('Home-Conversion'!H4:H202,'Home-Conversion'!G4:G202,"<>Closed Lost",'Home-Conversion'!G4:G202,"<>")),0) | F10: =((SUMIFS('Home-Conversion'!H4:H202,'Home-Conversion'!G4:G202,"Opportunity Creation")*0.1+SUMIFS('Home-Conversion'!H4:H202,'Home-Conversion'!G4:G202,"Scoping")*0.3+SUMIFS('Home-Conversion'!H4:H202,'Home-Conversion'!G4:G202,"BOM Submission")*0.5+SUMIFS('Home-Conversion'!H4:H202,'Home-Conversion'!G4:G202,"Resubmission")*0.7+SUMIFS('Home-Conversion'!H4:H202,'Home-Conversion'!G4:G202,"Negotiation")*0.9)) | H10: Opportunity Creation | I10: =COUNTIF('Madine- Conversion'!G4:G202,"Opportunity Creation")+COUNTIF('Zarrah-Conversion'!G3:G201,"Opportunity Creation")+COUNTIF('Home-Conversion'!G4:G202,"Opportunity Creation")+IF(RepPrefix4="",0,IFERROR(COUNTIF(INDIRECT("'"&RepPrefix4&"- Conversion'!G4:G202"),"Opportunity Creation"),0))+IF(RepPrefix5="",0,IFERROR(COUNTIF(INDIRECT("'"&RepPrefix5&"- Conversion'!G4:G202"),"Opportunity Creation"),0))+IF(RepPrefix6="",0,IFERROR(COUNTIF(INDIRECT("'"&RepPrefix6&"- Conversion'!G4:G202"),"Opportunity Creation"),0)) | J10: =SUMIFS('Madine- Conversion'!H4:H202,'Madine- Conversion'!G4:G202,"Opportunity Creation")+SUMIFS('Zarrah-Conversion'!H3:H201,'Zarrah-Conversion'!G3:G201,"Opportunity Creation")+SUMIFS('Home-Conversion'!H4:H202,'Home-Conversion'!G4:G202,"Opportunity Creation")+IF(RepPrefix4="",0,IFERROR(SUMIFS(INDIRECT("'"&RepPrefix4&"- Conversion'!H4:H202"),INDIRECT("'"&RepPrefix4&"- Conversion'!G4:G202"),"Opportunity Creation"),0))+IF(RepPrefix5="",0,IFERROR(SUMIFS(INDIRECT("'"&RepPrefix5&"- Conversion'!H4:H202"),INDIRECT("'"&RepPrefix5&"- Conversion'!G4:G202"),"Opportunity Creation"),0))+IF(RepPrefix6="",0,IFERROR(SUMIFS(INDIRECT("'"&RepPrefix6&"- Conversion'!H4:H202"),INDIRECT("'"&RepPrefix6&"- Conversion'!G4:G202"),"Opportunity Creation"),0)) | K10: =J10*0.1 | L10: 0.1 | N10: =IFERROR(F16/Quota,0)
B11: =RepName2 | C11: =(SUMIFS('Zarrah-Conversion'!H3:H201,'Zarrah-Conversion'!G3:G201,"<>Closed Lost",'Zarrah-Conversion'!G3:G201,"<>")) | D11: =(SUMIFS('Zarrah-Conversion'!I3:I201,'Zarrah-Conversion'!G3:G201,"<>Closed Lost",'Zarrah-Conversion'!G3:G201,"<>")) | E11: =IFERROR((SUMIFS('Zarrah-Conversion'!I3:I201,'Zarrah-Conversion'!G3:G201,"<>Closed Lost",'Zarrah-Conversion'!G3:G201,"<>"))/(SUMIFS('Zarrah-Conversion'!H3:H201,'Zarrah-Conversion'!G3:G201,"<>Closed Lost",'Zarrah-Conversion'!G3:G201,"<>")),0) | F11: =((SUMIFS('Zarrah-Conversion'!H3:H201,'Zarrah-Conversion'!G3:G201,"Opportunity Creation")*0.1+SUMIFS('Zarrah-Conversion'!H3:H201,'Zarrah-Conversion'!G3:G201,"Scoping")*0.3+SUMIFS('Zarrah-Conversion'!H3:H201,'Zarrah-Conversion'!G3:G201,"BOM Submission")*0.5+SUMIFS('Zarrah-Conversion'!H3:H201,'Zarrah-Conversion'!G3:G201,"Resubmission")*0.7+SUMIFS('Zarrah-Conversion'!H3:H201,'Zarrah-Conversion'!G3:G201,"Negotiation")*0.9)) | H11: Scoping | I11: =COUNTIF('Madine- Conversion'!G4:G202,"Scoping")+COUNTIF('Zarrah-Conversion'!G3:G201,"Scoping")+COUNTIF('Home-Conversion'!G4:G202,"Scoping")+IF(RepPrefix4="",0,IFERROR(COUNTIF(INDIRECT("'"&RepPrefix4&"- Conversion'!G4:G202"),"Scoping"),0))+IF(RepPrefix5="",0,IFERROR(COUNTIF(INDIRECT("'"&RepPrefix5&"- Conversion'!G4:G202"),"Scoping"),0))+IF(RepPrefix6="",0,IFERROR(COUNTIF(INDIRECT("'"&RepPrefix6&"- Conversion'!G4:G202"),"Scoping"),0)) | J11: =SUMIFS('Madine- Conversion'!H4:H202,'Madine- Conversion'!G4:G202,"Scoping")+SUMIFS('Zarrah-Conversion'!H3:H201,'Zarrah-Conversion'!G3:G201,"Scoping")+SUMIFS('Home-Conversion'!H4:H202,'Home-Conversion'!G4:G202,"Scoping")+IF(RepPrefix4="",0,IFERROR(SUMIFS(INDIRECT("'"&RepPrefix4&"- Conversion'!H4:H202"),INDIRECT("'"&RepPrefix4&"- Conversion'!G4:G202"),"Scoping"),0))+IF(RepPrefix5="",0,IFERROR(SUMIFS(INDIRECT("'"&RepPrefix5&"- Conversion'!H4:H202"),INDIRECT("'"&RepPrefix5&"- Conversion'!G4:G202"),"Scoping"),0))+IF(RepPrefix6="",0,IFERROR(SUMIFS(INDIRECT("'"&RepPrefix6&"- Conversion'!H4:H202"),INDIRECT("'"&RepPrefix6&"- Conversion'!G4:G202"),"Scoping"),0)) | K11: =J11*0.3 | L11: 0.3 | N11: Pipe÷Quota
B12: =RepName1 | C12: =(SUMIFS('Madine- Conversion'!H4:H202,'Madine- Conversion'!G4:G202,"<>Closed Lost",'Madine- Conversion'!G4:G202,"<>")) | D12: =(SUMIFS('Madine- Conversion'!I4:I202,'Madine- Conversion'!G4:G202,"<>Closed Lost",'Madine- Conversion'!G4:G202,"<>")) | E12: =IFERROR((SUMIFS('Madine- Conversion'!I4:I202,'Madine- Conversion'!G4:G202,"<>Closed Lost",'Madine- Conversion'!G4:G202,"<>"))/(SUMIFS('Madine- Conversion'!H4:H202,'Madine- Conversion'!G4:G202,"<>Closed Lost",'Madine- Conversion'!G4:G202,"<>")),0) | F12: =((SUMIFS('Madine- Conversion'!H4:H202,'Madine- Conversion'!G4:G202,"Opportunity Creation")*0.1+SUMIFS('Madine- Conversion'!H4:H202,'Madine- Conversion'!G4:G202,"Scoping")*0.3+SUMIFS('Madine- Conversion'!H4:H202,'Madine- Conversion'!G4:G202,"BOM Submission")*0.5+SUMIFS('Madine- Conversion'!H4:H202,'Madine- Conversion'!G4:G202,"Resubmission")*0.7+SUMIFS('Madine- Conversion'!H4:H202,'Madine- Conversion'!G4:G202,"Negotiation")*0.9)) | H12: BOM Submission | I12: =COUNTIF('Madine- Conversion'!G4:G202,"BOM Submission")+COUNTIF('Zarrah-Conversion'!G3:G201,"BOM Submission")+COUNTIF('Home-Conversion'!G4:G202,"BOM Submission")+IF(RepPrefix4="",0,IFERROR(COUNTIF(INDIRECT("'"&RepPrefix4&"- Conversion'!G4:G202"),"BOM Submission"),0))+IF(RepPrefix5="",0,IFERROR(COUNTIF(INDIRECT("'"&RepPrefix5&"- Conversion'!G4:G202"),"BOM Submission"),0))+IF(RepPrefix6="",0,IFERROR(COUNTIF(INDIRECT("'"&RepPrefix6&"- Conversion'!G4:G202"),"BOM Submission"),0)) | J12: =SUMIFS('Madine- Conversion'!H4:H202,'Madine- Conversion'!G4:G202,"BOM Submission")+SUMIFS('Zarrah-Conversion'!H3:H201,'Zarrah-Conversion'!G3:G201,"BOM Submission")+SUMIFS('Home-Conversion'!H4:H202,'Home-Conversion'!G4:G202,"BOM Submission")+IF(RepPrefix4="",0,IFERROR(SUMIFS(INDIRECT("'"&RepPrefix4&"- Conversion'!H4:H202"),INDIRECT("'"&RepPrefix4&"- Conversion'!G4:G202"),"BOM Submission"),0))+IF(RepPrefix5="",0,IFERROR(SUMIFS(INDIRECT("'"&RepPrefix5&"- Conversion'!H4:H202"),INDIRECT("'"&RepPrefix5&"- Conversion'!G4:G202"),"BOM Submission"),0))+IF(RepPrefix6="",0,IFERROR(SUMIFS(INDIRECT("'"&RepPrefix6&"- Conversion'!H4:H202"),INDIRECT("'"&RepPrefix6&"- Conversion'!G4:G202"),"BOM Submission"),0)) | K12: =J12*0.5 | L12: 0.5
B13: =IF(RepPrefix4="","",RepName4) | C13: =IF(RepPrefix4="","",(IF(RepPrefix4="",0,IFERROR(SUMIFS(INDIRECT("'"&RepPrefix4&"- Conversion'!H4:H202"),INDIRECT("'"&RepPrefix4&"- Conversion'!G4:G202"),"<>Closed Lost",INDIRECT("'"&RepPrefix4&"- Conversion'!G4:G202"),"<>"),0)))) | D13: =IF(RepPrefix4="","",(IF(RepPrefix4="",0,IFERROR(SUMIFS(INDIRECT("'"&RepPrefix4&"- Conversion'!I4:I202"),INDIRECT("'"&RepPrefix4&"- Conversion'!G4:G202"),"<>Closed Lost",INDIRECT("'"&RepPrefix4&"- Conversion'!G4:G202"),"<>"),0)))) | E13: =IF(RepPrefix4="","",IFERROR((IF(RepPrefix4="",0,IFERROR(SUMIFS(INDIRECT("'"&RepPrefix4&"- Conversion'!I4:I202"),INDIRECT("'"&RepPrefix4&"- Conversion'!G4:G202"),"<>Closed Lost",INDIRECT("'"&RepPrefix4&"- Conversion'!G4:G202"),"<>"),0)))/(IF(RepPrefix4="",0,IFERROR(SUMIFS(INDIRECT("'"&RepPrefix4&"- Conversion'!H4:H202"),INDIRECT("'"&RepPrefix4&"- Conversion'!G4:G202"),"<>Closed Lost",INDIRECT("'"&RepPrefix4&"- Conversion'!G4:G202"),"<>"),0))),0)) | F13: =IF(RepPrefix4="","",((IF(RepPrefix4="",0,IFERROR(SUMIFS(INDIRECT("'"&RepPrefix4&"- Conversion'!H4:H202"),INDIRECT("'"&RepPrefix4&"- Conversion'!G4:G202"),"Opportunity Creation"),0))*0.1+IF(RepPrefix4="",0,IFERROR(SUMIFS(INDIRECT("'"&RepPrefix4&"- Conversion'!H4:H202"),INDIRECT("'"&RepPrefix4&"- Conversion'!G4:G202"),"Scoping"),0))*0.3+IF(RepPrefix4="",0,IFERROR(SUMIFS(INDIRECT("'"&RepPrefix4&"- Conversion'!H4:H202"),INDIRECT("'"&RepPrefix4&"- Conversion'!G4:G202"),"BOM Submission"),0))*0.5+IF(RepPrefix4="",0,IFERROR(SUMIFS(INDIRECT("'"&RepPrefix4&"- Conversion'!H4:H202"),INDIRECT("'"&RepPrefix4&"- Conversion'!G4:G202"),"Resubmission"),0))*0.7+IF(RepPrefix4="",0,IFERROR(SUMIFS(INDIRECT("'"&RepPrefix4&"- Conversion'!H4:H202"),INDIRECT("'"&RepPrefix4&"- Conversion'!G4:G202"),"Negotiation"),0))*0.9))) | H13: Resubmission | I13: =COUNTIF('Madine- Conversion'!G4:G202,"Resubmission")+COUNTIF('Zarrah-Conversion'!G3:G201,"Resubmission")+COUNTIF('Home-Conversion'!G4:G202,"Resubmission")+IF(RepPrefix4="",0,IFERROR(COUNTIF(INDIRECT("'"&RepPrefix4&"- Conversion'!G4:G202"),"Resubmission"),0))+IF(RepPrefix5="",0,IFERROR(COUNTIF(INDIRECT("'"&RepPrefix5&"- Conversion'!G4:G202"),"Resubmission"),0))+IF(RepPrefix6="",0,IFERROR(COUNTIF(INDIRECT("'"&RepPrefix6&"- Conversion'!G4:G202"),"Resubmission"),0)) | J13: =SUMIFS('Madine- Conversion'!H4:H202,'Madine- Conversion'!G4:G202,"Resubmission")+SUMIFS('Zarrah-Conversion'!H3:H201,'Zarrah-Conversion'!G3:G201,"Resubmission")+SUMIFS('Home-Conversion'!H4:H202,'Home-Conversion'!G4:G202,"Resubmission")+IF(RepPrefix4="",0,IFERROR(SUMIFS(INDIRECT("'"&RepPrefix4&"- Conversion'!H4:H202"),INDIRECT("'"&RepPrefix4&"- Conversion'!G4:G202"),"Resubmission"),0))+IF(RepPrefix5="",0,IFERROR(SUMIFS(INDIRECT("'"&RepPrefix5&"- Conversion'!H4:H202"),INDIRECT("'"&RepPrefix5&"- Conversion'!G4:G202"),"Resubmission"),0))+IF(RepPrefix6="",0,IFERROR(SUMIFS(INDIRECT("'"&RepPrefix6&"- Conversion'!H4:H202"),INDIRECT("'"&RepPrefix6&"- Conversion'!G4:G202"),"Resubmission"),0)) | K13: =J13*0.7 | L13: 0.7
B14: =IF(RepPrefix5="","",RepName5) | C14: =IF(RepPrefix5="","",(IF(RepPrefix5="",0,IFERROR(SUMIFS(INDIRECT("'"&RepPrefix5&"- Conversion'!H4:H202"),INDIRECT("'"&RepPrefix5&"- Conversion'!G4:G202"),"<>Closed Lost",INDIRECT("'"&RepPrefix5&"- Conversion'!G4:G202"),"<>"),0)))) | D14: =IF(RepPrefix5="","",(IF(RepPrefix5="",0,IFERROR(SUMIFS(INDIRECT("'"&RepPrefix5&"- Conversion'!I4:I202"),INDIRECT("'"&RepPrefix5&"- Conversion'!G4:G202"),"<>Closed Lost",INDIRECT("'"&RepPrefix5&"- Conversion'!G4:G202"),"<>"),0)))) | E14: =IF(RepPrefix5="","",IFERROR((IF(RepPrefix5="",0,IFERROR(SUMIFS(INDIRECT("'"&RepPrefix5&"- Conversion'!I4:I202"),INDIRECT("'"&RepPrefix5&"- Conversion'!G4:G202"),"<>Closed Lost",INDIRECT("'"&RepPrefix5&"- Conversion'!G4:G202"),"<>"),0)))/(IF(RepPrefix5="",0,IFERROR(SUMIFS(INDIRECT("'"&RepPrefix5&"- Conversion'!H4:H202"),INDIRECT("'"&RepPrefix5&"- Conversion'!G4:G202"),"<>Closed Lost",INDIRECT("'"&RepPrefix5&"- Conversion'!G4:G202"),"<>"),0))),0)) | F14: =IF(RepPrefix5="","",((IF(RepPrefix5="",0,IFERROR(SUMIFS(INDIRECT("'"&RepPrefix5&"- Conversion'!H4:H202"),INDIRECT("'"&RepPrefix5&"- Conversion'!G4:G202"),"Opportunity Creation"),0))*0.1+IF(RepPrefix5="",0,IFERROR(SUMIFS(INDIRECT("'"&RepPrefix5&"- Conversion'!H4:H202"),INDIRECT("'"&RepPrefix5&"- Conversion'!G4:G202"),"Scoping"),0))*0.3+IF(RepPrefix5="",0,IFERROR(SUMIFS(INDIRECT("'"&RepPrefix5&"- Conversion'!H4:H202"),INDIRECT("'"&RepPrefix5&"- Conversion'!G4:G202"),"BOM Submission"),0))*0.5+IF(RepPrefix5="",0,IFERROR(SUMIFS(INDIRECT("'"&RepPrefix5&"- Conversion'!H4:H202"),INDIRECT("'"&RepPrefix5&"- Conversion'!G4:G202"),"Resubmission"),0))*0.7+IF(RepPrefix5="",0,IFERROR(SUMIFS(INDIRECT("'"&RepPrefix5&"- Conversion'!H4:H202"),INDIRECT("'"&RepPrefix5&"- Conversion'!G4:G202"),"Negotiation"),0))*0.9))) | H14: Negotiation | I14: =COUNTIF('Madine- Conversion'!G4:G202,"Negotiation")+COUNTIF('Zarrah-Conversion'!G3:G201,"Negotiation")+COUNTIF('Home-Conversion'!G4:G202,"Negotiation")+IF(RepPrefix4="",0,IFERROR(COUNTIF(INDIRECT("'"&RepPrefix4&"- Conversion'!G4:G202"),"Negotiation"),0))+IF(RepPrefix5="",0,IFERROR(COUNTIF(INDIRECT("'"&RepPrefix5&"- Conversion'!G4:G202"),"Negotiation"),0))+IF(RepPrefix6="",0,IFERROR(COUNTIF(INDIRECT("'"&RepPrefix6&"- Conversion'!G4:G202"),"Negotiation"),0)) | J14: =SUMIFS('Madine- Conversion'!H4:H202,'Madine- Conversion'!G4:G202,"Negotiation")+SUMIFS('Zarrah-Conversion'!H3:H201,'Zarrah-Conversion'!G3:G201,"Negotiation")+SUMIFS('Home-Conversion'!H4:H202,'Home-Conversion'!G4:G202,"Negotiation")+IF(RepPrefix4="",0,IFERROR(SUMIFS(INDIRECT("'"&RepPrefix4&"- Conversion'!H4:H202"),INDIRECT("'"&RepPrefix4&"- Conversion'!G4:G202"),"Negotiation"),0))+IF(RepPrefix5="",0,IFERROR(SUMIFS(INDIRECT("'"&RepPrefix5&"- Conversion'!H4:H202"),INDIRECT("'"&RepPrefix5&"- Conversion'!G4:G202"),"Negotiation"),0))+IF(RepPrefix6="",0,IFERROR(SUMIFS(INDIRECT("'"&RepPrefix6&"- Conversion'!H4:H202"),INDIRECT("'"&RepPrefix6&"- Conversion'!G4:G202"),"Negotiation"),0)) | K14: =J14*0.9 | L14: 0.9
B15: =IF(RepPrefix6="","",RepName6) | C15: =IF(RepPrefix6="","",(IF(RepPrefix6="",0,IFERROR(SUMIFS(INDIRECT("'"&RepPrefix6&"- Conversion'!H4:H202"),INDIRECT("'"&RepPrefix6&"- Conversion'!G4:G202"),"<>Closed Lost",INDIRECT("'"&RepPrefix6&"- Conversion'!G4:G202"),"<>"),0)))) | D15: =IF(RepPrefix6="","",(IF(RepPrefix6="",0,IFERROR(SUMIFS(INDIRECT("'"&RepPrefix6&"- Conversion'!I4:I202"),INDIRECT("'"&RepPrefix6&"- Conversion'!G4:G202"),"<>Closed Lost",INDIRECT("'"&RepPrefix6&"- Conversion'!G4:G202"),"<>"),0)))) | E15: =IF(RepPrefix6="","",IFERROR((IF(RepPrefix6="",0,IFERROR(SUMIFS(INDIRECT("'"&RepPrefix6&"- Conversion'!I4:I202"),INDIRECT("'"&RepPrefix6&"- Conversion'!G4:G202"),"<>Closed Lost",INDIRECT("'"&RepPrefix6&"- Conversion'!G4:G202"),"<>"),0)))/(IF(RepPrefix6="",0,IFERROR(SUMIFS(INDIRECT("'"&RepPrefix6&"- Conversion'!H4:H202"),INDIRECT("'"&RepPrefix6&"- Conversion'!G4:G202"),"<>Closed Lost",INDIRECT("'"&RepPrefix6&"- Conversion'!G4:G202"),"<>"),0))),0)) | F15: =IF(RepPrefix6="","",((IF(RepPrefix6="",0,IFERROR(SUMIFS(INDIRECT("'"&RepPrefix6&"- Conversion'!H4:H202"),INDIRECT("'"&RepPrefix6&"- Conversion'!G4:G202"),"Opportunity Creation"),0))*0.1+IF(RepPrefix6="",0,IFERROR(SUMIFS(INDIRECT("'"&RepPrefix6&"- Conversion'!H4:H202"),INDIRECT("'"&RepPrefix6&"- Conversion'!G4:G202"),"Scoping"),0))*0.3+IF(RepPrefix6="",0,IFERROR(SUMIFS(INDIRECT("'"&RepPrefix6&"- Conversion'!H4:H202"),INDIRECT("'"&RepPrefix6&"- Conversion'!G4:G202"),"BOM Submission"),0))*0.5+IF(RepPrefix6="",0,IFERROR(SUMIFS(INDIRECT("'"&RepPrefix6&"- Conversion'!H4:H202"),INDIRECT("'"&RepPrefix6&"- Conversion'!G4:G202"),"Resubmission"),0))*0.7+IF(RepPrefix6="",0,IFERROR(SUMIFS(INDIRECT("'"&RepPrefix6&"- Conversion'!H4:H202"),INDIRECT("'"&RepPrefix6&"- Conversion'!G4:G202"),"Negotiation"),0))*0.9))) | H15: Closed Won | I15: =COUNTIF('Madine- Conversion'!G4:G202,"Closed Won")+COUNTIF('Zarrah-Conversion'!G3:G201,"Closed Won")+COUNTIF('Home-Conversion'!G4:G202,"Closed Won")+IF(RepPrefix4="",0,IFERROR(COUNTIF(INDIRECT("'"&RepPrefix4&"- Conversion'!G4:G202"),"Closed Won"),0))+IF(RepPrefix5="",0,IFERROR(COUNTIF(INDIRECT("'"&RepPrefix5&"- Conversion'!G4:G202"),"Closed Won"),0))+IF(RepPrefix6="",0,IFERROR(COUNTIF(INDIRECT("'"&RepPrefix6&"- Conversion'!G4:G202"),"Closed Won"),0)) | J15: =SUMIFS('Madine- Conversion'!H4:H202,'Madine- Conversion'!G4:G202,"Closed Won")+SUMIFS('Zarrah-Conversion'!H3:H201,'Zarrah-Conversion'!G3:G201,"Closed Won")+SUMIFS('Home-Conversion'!H4:H202,'Home-Conversion'!G4:G202,"Closed Won")+IF(RepPrefix4="",0,IFERROR(SUMIFS(INDIRECT("'"&RepPrefix4&"- Conversion'!H4:H202"),INDIRECT("'"&RepPrefix4&"- Conversion'!G4:G202"),"Closed Won"),0))+IF(RepPrefix5="",0,IFERROR(SUMIFS(INDIRECT("'"&RepPrefix5&"- Conversion'!H4:H202"),INDIRECT("'"&RepPrefix5&"- Conversion'!G4:G202"),"Closed Won"),0))+IF(RepPrefix6="",0,IFERROR(SUMIFS(INDIRECT("'"&RepPrefix6&"- Conversion'!H4:H202"),INDIRECT("'"&RepPrefix6&"- Conversion'!G4:G202"),"Closed Won"),0)) | K15: =J15*1.0 | L15: 1
B16: TOTAL | C16: =SUM(C10:C15) | D16: =SUM(D10:D15) | E16: =IFERROR(D16/C16,0) | F16: =SUM(F10:F15) | H16: Closed Lost | I16: =COUNTIF('Madine- Conversion'!G4:G202,"Closed Lost")+COUNTIF('Zarrah-Conversion'!G3:G201,"Closed Lost")+COUNTIF('Home-Conversion'!G4:G202,"Closed Lost")+IF(RepPrefix4="",0,IFERROR(COUNTIF(INDIRECT("'"&RepPrefix4&"- Conversion'!G4:G202"),"Closed Lost"),0))+IF(RepPrefix5="",0,IFERROR(COUNTIF(INDIRECT("'"&RepPrefix5&"- Conversion'!G4:G202"),"Closed Lost"),0))+IF(RepPrefix6="",0,IFERROR(COUNTIF(INDIRECT("'"&RepPrefix6&"- Conversion'!G4:G202"),"Closed Lost"),0)) | J16: =SUMIFS('Madine- Conversion'!H4:H202,'Madine- Conversion'!G4:G202,"Closed Lost")+SUMIFS('Zarrah-Conversion'!H3:H201,'Zarrah-Conversion'!G3:G201,"Closed Lost")+SUMIFS('Home-Conversion'!H4:H202,'Home-Conversion'!G4:G202,"Closed Lost")+IF(RepPrefix4="",0,IFERROR(SUMIFS(INDIRECT("'"&RepPrefix4&"- Conversion'!H4:H202"),INDIRECT("'"&RepPrefix4&"- Conversion'!G4:G202"),"Closed Lost"),0))+IF(RepPrefix5="",0,IFERROR(SUMIFS(INDIRECT("'"&RepPrefix5&"- Conversion'!H4:H202"),INDIRECT("'"&RepPrefix5&"- Conversion'!G4:G202"),"Closed Lost"),0))+IF(RepPrefix6="",0,IFERROR(SUMIFS(INDIRECT("'"&RepPrefix6&"- Conversion'!H4:H202"),INDIRECT("'"&RepPrefix6&"- Conversion'!G4:G202"),"Closed Lost"),0)) | K16: 0 | L16: 0
H17: PIPELINE TOTAL | I17: =SUM(I10:I15) | J17: =SUM(J10:J15) | K17: =SUM(K10:K15)
B19: PIPELINE HEALTH · AT-RISK & PAST-DUE DEALS
B20: =SUM('Per-Rep Detail'!M5:M10) | D20: =(SUMPRODUCT(--ISNUMBER('Madine- Conversion'!J4:J202),--('Madine- Conversion'!J4:J202<TODAY()),--('Madine- Conversion'!G4:G202="Opportunity Creation"),'Madine- Conversion'!H4:H202)+SUMPRODUCT(--ISNUMBER('Madine- Conversion'!J4:J202),--('Madine- Conversion'!J4:J202<TODAY()),--('Madine- Conversion'!G4:G202="Scoping"),'Madine- Conversion'!H4:H202)+SUMPRODUCT(--ISNUMBER('Madine- Conversion'!J4:J202),--('Madine- Conversion'!J4:J202<TODAY()),--('Madine- Conversion'!G4:G202="BOM Submission"),'Madine- Conversion'!H4:H202)+SUMPRODUCT(--ISNUMBER('Madine- Conversion'!J4:J202),--('Madine- Conversion'!J4:J202<TODAY()),--('Madine- Conversion'!G4:G202="Resubmission"),'Madine- Conversion'!H4:H202)+SUMPRODUCT(--ISNUMBER('Madine- Conversion'!J4:J202),--('Madine- Conversion'!J4:J202<TODAY()),--('Madine- Conversion'!G4:G202="Negotiation"),'Madine- Conversion'!H4:H202))+(SUMPRODUCT(--ISNUMBER('Zarrah-Conversion'!J3:J201),--('Zarrah-Conversion'!J3:J201<TODAY()),--('Zarrah-Conversion'!G3:G201="Opportunity Creation"),'Zarrah-Conversion'!H3:H201)+SUMPRODUCT(--ISNUMBER('Zarrah-Conversion'!J3:J201),--('Zarrah-Conversion'!J3:J201<TODAY()),--('Zarrah-Conversion'!G3:G201="Scoping"),'Zarrah-Conversion'!H3:H201)+SUMPRODUCT(--ISNUMBER('Zarrah-Conversion'!J3:J201),--('Zarrah-Conversion'!J3:J201<TODAY()),--('Zarrah-Conversion'!G3:G201="BOM Submission"),'Zarrah-Conversion'!H3:H201)+SUMPRODUCT(--ISNUMBER('Zarrah-Conversion'!J3:J201),--('Zarrah-Conversion'!J3:J201<TODAY()),--('Zarrah-Conversion'!G3:G201="Resubmission"),'Zarrah-Conversion'!H3:H201)+SUMPRODUCT(--ISNUMBER('Zarrah-Conversion'!J3:J201),--('Zarrah-Conversion'!J3:J201<TODAY()),--('Zarrah-Conversion'!G3:G201="Negotiation"),'Zarrah-Conversion'!H3:H201))+(SUMPRODUCT(--ISNUMBER('Home-Conversion'!J4:J202),--('Home-Conversion'!J4:J202<TODAY()),--('Home-Conversion'!G4:G202="Opportunity Creation"),'Home-Conversion'!H4:H202)+SUMPRODUCT(--ISNUMBER('Home-Conversion'!J4:J202),--('Home-Conversion'!J4:J202<TODAY()),--('Home-Conversion'!G4:G202="Scoping"),'Home-Conversion'!H4:H202)+SUMPRODUCT(--ISNUMBER('Home-Conversion'!J4:J202),--('Home-Conversion'!J4:J202<TODAY()),--('Home-Conversion'!G4:G202="BOM Submission"),'Home-Conversion'!H4:H202)+SUMPRODUCT(--ISNUMBER('Home-Conversion'!J4:J202),--('Home-Conversion'!J4:J202<TODAY()),--('Home-Conversion'!G4:G202="Resubmission"),'Home-Conversion'!H4:H202)+SUMPRODUCT(--ISNUMBER('Home-Conversion'!J4:J202),--('Home-Conversion'!J4:J202<TODAY()),--('Home-Conversion'!G4:G202="Negotiation"),'Home-Conversion'!H4:H202))+IF(RepPrefix4="",0,IFERROR((SUMPRODUCT(--ISNUMBER(INDIRECT("'"&RepPrefix4&"- Conversion'!J4:J202")),--(INDIRECT("'"&RepPrefix4&"- Conversion'!J4:J202")<TODAY()),--(INDIRECT("'"&RepPrefix4&"- Conversion'!G4:G202")="Opportunity Creation"),INDIRECT("'"&RepPrefix4&"- Conversion'!H4:H202"))+SUMPRODUCT(--ISNUMBER(INDIRECT("'"&RepPrefix4&"- Conversion'!J4:J202")),--(INDIRECT("'"&RepPrefix4&"- Conversion'!J4:J202")<TODAY()),--(INDIRECT("'"&RepPrefix4&"- Conversion'!G4:G202")="Scoping"),INDIRECT("'"&RepPrefix4&"- Conversion'!H4:H202"))+SUMPRODUCT(--ISNUMBER(INDIRECT("'"&RepPrefix4&"- Conversion'!J4:J202")),--(INDIRECT("'"&RepPrefix4&"- Conversion'!J4:J202")<TODAY()),--(INDIRECT("'"&RepPrefix4&"- Conversion'!G4:G202")="BOM Submission"),INDIRECT("'"&RepPrefix4&"- Conversion'!H4:H202"))+SUMPRODUCT(--ISNUMBER(INDIRECT("'"&RepPrefix4&"- Conversion'!J4:J202")),--(INDIRECT("'"&RepPrefix4&"- Conversion'!J4:J202")<TODAY()),--(INDIRECT("'"&RepPrefix4&"- Conversion'!G4:G202")="Resubmission"),INDIRECT("'"&RepPrefix4&"- Conversion'!H4:H202"))+SUMPRODUCT(--ISNUMBER(INDIRECT("'"&RepPrefix4&"- Conversion'!J4:J202")),--(INDIRECT("'"&RepPrefix4&"- Conversion'!J4:J202")<TODAY()),--(INDIRECT("'"&RepPrefix4&"- Conversion'!G4:G202")="Negotiation"),INDIRECT("'"&RepPrefix4&"- Conversion'!H4:H202"))),0))+IF(RepPrefix5="",0,IFERROR((SUMPRODUCT(--ISNUMBER(INDIRECT("'"&RepPrefix5&"- Conversion'!J4:J202")),--(INDIRECT("'"&RepPrefix5&"- Conversion'!J4:J202")<TODAY()),--(INDIRECT("'"&RepPrefix5&"- Conversion'!G4:G202")="Opportunity Creation"),INDIRECT("'"&RepPrefix5&"- Conversion'!H4:H202"))+SUMPRODUCT(--ISNUMBER(INDIRECT("'"&RepPrefix5&"- Conversion'!J4:J202")),--(INDIRECT("'"&RepPrefix5&"- Conversion'!J4:J202")<TODAY()),--(INDIRECT("'"&RepPrefix5&"- Conversion'!G4:G202")="Scoping"),INDIRECT("'"&RepPrefix5&"- Conversion'!H4:H202"))+SUMPRODUCT(--ISNUMBER(INDIRECT("'"&RepPrefix5&"- Conversion'!J4:J202")),--(INDIRECT("'"&RepPrefix5&"- Conversion'!J4:J202")<TODAY()),--(INDIRECT("'"&RepPrefix5&"- Conversion'!G4:G202")="BOM Submission"),INDIRECT("'"&RepPrefix5&"- Conversion'!H4:H202"))+SUMPRODUCT(--ISNUMBER(INDIRECT("'"&RepPrefix5&"- Conversion'!J4:J202")),--(INDIRECT("'"&RepPrefix5&"- Conversion'!J4:J202")<TODAY()),--(INDIRECT("'"&RepPrefix5&"- Conversion'!G4:G202")="Resubmission"),INDIRECT("'"&RepPrefix5&"- Conversion'!H4:H202"))+SUMPRODUCT(--ISNUMBER(INDIRECT("'"&RepPrefix5&"- Conversion'!J4:J202")),--(INDIRECT("'"&RepPrefix5&"- Conversion'!J4:J202")<TODAY()),--(INDIRECT("'"&RepPrefix5&"- Conversion'!G4:G202")="Negotiation"),INDIRECT("'"&RepPrefix5&"- Conversion'!H4:H202"))),0))+IF(RepPrefix6="",0,IFERROR((SUMPRODUCT(--ISNUMBER(INDIRECT("'"&RepPrefix6&"- Conversion'!J4:J202")),--(INDIRECT("'"&RepPrefix6&"- Conversion'!J4:J202")<TODAY()),--(INDIRECT("'"&RepPrefix6&"- Conversion'!G4:G202")="Opportunity Creation"),INDIRECT("'"&RepPrefix6&"- Conversion'!H4:H202"))+SUMPRODUCT(--ISNUMBER(INDIRECT("'"&RepPrefix6&"- Conversion'!J4:J202")),--(INDIRECT("'"&RepPrefix6&"- Conversion'!J4:J202")<TODAY()),--(INDIRECT("'"&RepPrefix6&"- Conversion'!G4:G202")="Scoping"),INDIRECT("'"&RepPrefix6&"- Conversion'!H4:H202"))+SUMPRODUCT(--ISNUMBER(INDIRECT("'"&RepPrefix6&"- Conversion'!J4:J202")),--(INDIRECT("'"&RepPrefix6&"- Conversion'!J4:J202")<TODAY()),--(INDIRECT("'"&RepPrefix6&"- Conversion'!G4:G202")="BOM Submission"),INDIRECT("'"&RepPrefix6&"- Conversion'!H4:H202"))+SUMPRODUCT(--ISNUMBER(INDIRECT("'"&RepPrefix6&"- Conversion'!J4:J202")),--(INDIRECT("'"&RepPrefix6&"- Conversion'!J4:J202")<TODAY()),--(INDIRECT("'"&RepPrefix6&"- Conversion'!G4:G202")="Resubmission"),INDIRECT("'"&RepPrefix6&"- Conversion'!H4:H202"))+SUMPRODUCT(--ISNUMBER(INDIRECT("'"&RepPrefix6&"- Conversion'!J4:J202")),--(INDIRECT("'"&RepPrefix6&"- Conversion'!J4:J202")<TODAY()),--(INDIRECT("'"&RepPrefix6&"- Conversion'!G4:G202")="Negotiation"),INDIRECT("'"&RepPrefix6&"- Conversion'!H4:H202"))),0)) | F20: =SUM('Per-Rep Detail'!C5:C10) | H20: =IFERROR(('Per-Rep Detail'!D11+'Per-Rep Detail'!E11+'Per-Rep Detail'!F11)/'Per-Rep Detail'!C11,0) | J20: =IFERROR((SUMIFS('Madine- Conversion'!H4:H202,'Madine- Conversion'!G4:G202,"Closed Lost")+SUMIFS('Zarrah-Conversion'!H3:H201,'Zarrah-Conversion'!G3:G201,"Closed Lost")+SUMIFS('Home-Conversion'!H4:H202,'Home-Conversion'!G4:G202,"Closed Lost")+IF(RepPrefix4="",0,IFERROR(SUMIFS(INDIRECT("'"&RepPrefix4&"- Conversion'!H4:H202"),INDIRECT("'"&RepPrefix4&"- Conversion'!G4:G202"),"Closed Lost"),0))+IF(RepPrefix5="",0,IFERROR(SUMIFS(INDIRECT("'"&RepPrefix5&"- Conversion'!H4:H202"),INDIRECT("'"&RepPrefix5&"- Conversion'!G4:G202"),"Closed Lost"),0))+IF(RepPrefix6="",0,IFERROR(SUMIFS(INDIRECT("'"&RepPrefix6&"- Conversion'!H4:H202"),INDIRECT("'"&RepPrefix6&"- Conversion'!G4:G202"),"Closed Lost"),0)))/(((SUMIFS('Madine- Conversion'!H4:H202,'Madine- Conversion'!G4:G202,"Closed Won")+SUMIFS('Zarrah-Conversion'!H3:H201,'Zarrah-Conversion'!G3:G201,"Closed Won")+SUMIFS('Home-Conversion'!H4:H202,'Home-Conversion'!G4:G202,"Closed Won")+IF(RepPrefix4="",0,IFERROR(SUMIFS(INDIRECT("'"&RepPrefix4&"- Conversion'!H4:H202"),INDIRECT("'"&RepPrefix4&"- Conversion'!G4:G202"),"Closed Won"),0))+IF(RepPrefix5="",0,IFERROR(SUMIFS(INDIRECT("'"&RepPrefix5&"- Conversion'!H4:H202"),INDIRECT("'"&RepPrefix5&"- Conversion'!G4:G202"),"Closed Won"),0))+IF(RepPrefix6="",0,IFERROR(SUMIFS(INDIRECT("'"&RepPrefix6&"- Conversion'!H4:H202"),INDIRECT("'"&RepPrefix6&"- Conversion'!G4:G202"),"Closed Won"),0))))+(SUMIFS('Madine- Conversion'!H4:H202,'Madine- Conversion'!G4:G202,"Closed Lost")+SUMIFS('Zarrah-Conversion'!H3:H201,'Zarrah-Conversion'!G3:G201,"Closed Lost")+SUMIFS('Home-Conversion'!H4:H202,'Home-Conversion'!G4:G202,"Closed Lost")+IF(RepPrefix4="",0,IFERROR(SUMIFS(INDIRECT("'"&RepPrefix4&"- Conversion'!H4:H202"),INDIRECT("'"&RepPrefix4&"- Conversion'!G4:G202"),"Closed Lost"),0))+IF(RepPrefix5="",0,IFERROR(SUMIFS(INDIRECT("'"&RepPrefix5&"- Conversion'!H4:H202"),INDIRECT("'"&RepPrefix5&"- Conversion'!G4:G202"),"Closed Lost"),0))+IF(RepPrefix6="",0,IFERROR(SUMIFS(INDIRECT("'"&RepPrefix6&"- Conversion'!H4:H202"),INDIRECT("'"&RepPrefix6&"- Conversion'!G4:G202"),"Closed Lost"),0)))),0) | L20: =IFERROR(F16/Quota,0)
B21: PAST-DUE DEALS | D21: PAST-DUE TCV | F21: COVERAGE LEADS | H21: COV→CONV % | J21: LOST RATE (₱) | L21: PIPE COVERAGE
B23: TOP DEALS — DRILL TO 'Pipeline Health' SHEET FOR FULL LIST
B24: ACCOUNT | E24: REP | F24: STAGE | H24: TCV | J24: GP | L24: CLOSING | N24: FLAG
B25: ='Pipeline Health'!B5 | E25: ='Pipeline Health'!C5 | F25: ='Pipeline Health'!D5 | H25: ='Pipeline Health'!E5 | J25: ='Pipeline Health'!F5 | L25: ='Pipeline Health'!G5 | N25: ='Pipeline Health'!H5
B26: ='Pipeline Health'!B6 | E26: ='Pipeline Health'!C6 | F26: ='Pipeline Health'!D6 | H26: ='Pipeline Health'!E6 | J26: ='Pipeline Health'!F6 | L26: ='Pipeline Health'!G6 | N26: ='Pipeline Health'!H6
B27: ='Pipeline Health'!B7 | E27: ='Pipeline Health'!C7 | F27: ='Pipeline Health'!D7 | H27: ='Pipeline Health'!E7 | J27: ='Pipeline Health'!F7 | L27: ='Pipeline Health'!G7 | N27: ='Pipeline Health'!H7
B28: ='Pipeline Health'!B8 | E28: ='Pipeline Health'!C8 | F28: ='Pipeline Health'!D8 | H28: ='Pipeline Health'!E8 | J28: ='Pipeline Health'!F8 | L28: ='Pipeline Health'!G8 | N28: ='Pipeline Health'!H8
B29: ='Pipeline Health'!B9 | E29: ='Pipeline Health'!C9 | F29: ='Pipeline Health'!D9 | H29: ='Pipeline Health'!E9 | J29: ='Pipeline Health'!F9 | L29: ='Pipeline Health'!G9 | N29: ='Pipeline Health'!H9
B30: ='Pipeline Health'!B10 | E30: ='Pipeline Health'!C10 | F30: ='Pipeline Health'!D10 | H30: ='Pipeline Health'!E10 | J30: ='Pipeline Health'!F10 | L30: ='Pipeline Health'!G10 | N30: ='Pipeline Health'!H10
B32: Live formulas · Edit source sheets to refresh · Inputs sheet drives quota/thresholds

Sheet Per-Rep Detail
B2: PER-REP DETAIL · LEADERBOARD
B4: REP | C4: Coverage Leads | D4: Active Opps | E4: Closed Won | F4: Closed Lost | G4: Win Rate | H4: TCV (Pipe+Won) | I4: GP (Pipe+Won) | J4: GP % | K4: Weighted Pipe | L4: Avg Deal Size | M4: Past-Due Deals
B5: =RepName1 | C5: =COUNTIFS('Madine- Coverage'!C4:C202,"<>") | D5: =(COUNTIFS('Madine- Conversion'!G4:G202,"<>Closed Lost",'Madine- Conversion'!G4:G202,"<>Closed Won",'Madine- Conversion'!G4:G202,"<>")) | E5: =COUNTIF('Madine- Conversion'!G4:G202,"Closed Won") | F5: =COUNTIF('Madine- Conversion'!G4:G202,"Closed Lost") | G5: =IFERROR(COUNTIF('Madine- Conversion'!G4:G202,"Closed Won")/(COUNTIF('Madine- Conversion'!G4:G202,"Closed Won")+COUNTIF('Madine- Conversion'!G4:G202,"Closed Lost")),0) | H5: =(SUMIFS('Madine- Conversion'!H4:H202,'Madine- Conversion'!G4:G202,"<>Closed Lost",'Madine- Conversion'!G4:G202,"<>")) | I5: =(SUMIFS('Madine- Conversion'!I4:I202,'Madine- Conversion'!G4:G202,"<>Closed Lost",'Madine- Conversion'!G4:G202,"<>")) | J5: =IFERROR(I5/H5,0) | K5: =((SUMIFS('Madine- Conversion'!H4:H202,'Madine- Conversion'!G4:G202,"Opportunity Creation")*0.1+SUMIFS('Madine- Conversion'!H4:H202,'Madine- Conversion'!G4:G202,"Scoping")*0.3+SUMIFS('Madine- Conversion'!H4:H202,'Madine- Conversion'!G4:G202,"BOM Submission")*0.5+SUMIFS('Madine- Conversion'!H4:H202,'Madine- Conversion'!G4:G202,"Resubmission")*0.7+SUMIFS('Madine- Conversion'!H4:H202,'Madine- Conversion'!G4:G202,"Negotiation")*0.9)) | L5: =IFERROR(H5/(D5+E5),0) | M5: =((SUMPRODUCT(--ISNUMBER('Madine- Conversion'!J4:J202),--('Madine- Conversion'!J4:J202<TODAY()),--('Madine- Conversion'!G4:G202="Opportunity Creation"))+SUMPRODUCT(--ISNUMBER('Madine- Conversion'!J4:J202),--('Madine- Conversion'!J4:J202<TODAY()),--('Madine- Conversion'!G4:G202="Scoping"))+SUMPRODUCT(--ISNUMBER('Madine- Conversion'!J4:J202),--('Madine- Conversion'!J4:J202<TODAY()),--('Madine- Conversion'!G4:G202="BOM Submission"))+SUMPRODUCT(--ISNUMBER('Madine- Conversion'!J4:J202),--('Madine- Conversion'!J4:J202<TODAY()),--('Madine- Conversion'!G4:G202="Resubmission"))+SUMPRODUCT(--ISNUMBER('Madine- Conversion'!J4:J202),--('Madine- Conversion'!J4:J202<TODAY()),--('Madine- Conversion'!G4:G202="Negotiation"))))
B6: =RepName2 | C6: =COUNTIFS('Zarrah- Coverage'!C4:C202,"<>") | D6: =(COUNTIFS('Zarrah-Conversion'!G3:G201,"<>Closed Lost",'Zarrah-Conversion'!G3:G201,"<>Closed Won",'Zarrah-Conversion'!G3:G201,"<>")) | E6: =COUNTIF('Zarrah-Conversion'!G3:G201,"Closed Won") | F6: =COUNTIF('Zarrah-Conversion'!G3:G201,"Closed Lost") | G6: =IFERROR(COUNTIF('Zarrah-Conversion'!G3:G201,"Closed Won")/(COUNTIF('Zarrah-Conversion'!G3:G201,"Closed Won")+COUNTIF('Zarrah-Conversion'!G3:G201,"Closed Lost")),0) | H6: =(SUMIFS('Zarrah-Conversion'!H3:H201,'Zarrah-Conversion'!G3:G201,"<>Closed Lost",'Zarrah-Conversion'!G3:G201,"<>")) | I6: =(SUMIFS('Zarrah-Conversion'!I3:I201,'Zarrah-Conversion'!G3:G201,"<>Closed Lost",'Zarrah-Conversion'!G3:G201,"<>")) | J6: =IFERROR(I6/H6,0) | K6: =((SUMIFS('Zarrah-Conversion'!H3:H201,'Zarrah-Conversion'!G3:G201,"Opportunity Creation")*0.1+SUMIFS('Zarrah-Conversion'!H3:H201,'Zarrah-Conversion'!G3:G201,"Scoping")*0.3+SUMIFS('Zarrah-Conversion'!H3:H201,'Zarrah-Conversion'!G3:G201,"BOM Submission")*0.5+SUMIFS('Zarrah-Conversion'!H3:H201,'Zarrah-Conversion'!G3:G201,"Resubmission")*0.7+SUMIFS('Zarrah-Conversion'!H3:H201,'Zarrah-Conversion'!G3:G201,"Negotiation")*0.9)) | L6: =IFERROR(H6/(D6+E6),0) | M6: =((SUMPRODUCT(--ISNUMBER('Zarrah-Conversion'!J3:J201),--('Zarrah-Conversion'!J3:J201<TODAY()),--('Zarrah-Conversion'!G3:G201="Opportunity Creation"))+SUMPRODUCT(--ISNUMBER('Zarrah-Conversion'!J3:J201),--('Zarrah-Conversion'!J3:J201<TODAY()),--('Zarrah-Conversion'!G3:G201="Scoping"))+SUMPRODUCT(--ISNUMBER('Zarrah-Conversion'!J3:J201),--('Zarrah-Conversion'!J3:J201<TODAY()),--('Zarrah-Conversion'!G3:G201="BOM Submission"))+SUMPRODUCT(--ISNUMBER('Zarrah-Conversion'!J3:J201),--('Zarrah-Conversion'!J3:J201<TODAY()),--('Zarrah-Conversion'!G3:G201="Resubmission"))+SUMPRODUCT(--ISNUMBER('Zarrah-Conversion'!J3:J201),--('Zarrah-Conversion'!J3:J201<TODAY()),--('Zarrah-Conversion'!G3:G201="Negotiation"))))
B7: =RepName3 | C7: =COUNTIFS('Home-Coverage'!C4:C202,"<>") | D7: =(COUNTIFS('Home-Conversion'!G4:G202,"<>Closed Lost",'Home-Conversion'!G4:G202,"<>Closed Won",'Home-Conversion'!G4:G202,"<>")) | E7: =COUNTIF('Home-Conversion'!G4:G202,"Closed Won") | F7: =COUNTIF('Home-Conversion'!G4:G202,"Closed Lost") | G7: =IFERROR(COUNTIF('Home-Conversion'!G4:G202,"Closed Won")/(COUNTIF('Home-Conversion'!G4:G202,"Closed Won")+COUNTIF('Home-Conversion'!G4:G202,"Closed Lost")),0) | H7: =(SUMIFS('Home-Conversion'!H4:H202,'Home-Conversion'!G4:G202,"<>Closed Lost",'Home-Conversion'!G4:G202,"<>")) | I7: =(SUMIFS('Home-Conversion'!I4:I202,'Home-Conversion'!G4:G202,"<>Closed Lost",'Home-Conversion'!G4:G202,"<>")) | J7: =IFERROR(I7/H7,0) | K7: =((SUMIFS('Home-Conversion'!H4:H202,'Home-Conversion'!G4:G202,"Opportunity Creation")*0.1+SUMIFS('Home-Conversion'!H4:H202,'Home-Conversion'!G4:G202,"Scoping")*0.3+SUMIFS('Home-Conversion'!H4:H202,'Home-Conversion'!G4:G202,"BOM Submission")*0.5+SUMIFS('Home-Conversion'!H4:H202,'Home-Conversion'!G4:G202,"Resubmission")*0.7+SUMIFS('Home-Conversion'!H4:H202,'Home-Conversion'!G4:G202,"Negotiation")*0.9)) | L7: =IFERROR(H7/(D7+E7),0) | M7: =((SUMPRODUCT(--ISNUMBER('Home-Conversion'!J4:J202),--('Home-Conversion'!J4:J202<TODAY()),--('Home-Conversion'!G4:G202="Opportunity Creation"))+SUMPRODUCT(--ISNUMBER('Home-Conversion'!J4:J202),--('Home-Conversion'!J4:J202<TODAY()),--('Home-Conversion'!G4:G202="Scoping"))+SUMPRODUCT(--ISNUMBER('Home-Conversion'!J4:J202),--('Home-Conversion'!J4:J202<TODAY()),--('Home-Conversion'!G4:G202="BOM Submission"))+SUMPRODUCT(--ISNUMBER('Home-Conversion'!J4:J202),--('Home-Conversion'!J4:J202<TODAY()),--('Home-Conversion'!G4:G202="Resubmission"))+SUMPRODUCT(--ISNUMBER('Home-Conversion'!J4:J202),--('Home-Conversion'!J4:J202<TODAY()),--('Home-Conversion'!G4:G202="Negotiation"))))
B8: =IF(RepPrefix4="","",RepName4) | C8: =IF(RepPrefix4="","",IF(RepPrefix4="",0,IFERROR(COUNTIFS(INDIRECT("'"&RepPrefix4&"- Coverage'!C4:C202"),"<>"),0))) | D8: =IF(RepPrefix4="","",(IF(RepPrefix4="",0,IFERROR(COUNTIFS(INDIRECT("'"&RepPrefix4&"- Conversion'!G4:G202"),"<>Closed Lost",INDIRECT("'"&RepPrefix4&"- Conversion'!G4:G202"),"<>Closed Won",INDIRECT("'"&RepPrefix4&"- Conversion'!G4:G202"),"<>"),0)))) | E8: =IF(RepPrefix4="","",IF(RepPrefix4="",0,IFERROR(COUNTIF(INDIRECT("'"&RepPrefix4&"- Conversion'!G4:G202"),"Closed Won"),0))) | F8: =IF(RepPrefix4="","",IF(RepPrefix4="",0,IFERROR(COUNTIF(INDIRECT("'"&RepPrefix4&"- Conversion'!G4:G202"),"Closed Lost"),0))) | G8: =IF(RepPrefix4="","",IFERROR(IF(RepPrefix4="",0,IFERROR(COUNTIF(INDIRECT("'"&RepPrefix4&"- Conversion'!G4:G202"),"Closed Won"),0))/(IF(RepPrefix4="",0,IFERROR(COUNTIF(INDIRECT("'"&RepPrefix4&"- Conversion'!G4:G202"),"Closed Won"),0))+IF(RepPrefix4="",0,IFERROR(COUNTIF(INDIRECT("'"&RepPrefix4&"- Conversion'!G4:G202"),"Closed Lost"),0))),0)) | H8: =IF(RepPrefix4="","",(IF(RepPrefix4="",0,IFERROR(SUMIFS(INDIRECT("'"&RepPrefix4&"- Conversion'!H4:H202"),INDIRECT("'"&RepPrefix4&"- Conversion'!G4:G202"),"<>Closed Lost",INDIRECT("'"&RepPrefix4&"- Conversion'!G4:G202"),"<>"),0)))) | I8: =IF(RepPrefix4="","",(IF(RepPrefix4="",0,IFERROR(SUMIFS(INDIRECT("'"&RepPrefix4&"- Conversion'!I4:I202"),INDIRECT("'"&RepPrefix4&"- Conversion'!G4:G202"),"<>Closed Lost",INDIRECT("'"&RepPrefix4&"- Conversion'!G4:G202"),"<>"),0)))) | J8: =IFERROR(I8/H8,0) | K8: =IF(RepPrefix4="","",((IF(RepPrefix4="",0,IFERROR(SUMIFS(INDIRECT("'"&RepPrefix4&"- Conversion'!H4:H202"),INDIRECT("'"&RepPrefix4&"- Conversion'!G4:G202"),"Opportunity Creation"),0))*0.1+IF(RepPrefix4="",0,IFERROR(SUMIFS(INDIRECT("'"&RepPrefix4&"- Conversion'!H4:H202"),INDIRECT("'"&RepPrefix4&"- Conversion'!G4:G202"),"Scoping"),0))*0.3+IF(RepPrefix4="",0,IFERROR(SUMIFS(INDIRECT("'"&RepPrefix4&"- Conversion'!H4:H202"),INDIRECT("'"&RepPrefix4&"- Conversion'!G4:G202"),"BOM Submission"),0))*0.5+IF(RepPrefix4="",0,IFERROR(SUMIFS(INDIRECT("'"&RepPrefix4&"- Conversion'!H4:H202"),INDIRECT("'"&RepPrefix4&"- Conversion'!G4:G202"),"Resubmission"),0))*0.7+IF(RepPrefix4="",0,IFERROR(SUMIFS(INDIRECT("'"&RepPrefix4&"- Conversion'!H4:H202"),INDIRECT("'"&RepPrefix4&"- Conversion'!G4:G202"),"Negotiation"),0))*0.9))) | L8: =IFERROR(H8/(D8+E8),0) | M8: =IF(RepPrefix4="","",(IF(RepPrefix4="",0,IFERROR((SUMPRODUCT(--ISNUMBER(INDIRECT("'"&RepPrefix4&"- Conversion'!J4:J202")),--(INDIRECT("'"&RepPrefix4&"- Conversion'!J4:J202")<TODAY()),--(INDIRECT("'"&RepPrefix4&"- Conversion'!G4:G202")="Opportunity Creation"))+SUMPRODUCT(--ISNUMBER(INDIRECT("'"&RepPrefix4&"- Conversion'!J4:J202")),--(INDIRECT("'"&RepPrefix4&"- Conversion'!J4:J202")<TODAY()),--(INDIRECT("'"&RepPrefix4&"- Conversion'!G4:G202")="Scoping"))+SUMPRODUCT(--ISNUMBER(INDIRECT("'"&RepPrefix4&"- Conversion'!J4:J202")),--(INDIRECT("'"&RepPrefix4&"- Conversion'!J4:J202")<TODAY()),--(INDIRECT("'"&RepPrefix4&"- Conversion'!G4:G202")="BOM Submission"))+SUMPRODUCT(--ISNUMBER(INDIRECT("'"&RepPrefix4&"- Conversion'!J4:J202")),--(INDIRECT("'"&RepPrefix4&"- Conversion'!J4:J202")<TODAY()),--(INDIRECT("'"&RepPrefix4&"- Conversion'!G4:G202")="Resubmission"))+SUMPRODUCT(--ISNUMBER(INDIRECT("'"&RepPrefix4&"- Conversion'!J4:J202")),--(INDIRECT("'"&RepPrefix4&"- Conversion'!J4:J202")<TODAY()),--(INDIRECT("'"&RepPrefix4&"- Conversion'!G4:G202")="Negotiation"))),0))))
B9: =IF(RepPrefix5="","",RepName5) | C9: =IF(RepPrefix5="","",IF(RepPrefix5="",0,IFERROR(COUNTIFS(INDIRECT("'"&RepPrefix5&"- Coverage'!C4:C202"),"<>"),0))) | D9: =IF(RepPrefix5="","",(IF(RepPrefix5="",0,IFERROR(COUNTIFS(INDIRECT("'"&RepPrefix5&"- Conversion'!G4:G202"),"<>Closed Lost",INDIRECT("'"&RepPrefix5&"- Conversion'!G4:G202"),"<>Closed Won",INDIRECT("'"&RepPrefix5&"- Conversion'!G4:G202"),"<>"),0)))) | E9: =IF(RepPrefix5="","",IF(RepPrefix5="",0,IFERROR(COUNTIF(INDIRECT("'"&RepPrefix5&"- Conversion'!G4:G202"),"Closed Won"),0))) | F9: =IF(RepPrefix5="","",IF(RepPrefix5="",0,IFERROR(COUNTIF(INDIRECT("'"&RepPrefix5&"- Conversion'!G4:G202"),"Closed Lost"),0))) | G9: =IF(RepPrefix5="","",IFERROR(IF(RepPrefix5="",0,IFERROR(COUNTIF(INDIRECT("'"&RepPrefix5&"- Conversion'!G4:G202"),"Closed Won"),0))/(IF(RepPrefix5="",0,IFERROR(COUNTIF(INDIRECT("'"&RepPrefix5&"- Conversion'!G4:G202"),"Closed Won"),0))+IF(RepPrefix5="",0,IFERROR(COUNTIF(INDIRECT("'"&RepPrefix5&"- Conversion'!G4:G202"),"Closed Lost"),0))),0)) | H9: =IF(RepPrefix5="","",(IF(RepPrefix5="",0,IFERROR(SUMIFS(INDIRECT("'"&RepPrefix5&"- Conversion'!H4:H202"),INDIRECT("'"&RepPrefix5&"- Conversion'!G4:G202"),"<>Closed Lost",INDIRECT("'"&RepPrefix5&"- Conversion'!G4:G202"),"<>"),0)))) | I9: =IF(RepPrefix5="","",(IF(RepPrefix5="",0,IFERROR(SUMIFS(INDIRECT("'"&RepPrefix5&"- Conversion'!I4:I202"),INDIRECT("'"&RepPrefix5&"- Conversion'!G4:G202"),"<>Closed Lost",INDIRECT("'"&RepPrefix5&"- Conversion'!G4:G202"),"<>"),0)))) | J9: =IFERROR(I9/H9,0) | K9: =IF(RepPrefix5="","",((IF(RepPrefix5="",0,IFERROR(SUMIFS(INDIRECT("'"&RepPrefix5&"- Conversion'!H4:H202"),INDIRECT("'"&RepPrefix5&"- Conversion'!G4:G202"),"Opportunity Creation"),0))*0.1+IF(RepPrefix5="",0,IFERROR(SUMIFS(INDIRECT("'"&RepPrefix5&"- Conversion'!H4:H202"),INDIRECT("'"&RepPrefix5&"- Conversion'!G4:G202"),"Scoping"),0))*0.3+IF(RepPrefix5="",0,IFERROR(SUMIFS(INDIRECT("'"&RepPrefix5&"- Conversion'!H4:H202"),INDIRECT("'"&RepPrefix5&"- Conversion'!G4:G202"),"BOM Submission"),0))*0.5+IF(RepPrefix5="",0,IFERROR(SUMIFS(INDIRECT("'"&RepPrefix5&"- Conversion'!H4:H202"),INDIRECT("'"&RepPrefix5&"- Conversion'!G4:G202"),"Resubmission"),0))*0.7+IF(RepPrefix5="",0,IFERROR(SUMIFS(INDIRECT("'"&RepPrefix5&"- Conversion'!H4:H202"),INDIRECT("'"&RepPrefix5&"- Conversion'!G4:G202"),"Negotiation"),0))*0.9))) | L9: =IFERROR(H9/(D9+E9),0) | M9: =IF(RepPrefix5="","",(IF(RepPrefix5="",0,IFERROR((SUMPRODUCT(--ISNUMBER(INDIRECT("'"&RepPrefix5&"- Conversion'!J4:J202")),--(INDIRECT("'"&RepPrefix5&"- Conversion'!J4:J202")<TODAY()),--(INDIRECT("'"&RepPrefix5&"- Conversion'!G4:G202")="Opportunity Creation"))+SUMPRODUCT(--ISNUMBER(INDIRECT("'"&RepPrefix5&"- Conversion'!J4:J202")),--(INDIRECT("'"&RepPrefix5&"- Conversion'!J4:J202")<TODAY()),--(INDIRECT("'"&RepPrefix5&"- Conversion'!G4:G202")="Scoping"))+SUMPRODUCT(--ISNUMBER(INDIRECT("'"&RepPrefix5&"- Conversion'!J4:J202")),--(INDIRECT("'"&RepPrefix5&"- Conversion'!J4:J202")<TODAY()),--(INDIRECT("'"&RepPrefix5&"- Conversion'!G4:G202")="BOM Submission"))+SUMPRODUCT(--ISNUMBER(INDIRECT("'"&RepPrefix5&"- Conversion'!J4:J202")),--(INDIRECT("'"&RepPrefix5&"- Conversion'!J4:J202")<TODAY()),--(INDIRECT("'"&RepPrefix5&"- Conversion'!G4:G202")="Resubmission"))+SUMPRODUCT(--ISNUMBER(INDIRECT("'"&RepPrefix5&"- Conversion'!J4:J202")),--(INDIRECT("'"&RepPrefix5&"- Conversion'!J4:J202")<TODAY()),--(INDIRECT("'"&RepPrefix5&"- Conversion'!G4:G202")="Negotiation"))),0))))
B10: =IF(RepPrefix6="","",RepName6) | C10: =IF(RepPrefix6="","",IF(RepPrefix6="",0,IFERROR(COUNTIFS(INDIRECT("'"&RepPrefix6&"- Coverage'!C4:C202"),"<>"),0))) | D10: =IF(RepPrefix6="","",(IF(RepPrefix6="",0,IFERROR(COUNTIFS(INDIRECT("'"&RepPrefix6&"- Conversion'!G4:G202"),"<>Closed Lost",INDIRECT("'"&RepPrefix6&"- Conversion'!G4:G202"),"<>Closed Won",INDIRECT("'"&RepPrefix6&"- Conversion'!G4:G202"),"<>"),0)))) | E10: =IF(RepPrefix6="","",IF(RepPrefix6="",0,IFERROR(COUNTIF(INDIRECT("'"&RepPrefix6&"- Conversion'!G4:G202"),"Closed Won"),0))) | F10: =IF(RepPrefix6="","",IF(RepPrefix6="",0,IFERROR(COUNTIF(INDIRECT("'"&RepPrefix6&"- Conversion'!G4:G202"),"Closed Lost"),0))) | G10: =IF(RepPrefix6="","",IFERROR(IF(RepPrefix6="",0,IFERROR(COUNTIF(INDIRECT("'"&RepPrefix6&"- Conversion'!G4:G202"),"Closed Won"),0))/(IF(RepPrefix6="",0,IFERROR(COUNTIF(INDIRECT("'"&RepPrefix6&"- Conversion'!G4:G202"),"Closed Won"),0))+IF(RepPrefix6="",0,IFERROR(COUNTIF(INDIRECT("'"&RepPrefix6&"- Conversion'!G4:G202"),"Closed Lost"),0))),0)) | H10: =IF(RepPrefix6="","",(IF(RepPrefix6="",0,IFERROR(SUMIFS(INDIRECT("'"&RepPrefix6&"- Conversion'!H4:H202"),INDIRECT("'"&RepPrefix6&"- Conversion'!G4:G202"),"<>Closed Lost",INDIRECT("'"&RepPrefix6&"- Conversion'!G4:G202"),"<>"),0)))) | I10: =IF(RepPrefix6="","",(IF(RepPrefix6="",0,IFERROR(SUMIFS(INDIRECT("'"&RepPrefix6&"- Conversion'!I4:I202"),INDIRECT("'"&RepPrefix6&"- Conversion'!G4:G202"),"<>Closed Lost",INDIRECT("'"&RepPrefix6&"- Conversion'!G4:G202"),"<>"),0)))) | J10: =IFERROR(I10/H10,0) | K10: =IF(RepPrefix6="","",((IF(RepPrefix6="",0,IFERROR(SUMIFS(INDIRECT("'"&RepPrefix6&"- Conversion'!H4:H202"),INDIRECT("'"&RepPrefix6&"- Conversion'!G4:G202"),"Opportunity Creation"),0))*0.1+IF(RepPrefix6="",0,IFERROR(SUMIFS(INDIRECT("'"&RepPrefix6&"- Conversion'!H4:H202"),INDIRECT("'"&RepPrefix6&"- Conversion'!G4:G202"),"Scoping"),0))*0.3+IF(RepPrefix6="",0,IFERROR(SUMIFS(INDIRECT("'"&RepPrefix6&"- Conversion'!H4:H202"),INDIRECT("'"&RepPrefix6&"- Conversion'!G4:G202"),"BOM Submission"),0))*0.5+IF(RepPrefix6="",0,IFERROR(SUMIFS(INDIRECT("'"&RepPrefix6&"- Conversion'!H4:H202"),INDIRECT("'"&RepPrefix6&"- Conversion'!G4:G202"),"Resubmission"),0))*0.7+IF(RepPrefix6="",0,IFERROR(SUMIFS(INDIRECT("'"&RepPrefix6&"- Conversion'!H4:H202"),INDIRECT("'"&RepPrefix6&"- Conversion'!G4:G202"),"Negotiation"),0))*0.9))) | L10: =IFERROR(H10/(D10+E10),0) | M10: =IF(RepPrefix6="","",(IF(RepPrefix6="",0,IFERROR((SUMPRODUCT(--ISNUMBER(INDIRECT("'"&RepPrefix6&"- Conversion'!J4:J202")),--(INDIRECT("'"&RepPrefix6&"- Conversion'!J4:J202")<TODAY()),--(INDIRECT("'"&RepPrefix6&"- Conversion'!G4:G202")="Opportunity Creation"))+SUMPRODUCT(--ISNUMBER(INDIRECT("'"&RepPrefix6&"- Conversion'!J4:J202")),--(INDIRECT("'"&RepPrefix6&"- Conversion'!J4:J202")<TODAY()),--(INDIRECT("'"&RepPrefix6&"- Conversion'!G4:G202")="Scoping"))+SUMPRODUCT(--ISNUMBER(INDIRECT("'"&RepPrefix6&"- Conversion'!J4:J202")),--(INDIRECT("'"&RepPrefix6&"- Conversion'!J4:J202")<TODAY()),--(INDIRECT("'"&RepPrefix6&"- Conversion'!G4:G202")="BOM Submission"))+SUMPRODUCT(--ISNUMBER(INDIRECT("'"&RepPrefix6&"- Conversion'!J4:J202")),--(INDIRECT("'"&RepPrefix6&"- Conversion'!J4:J202")<TODAY()),--(INDIRECT("'"&RepPrefix6&"- Conversion'!G4:G202")="Resubmission"))+SUMPRODUCT(--ISNUMBER(INDIRECT("'"&RepPrefix6&"- Conversion'!J4:J202")),--(INDIRECT("'"&RepPrefix6&"- Conversion'!J4:J202")<TODAY()),--(INDIRECT("'"&RepPrefix6&"- Conversion'!G4:G202")="Negotiation"))),0))))
B11: TOTAL | C11: =SUM(C5:C10) | D11: =SUM(D5:D10) | E11: =SUM(E5:E10) | F11: =SUM(F5:F10) | G11: =IFERROR(SUM(E5:E10)/(SUM(E5:E10)+SUM(F5:F10)),0) | H11: =SUM(H5:H10) | I11: =SUM(I5:I10) | J11: =IFERROR(I11/H11,0) | K11: =SUM(K5:K10) | L11: =IFERROR(H11/(D11+E11),0) | M11: =SUM(M5:M10)

Sheet Stage Funnel
B2: STAGE FUNNEL · PIPELINE BY STAGE
B4: STAGE | C4: Probability | D4: =RepName1&" #" | E4: =RepName2&" #" | F4: =RepName3&" #" | G4: =IF(RepPrefix4="","—",RepName4&" #") | H4: =IF(RepPrefix5="","—",RepName5&" #") | I4: =IF(RepPrefix6="","—",RepName6&" #") | J4: Total Opps | K4: Total TCV | L4: Weighted
B5: Opportunity Creation | C5: 0.1 | D5: =COUNTIF('Madine- Conversion'!G4:G202,"Opportunity Creation") | E5: =COUNTIF('Zarrah-Conversion'!G3:G201,"Opportunity Creation") | F5: =COUNTIF('Home-Conversion'!G4:G202,"Opportunity Creation") | G5: =IF(RepPrefix4="","",IF(RepPrefix4="",0,IFERROR(COUNTIF(INDIRECT("'"&RepPrefix4&"- Conversion'!G4:G202"),"Opportunity Creation"),0))) | H5: =IF(RepPrefix5="","",IF(RepPrefix5="",0,IFERROR(COUNTIF(INDIRECT("'"&RepPrefix5&"- Conversion'!G4:G202"),"Opportunity Creation"),0))) | I5: =IF(RepPrefix6="","",IF(RepPrefix6="",0,IFERROR(COUNTIF(INDIRECT("'"&RepPrefix6&"- Conversion'!G4:G202"),"Opportunity Creation"),0))) | J5: =SUM(D5:I5) | K5: =SUMIFS('Madine- Conversion'!H4:H202,'Madine- Conversion'!G4:G202,"Opportunity Creation")+SUMIFS('Zarrah-Conversion'!H3:H201,'Zarrah-Conversion'!G3:G201,"Opportunity Creation")+SUMIFS('Home-Conversion'!H4:H202,'Home-Conversion'!G4:G202,"Opportunity Creation")+IF(RepPrefix4="",0,IFERROR(SUMIFS(INDIRECT("'"&RepPrefix4&"- Conversion'!H4:H202"),INDIRECT("'"&RepPrefix4&"- Conversion'!G4:G202"),"Opportunity Creation"),0))+IF(RepPrefix5="",0,IFERROR(SUMIFS(INDIRECT("'"&RepPrefix5&"- Conversion'!H4:H202"),INDIRECT("'"&RepPrefix5&"- Conversion'!G4:G202"),"Opportunity Creation"),0))+IF(RepPrefix6="",0,IFERROR(SUMIFS(INDIRECT("'"&RepPrefix6&"- Conversion'!H4:H202"),INDIRECT("'"&RepPrefix6&"- Conversion'!G4:G202"),"Opportunity Creation"),0)) | L5: =K5*C5
B6: Scoping | C6: 0.3 | D6: =COUNTIF('Madine- Conversion'!G4:G202,"Scoping") | E6: =COUNTIF('Zarrah-Conversion'!G3:G201,"Scoping") | F6: =COUNTIF('Home-Conversion'!G4:G202,"Scoping") | G6: =IF(RepPrefix4="","",IF(RepPrefix4="",0,IFERROR(COUNTIF(INDIRECT("'"&RepPrefix4&"- Conversion'!G4:G202"),"Scoping"),0))) | H6: =IF(RepPrefix5="","",IF(RepPrefix5="",0,IFERROR(COUNTIF(INDIRECT("'"&RepPrefix5&"- Conversion'!G4:G202"),"Scoping"),0))) | I6: =IF(RepPrefix6="","",IF(RepPrefix6="",0,IFERROR(COUNTIF(INDIRECT("'"&RepPrefix6&"- Conversion'!G4:G202"),"Scoping"),0))) | J6: =SUM(D6:I6) | K6: =SUMIFS('Madine- Conversion'!H4:H202,'Madine- Conversion'!G4:G202,"Scoping")+SUMIFS('Zarrah-Conversion'!H3:H201,'Zarrah-Conversion'!G3:G201,"Scoping")+SUMIFS('Home-Conversion'!H4:H202,'Home-Conversion'!G4:G202,"Scoping")+IF(RepPrefix4="",0,IFERROR(SUMIFS(INDIRECT("'"&RepPrefix4&"- Conversion'!H4:H202"),INDIRECT("'"&RepPrefix4&"- Conversion'!G4:G202"),"Scoping"),0))+IF(RepPrefix5="",0,IFERROR(SUMIFS(INDIRECT("'"&RepPrefix5&"- Conversion'!H4:H202"),INDIRECT("'"&RepPrefix5&"- Conversion'!G4:G202"),"Scoping"),0))+IF(RepPrefix6="",0,IFERROR(SUMIFS(INDIRECT("'"&RepPrefix6&"- Conversion'!H4:H202"),INDIRECT("'"&RepPrefix6&"- Conversion'!G4:G202"),"Scoping"),0)) | L6: =K6*C6
B7: BOM Submission | C7: 0.5 | D7: =COUNTIF('Madine- Conversion'!G4:G202,"BOM Submission") | E7: =COUNTIF('Zarrah-Conversion'!G3:G201,"BOM Submission") | F7: =COUNTIF('Home-Conversion'!G4:G202,"BOM Submission") | G7: =IF(RepPrefix4="","",IF(RepPrefix4="",0,IFERROR(COUNTIF(INDIRECT("'"&RepPrefix4&"- Conversion'!G4:G202"),"BOM Submission"),0))) | H7: =IF(RepPrefix5="","",IF(RepPrefix5="",0,IFERROR(COUNTIF(INDIRECT("'"&RepPrefix5&"- Conversion'!G4:G202"),"BOM Submission"),0))) | I7: =IF(RepPrefix6="","",IF(RepPrefix6="",0,IFERROR(COUNTIF(INDIRECT("'"&RepPrefix6&"- Conversion'!G4:G202"),"BOM Submission"),0))) | J7: =SUM(D7:I7) | K7: =SUMIFS('Madine- Conversion'!H4:H202,'Madine- Conversion'!G4:G202,"BOM Submission")+SUMIFS('Zarrah-Conversion'!H3:H201,'Zarrah-Conversion'!G3:G201,"BOM Submission")+SUMIFS('Home-Conversion'!H4:H202,'Home-Conversion'!G4:G202,"BOM Submission")+IF(RepPrefix4="",0,IFERROR(SUMIFS(INDIRECT("'"&RepPrefix4&"- Conversion'!H4:H202"),INDIRECT("'"&RepPrefix4&"- Conversion'!G4:G202"),"BOM Submission"),0))+IF(RepPrefix5="",0,IFERROR(SUMIFS(INDIRECT("'"&RepPrefix5&"- Conversion'!H4:H202"),INDIRECT("'"&RepPrefix5&"- Conversion'!G4:G202"),"BOM Submission"),0))+IF(RepPrefix6="",0,IFERROR(SUMIFS(INDIRECT("'"&RepPrefix6&"- Conversion'!H4:H202"),INDIRECT("'"&RepPrefix6&"- Conversion'!G4:G202"),"BOM Submission"),0)) | L7: =K7*C7
B8: Resubmission | C8: 0.7 | D8: =COUNTIF('Madine- Conversion'!G4:G202,"Resubmission") | E8: =COUNTIF('Zarrah-Conversion'!G3:G201,"Resubmission") | F8: =COUNTIF('Home-Conversion'!G4:G202,"Resubmission") | G8: =IF(RepPrefix4="","",IF(RepPrefix4="",0,IFERROR(COUNTIF(INDIRECT("'"&RepPrefix4&"- Conversion'!G4:G202"),"Resubmission"),0))) | H8: =IF(RepPrefix5="","",IF(RepPrefix5="",0,IFERROR(COUNTIF(INDIRECT("'"&RepPrefix5&"- Conversion'!G4:G202"),"Resubmission"),0))) | I8: =IF(RepPrefix6="","",IF(RepPrefix6="",0,IFERROR(COUNTIF(INDIRECT("'"&RepPrefix6&"- Conversion'!G4:G202"),"Resubmission"),0))) | J8: =SUM(D8:I8) | K8: =SUMIFS('Madine- Conversion'!H4:H202,'Madine- Conversion'!G4:G202,"Resubmission")+SUMIFS('Zarrah-Conversion'!H3:H201,'Zarrah-Conversion'!G3:G201,"Resubmission")+SUMIFS('Home-Conversion'!H4:H202,'Home-Conversion'!G4:G202,"Resubmission")+IF(RepPrefix4="",0,IFERROR(SUMIFS(INDIRECT("'"&RepPrefix4&"- Conversion'!H4:H202"),INDIRECT("'"&RepPrefix4&"- Conversion'!G4:G202"),"Resubmission"),0))+IF(RepPrefix5="",0,IFERROR(SUMIFS(INDIRECT("'"&RepPrefix5&"- Conversion'!H4:H202"),INDIRECT("'"&RepPrefix5&"- Conversion'!G4:G202"),"Resubmission"),0))+IF(RepPrefix6="",0,IFERROR(SUMIFS(INDIRECT("'"&RepPrefix6&"- Conversion'!H4:H202"),INDIRECT("'"&RepPrefix6&"- Conversion'!G4:G202"),"Resubmission"),0)) | L8: =K8*C8
B9: Negotiation | C9: 0.9 | D9: =COUNTIF('Madine- Conversion'!G4:G202,"Negotiation") | E9: =COUNTIF('Zarrah-Conversion'!G3:G201,"Negotiation") | F9: =COUNTIF('Home-Conversion'!G4:G202,"Negotiation") | G9: =IF(RepPrefix4="","",IF(RepPrefix4="",0,IFERROR(COUNTIF(INDIRECT("'"&RepPrefix4&"- Conversion'!G4:G202"),"Negotiation"),0))) | H9: =IF(RepPrefix5="","",IF(RepPrefix5="",0,IFERROR(COUNTIF(INDIRECT("'"&RepPrefix5&"- Conversion'!G4:G202"),"Negotiation"),0))) | I9: =IF(RepPrefix6="","",IF(RepPrefix6="",0,IFERROR(COUNTIF(INDIRECT("'"&RepPrefix6&"- Conversion'!G4:G202"),"Negotiation"),0))) | J9: =SUM(D9:I9) | K9: =SUMIFS('Madine- Conversion'!H4:H202,'Madine- Conversion'!G4:G202,"Negotiation")+SUMIFS('Zarrah-Conversion'!H3:H201,'Zarrah-Conversion'!G3:G201,"Negotiation")+SUMIFS('Home-Conversion'!H4:H202,'Home-Conversion'!G4:G202,"Negotiation")+IF(RepPrefix4="",0,IFERROR(SUMIFS(INDIRECT("'"&RepPrefix4&"- Conversion'!H4:H202"),INDIRECT("'"&RepPrefix4&"- Conversion'!G4:G202"),"Negotiation"),0))+IF(RepPrefix5="",0,IFERROR(SUMIFS(INDIRECT("'"&RepPrefix5&"- Conversion'!H4:H202"),INDIRECT("'"&RepPrefix5&"- Conversion'!G4:G202"),"Negotiation"),0))+IF(RepPrefix6="",0,IFERROR(SUMIFS(INDIRECT("'"&RepPrefix6&"- Conversion'!H4:H202"),INDIRECT("'"&RepPrefix6&"- Conversion'!G4:G202"),"Negotiation"),0)) | L9: =K9*C9
B10: Closed Won | C10: 1 | D10: =COUNTIF('Madine- Conversion'!G4:G202,"Closed Won") | E10: =COUNTIF('Zarrah-Conversion'!G3:G201,"Closed Won") | F10: =COUNTIF('Home-Conversion'!G4:G202,"Closed Won") | G10: =IF(RepPrefix4="","",IF(RepPrefix4="",0,IFERROR(COUNTIF(INDIRECT("'"&RepPrefix4&"- Conversion'!G4:G202"),"Closed Won"),0))) | H10: =IF(RepPrefix5="","",IF(RepPrefix5="",0,IFERROR(COUNTIF(INDIRECT("'"&RepPrefix5&"- Conversion'!G4:G202"),"Closed Won"),0))) | I10: =IF(RepPrefix6="","",IF(RepPrefix6="",0,IFERROR(COUNTIF(INDIRECT("'"&RepPrefix6&"- Conversion'!G4:G202"),"Closed Won"),0))) | J10: =SUM(D10:I10) | K10: =SUMIFS('Madine- Conversion'!H4:H202,'Madine- Conversion'!G4:G202,"Closed Won")+SUMIFS('Zarrah-Conversion'!H3:H201,'Zarrah-Conversion'!G3:G201,"Closed Won")+SUMIFS('Home-Conversion'!H4:H202,'Home-Conversion'!G4:G202,"Closed Won")+IF(RepPrefix4="",0,IFERROR(SUMIFS(INDIRECT("'"&RepPrefix4&"- Conversion'!H4:H202"),INDIRECT("'"&RepPrefix4&"- Conversion'!G4:G202"),"Closed Won"),0))+IF(RepPrefix5="",0,IFERROR(SUMIFS(INDIRECT("'"&RepPrefix5&"- Conversion'!H4:H202"),INDIRECT("'"&RepPrefix5&"- Conversion'!G4:G202"),"Closed Won"),0))+IF(RepPrefix6="",0,IFERROR(SUMIFS(INDIRECT("'"&RepPrefix6&"- Conversion'!H4:H202"),INDIRECT("'"&RepPrefix6&"- Conversion'!G4:G202"),"Closed Won"),0)) | L10: =K10*C10
B11: Closed Lost | C11: 0 | D11: =COUNTIF('Madine- Conversion'!G4:G202,"Closed Lost") | E11: =COUNTIF('Zarrah-Conversion'!G3:G201,"Closed Lost") | F11: =COUNTIF('Home-Conversion'!G4:G202,"Closed Lost") | G11: =IF(RepPrefix4="","",IF(RepPrefix4="",0,IFERROR(COUNTIF(INDIRECT("'"&RepPrefix4&"- Conversion'!G4:G202"),"Closed Lost"),0))) | H11: =IF(RepPrefix5="","",IF(RepPrefix5="",0,IFERROR(COUNTIF(INDIRECT("'"&RepPrefix5&"- Conversion'!G4:G202"),"Closed Lost"),0))) | I11: =IF(RepPrefix6="","",IF(RepPrefix6="",0,IFERROR(COUNTIF(INDIRECT("'"&RepPrefix6&"- Conversion'!G4:G202"),"Closed Lost"),0))) | J11: =SUM(D11:I11) | K11: =SUMIFS('Madine- Conversion'!H4:H202,'Madine- Conversion'!G4:G202,"Closed Lost")+SUMIFS('Zarrah-Conversion'!H3:H201,'Zarrah-Conversion'!G3:G201,"Closed Lost")+SUMIFS('Home-Conversion'!H4:H202,'Home-Conversion'!G4:G202,"Closed Lost")+IF(RepPrefix4="",0,IFERROR(SUMIFS(INDIRECT("'"&RepPrefix4&"- Conversion'!H4:H202"),INDIRECT("'"&RepPrefix4&"- Conversion'!G4:G202"),"Closed Lost"),0))+IF(RepPrefix5="",0,IFERROR(SUMIFS(INDIRECT("'"&RepPrefix5&"- Conversion'!H4:H202"),INDIRECT("'"&RepPrefix5&"- Conversion'!G4:G202"),"Closed Lost"),0))+IF(RepPrefix6="",0,IFERROR(SUMIFS(INDIRECT("'"&RepPrefix6&"- Conversion'!H4:H202"),INDIRECT("'"&RepPrefix6&"- Conversion'!G4:G202"),"Closed Lost"),0)) | L11: =K11*C11
B12: PIPELINE TOTAL (excl. Lost) | D12: =SUM(D5:D10) | E12: =SUM(E5:E10) | F12: =SUM(F5:F10) | G12: =SUM(G5:G10) | H12: =SUM(H5:H10) | I12: =SUM(I5:I10) | J12: =SUM(J5:J10) | K12: =SUM(K5:K10) | L12: =SUM(L5:L10)

Sheet Pipeline Health
B2: PIPELINE HEALTH · TOP DEALS & AT-RISK
B4: ACCOUNT | C4: REP | D4: STAGE | E4: TCV | F4: GP | G4: CLOSING | H4: FLAG | I4: NOTES
B5: =IFERROR(INDEX('Home-Conversion'!D4:D202,MATCH(LARGE('Home-Conversion'!T4:T202,1),'Home-Conversion'!T4:T202,0)),"") | C5: =IF(B5="","",RepName3) | D5: =IFERROR(INDEX('Home-Conversion'!G4:G202,MATCH(LARGE('Home-Conversion'!T4:T202,1),'Home-Conversion'!T4:T202,0)),"") | E5: =IFERROR(LARGE('Home-Conversion'!T4:T202,1),"") | F5: =IFERROR(INDEX('Home-Conversion'!I4:I202,MATCH(LARGE('Home-Conversion'!T4:T202,1),'Home-Conversion'!T4:T202,0)),"") | G5: =IFERROR(INDEX('Home-Conversion'!J4:J202,MATCH(LARGE('Home-Conversion'!T4:T202,1),'Home-Conversion'!T4:T202,0)),"") | H5: =IF(B5="","",IF(D5="Closed Won","✓ WON",IF(D5="Closed Lost","✗ LOST",IF(AND(G5<>"",ISNUMBER(G5),G5<TODAY()),"⚠ PAST DUE",IF(G5="","◔ NO DATE",IF(D5="Negotiation","● NEGOTIATING","○ ACTIVE"))))))
B6: =IFERROR(INDEX('Home-Conversion'!D4:D202,MATCH(LARGE('Home-Conversion'!T4:T202,2),'Home-Conversion'!T4:T202,0)),"") | C6: =IF(B6="","",RepName3) | D6: =IFERROR(INDEX('Home-Conversion'!G4:G202,MATCH(LARGE('Home-Conversion'!T4:T202,2),'Home-Conversion'!T4:T202,0)),"") | E6: =IFERROR(LARGE('Home-Conversion'!T4:T202,2),"") | F6: =IFERROR(INDEX('Home-Conversion'!I4:I202,MATCH(LARGE('Home-Conversion'!T4:T202,2),'Home-Conversion'!T4:T202,0)),"") | G6: =IFERROR(INDEX('Home-Conversion'!J4:J202,MATCH(LARGE('Home-Conversion'!T4:T202,2),'Home-Conversion'!T4:T202,0)),"") | H6: =IF(B6="","",IF(D6="Closed Won","✓ WON",IF(D6="Closed Lost","✗ LOST",IF(AND(G6<>"",ISNUMBER(G6),G6<TODAY()),"⚠ PAST DUE",IF(G6="","◔ NO DATE",IF(D6="Negotiation","● NEGOTIATING","○ ACTIVE"))))))
B7: =IFERROR(INDEX('Home-Conversion'!D4:D202,MATCH(LARGE('Home-Conversion'!T4:T202,3),'Home-Conversion'!T4:T202,0)),"") | C7: =IF(B7="","",RepName3) | D7: =IFERROR(INDEX('Home-Conversion'!G4:G202,MATCH(LARGE('Home-Conversion'!T4:T202,3),'Home-Conversion'!T4:T202,0)),"") | E7: =IFERROR(LARGE('Home-Conversion'!T4:T202,3),"") | F7: =IFERROR(INDEX('Home-Conversion'!I4:I202,MATCH(LARGE('Home-Conversion'!T4:T202,3),'Home-Conversion'!T4:T202,0)),"") | G7: =IFERROR(INDEX('Home-Conversion'!J4:J202,MATCH(LARGE('Home-Conversion'!T4:T202,3),'Home-Conversion'!T4:T202,0)),"") | H7: =IF(B7="","",IF(D7="Closed Won","✓ WON",IF(D7="Closed Lost","✗ LOST",IF(AND(G7<>"",ISNUMBER(G7),G7<TODAY()),"⚠ PAST DUE",IF(G7="","◔ NO DATE",IF(D7="Negotiation","● NEGOTIATING","○ ACTIVE"))))))
B8: =IFERROR(INDEX('Home-Conversion'!D4:D202,MATCH(LARGE('Home-Conversion'!T4:T202,4),'Home-Conversion'!T4:T202,0)),"") | C8: =IF(B8="","",RepName3) | D8: =IFERROR(INDEX('Home-Conversion'!G4:G202,MATCH(LARGE('Home-Conversion'!T4:T202,4),'Home-Conversion'!T4:T202,0)),"") | E8: =IFERROR(LARGE('Home-Conversion'!T4:T202,4),"") | F8: =IFERROR(INDEX('Home-Conversion'!I4:I202,MATCH(LARGE('Home-Conversion'!T4:T202,4),'Home-Conversion'!T4:T202,0)),"") | G8: =IFERROR(INDEX('Home-Conversion'!J4:J202,MATCH(LARGE('Home-Conversion'!T4:T202,4),'Home-Conversion'!T4:T202,0)),"") | H8: =IF(B8="","",IF(D8="Closed Won","✓ WON",IF(D8="Closed Lost","✗ LOST",IF(AND(G8<>"",ISNUMBER(G8),G8<TODAY()),"⚠ PAST DUE",IF(G8="","◔ NO DATE",IF(D8="Negotiation","● NEGOTIATING","○ ACTIVE"))))))
B9: =IFERROR(INDEX('Home-Conversion'!D4:D202,MATCH(LARGE('Home-Conversion'!T4:T202,5),'Home-Conversion'!T4:T202,0)),"") | C9: =IF(B9="","",RepName3) | D9: =IFERROR(INDEX('Home-Conversion'!G4:G202,MATCH(LARGE('Home-Conversion'!T4:T202,5),'Home-Conversion'!T4:T202,0)),"") | E9: =IFERROR(LARGE('Home-Conversion'!T4:T202,5),"") | F9: =IFERROR(INDEX('Home-Conversion'!I4:I202,MATCH(LARGE('Home-Conversion'!T4:T202,5),'Home-Conversion'!T4:T202,0)),"") | G9: =IFERROR(INDEX('Home-Conversion'!J4:J202,MATCH(LARGE('Home-Conversion'!T4:T202,5),'Home-Conversion'!T4:T202,0)),"") | H9: =IF(B9="","",IF(D9="Closed Won","✓ WON",IF(D9="Closed Lost","✗ LOST",IF(AND(G9<>"",ISNUMBER(G9),G9<TODAY()),"⚠ PAST DUE",IF(G9="","◔ NO DATE",IF(D9="Negotiation","● NEGOTIATING","○ ACTIVE"))))))
B10: =IFERROR(INDEX('Home-Conversion'!D4:D202,MATCH(LARGE('Home-Conversion'!T4:T202,6),'Home-Conversion'!T4:T202,0)),"") | C10: =IF(B10="","",RepName3) | D10: =IFERROR(INDEX('Home-Conversion'!G4:G202,MATCH(LARGE('Home-Conversion'!T4:T202,6),'Home-Conversion'!T4:T202,0)),"") | E10: =IFERROR(LARGE('Home-Conversion'!T4:T202,6),"") | F10: =IFERROR(INDEX('Home-Conversion'!I4:I202,MATCH(LARGE('Home-Conversion'!T4:T202,6),'Home-Conversion'!T4:T202,0)),"") | G10: =IFERROR(INDEX('Home-Conversion'!J4:J202,MATCH(LARGE('Home-Conversion'!T4:T202,6),'Home-Conversion'!T4:T202,0)),"") | H10: =IF(B10="","",IF(D10="Closed Won","✓ WON",IF(D10="Closed Lost","✗ LOST",IF(AND(G10<>"",ISNUMBER(G10),G10<TODAY()),"⚠ PAST DUE",IF(G10="","◔ NO DATE",IF(D10="Negotiation","● NEGOTIATING","○ ACTIVE"))))))
B11: =IFERROR(INDEX('Home-Conversion'!D4:D202,MATCH(LARGE('Home-Conversion'!T4:T202,7),'Home-Conversion'!T4:T202,0)),"") | C11: =IF(B11="","",RepName3) | D11: =IFERROR(INDEX('Home-Conversion'!G4:G202,MATCH(LARGE('Home-Conversion'!T4:T202,7),'Home-Conversion'!T4:T202,0)),"") | E11: =IFERROR(LARGE('Home-Conversion'!T4:T202,7),"") | F11: =IFERROR(INDEX('Home-Conversion'!I4:I202,MATCH(LARGE('Home-Conversion'!T4:T202,7),'Home-Conversion'!T4:T202,0)),"") | G11: =IFERROR(INDEX('Home-Conversion'!J4:J202,MATCH(LARGE('Home-Conversion'!T4:T202,7),'Home-Conversion'!T4:T202,0)),"") | H11: =IF(B11="","",IF(D11="Closed Won","✓ WON",IF(D11="Closed Lost","✗ LOST",IF(AND(G11<>"",ISNUMBER(G11),G11<TODAY()),"⚠ PAST DUE",IF(G11="","◔ NO DATE",IF(D11="Negotiation","● NEGOTIATING","○ ACTIVE"))))))
B12: =IFERROR(INDEX('Home-Conversion'!D4:D202,MATCH(LARGE('Home-Conversion'!T4:T202,8),'Home-Conversion'!T4:T202,0)),"") | C12: =IF(B12="","",RepName3) | D12: =IFERROR(INDEX('Home-Conversion'!G4:G202,MATCH(LARGE('Home-Conversion'!T4:T202,8),'Home-Conversion'!T4:T202,0)),"") | E12: =IFERROR(LARGE('Home-Conversion'!T4:T202,8),"") | F12: =IFERROR(INDEX('Home-Conversion'!I4:I202,MATCH(LARGE('Home-Conversion'!T4:T202,8),'Home-Conversion'!T4:T202,0)),"") | G12: =IFERROR(INDEX('Home-Conversion'!J4:J202,MATCH(LARGE('Home-Conversion'!T4:T202,8),'Home-Conversion'!T4:T202,0)),"") | H12: =IF(B12="","",IF(D12="Closed Won","✓ WON",IF(D12="Closed Lost","✗ LOST",IF(AND(G12<>"",ISNUMBER(G12),G12<TODAY()),"⚠ PAST DUE",IF(G12="","◔ NO DATE",IF(D12="Negotiation","● NEGOTIATING","○ ACTIVE"))))))
B13: =IFERROR(INDEX('Zarrah-Conversion'!D3:D201,MATCH(LARGE('Zarrah-Conversion'!T3:T201,1),'Zarrah-Conversion'!T3:T201,0)),"") | C13: =IF(B13="","",RepName2) | D13: =IFERROR(INDEX('Zarrah-Conversion'!G3:G201,MATCH(LARGE('Zarrah-Conversion'!T3:T201,1),'Zarrah-Conversion'!T3:T201,0)),"") | E13: =IFERROR(LARGE('Zarrah-Conversion'!T3:T201,1),"") | F13: =IFERROR(INDEX('Zarrah-Conversion'!I3:I201,MATCH(LARGE('Zarrah-Conversion'!T3:T201,1),'Zarrah-Conversion'!T3:T201,0)),"") | G13: =IFERROR(INDEX('Zarrah-Conversion'!J3:J201,MATCH(LARGE('Zarrah-Conversion'!T3:T201,1),'Zarrah-Conversion'!T3:T201,0)),"") | H13: =IF(B13="","",IF(D13="Closed Won","✓ WON",IF(D13="Closed Lost","✗ LOST",IF(AND(G13<>"",ISNUMBER(G13),G13<TODAY()),"⚠ PAST DUE",IF(G13="","◔ NO DATE",IF(D13="Negotiation","● NEGOTIATING","○ ACTIVE"))))))
B14: =IFERROR(INDEX('Zarrah-Conversion'!D3:D201,MATCH(LARGE('Zarrah-Conversion'!T3:T201,2),'Zarrah-Conversion'!T3:T201,0)),"") | C14: =IF(B14="","",RepName2) | D14: =IFERROR(INDEX('Zarrah-Conversion'!G3:G201,MATCH(LARGE('Zarrah-Conversion'!T3:T201,2),'Zarrah-Conversion'!T3:T201,0)),"") | E14: =IFERROR(LARGE('Zarrah-Conversion'!T3:T201,2),"") | F14: =IFERROR(INDEX('Zarrah-Conversion'!I3:I201,MATCH(LARGE('Zarrah-Conversion'!T3:T201,2),'Zarrah-Conversion'!T3:T201,0)),"") | G14: =IFERROR(INDEX('Zarrah-Conversion'!J3:J201,MATCH(LARGE('Zarrah-Conversion'!T3:T201,2),'Zarrah-Conversion'!T3:T201,0)),"") | H14: =IF(B14="","",IF(D14="Closed Won","✓ WON",IF(D14="Closed Lost","✗ LOST",IF(AND(G14<>"",ISNUMBER(G14),G14<TODAY()),"⚠ PAST DUE",IF(G14="","◔ NO DATE",IF(D14="Negotiation","● NEGOTIATING","○ ACTIVE"))))))
B15: =IFERROR(INDEX('Zarrah-Conversion'!D3:D201,MATCH(LARGE('Zarrah-Conversion'!T3:T201,3),'Zarrah-Conversion'!T3:T201,0)),"") | C15: =IF(B15="","",RepName2) | D15: =IFERROR(INDEX('Zarrah-Conversion'!G3:G201,MATCH(LARGE('Zarrah-Conversion'!T3:T201,3),'Zarrah-Conversion'!T3:T201,0)),"") | E15: =IFERROR(LARGE('Zarrah-Conversion'!T3:T201,3),"") | F15: =IFERROR(INDEX('Zarrah-Conversion'!I3:I201,MATCH(LARGE('Zarrah-Conversion'!T3:T201,3),'Zarrah-Conversion'!T3:T201,0)),"") | G15: =IFERROR(INDEX('Zarrah-Conversion'!J3:J201,MATCH(LARGE('Zarrah-Conversion'!T3:T201,3),'Zarrah-Conversion'!T3:T201,0)),"") | H15: =IF(B15="","",IF(D15="Closed Won","✓ WON",IF(D15="Closed Lost","✗ LOST",IF(AND(G15<>"",ISNUMBER(G15),G15<TODAY()),"⚠ PAST DUE",IF(G15="","◔ NO DATE",IF(D15="Negotiation","● NEGOTIATING","○ ACTIVE"))))))
B16: =IFERROR(INDEX('Zarrah-Conversion'!D3:D201,MATCH(LARGE('Zarrah-Conversion'!T3:T201,4),'Zarrah-Conversion'!T3:T201,0)),"") | C16: =IF(B16="","",RepName2) | D16: =IFERROR(INDEX('Zarrah-Conversion'!G3:G201,MATCH(LARGE('Zarrah-Conversion'!T3:T201,4),'Zarrah-Conversion'!T3:T201,0)),"") | E16: =IFERROR(LARGE('Zarrah-Conversion'!T3:T201,4),"") | F16: =IFERROR(INDEX('Zarrah-Conversion'!I3:I201,MATCH(LARGE('Zarrah-Conversion'!T3:T201,4),'Zarrah-Conversion'!T3:T201,0)),"") | G16: =IFERROR(INDEX('Zarrah-Conversion'!J3:J201,MATCH(LARGE('Zarrah-Conversion'!T3:T201,4),'Zarrah-Conversion'!T3:T201,0)),"") | H16: =IF(B16="","",IF(D16="Closed Won","✓ WON",IF(D16="Closed Lost","✗ LOST",IF(AND(G16<>"",ISNUMBER(G16),G16<TODAY()),"⚠ PAST DUE",IF(G16="","◔ NO DATE",IF(D16="Negotiation","● NEGOTIATING","○ ACTIVE"))))))
B17: =IFERROR(INDEX('Zarrah-Conversion'!D3:D201,MATCH(LARGE('Zarrah-Conversion'!T3:T201,5),'Zarrah-Conversion'!T3:T201,0)),"") | C17: =IF(B17="","",RepName2) | D17: =IFERROR(INDEX('Zarrah-Conversion'!G3:G201,MATCH(LARGE('Zarrah-Conversion'!T3:T201,5),'Zarrah-Conversion'!T3:T201,0)),"") | E17: =IFERROR(LARGE('Zarrah-Conversion'!T3:T201,5),"") | F17: =IFERROR(INDEX('Zarrah-Conversion'!I3:I201,MATCH(LARGE('Zarrah-Conversion'!T3:T201,5),'Zarrah-Conversion'!T3:T201,0)),"") | G17: =IFERROR(INDEX('Zarrah-Conversion'!J3:J201,MATCH(LARGE('Zarrah-Conversion'!T3:T201,5),'Zarrah-Conversion'!T3:T201,0)),"") | H17: =IF(B17="","",IF(D17="Closed Won","✓ WON",IF(D17="Closed Lost","✗ LOST",IF(AND(G17<>"",ISNUMBER(G17),G17<TODAY()),"⚠ PAST DUE",IF(G17="","◔ NO DATE",IF(D17="Negotiation","● NEGOTIATING","○ ACTIVE"))))))
B18: =IFERROR(INDEX('Zarrah-Conversion'!D3:D201,MATCH(LARGE('Zarrah-Conversion'!T3:T201,6),'Zarrah-Conversion'!T3:T201,0)),"") | C18: =IF(B18="","",RepName2) | D18: =IFERROR(INDEX('Zarrah-Conversion'!G3:G201,MATCH(LARGE('Zarrah-Conversion'!T3:T201,6),'Zarrah-Conversion'!T3:T201,0)),"") | E18: =IFERROR(LARGE('Zarrah-Conversion'!T3:T201,6),"") | F18: =IFERROR(INDEX('Zarrah-Conversion'!I3:I201,MATCH(LARGE('Zarrah-Conversion'!T3:T201,6),'Zarrah-Conversion'!T3:T201,0)),"") | G18: =IFERROR(INDEX('Zarrah-Conversion'!J3:J201,MATCH(LARGE('Zarrah-Conversion'!T3:T201,6),'Zarrah-Conversion'!T3:T201,0)),"") | H18: =IF(B18="","",IF(D18="Closed Won","✓ WON",IF(D18="Closed Lost","✗ LOST",IF(AND(G18<>"",ISNUMBER(G18),G18<TODAY()),"⚠ PAST DUE",IF(G18="","◔ NO DATE",IF(D18="Negotiation","● NEGOTIATING","○ ACTIVE"))))))
B19: =IFERROR(INDEX('Zarrah-Conversion'!D3:D201,MATCH(LARGE('Zarrah-Conversion'!T3:T201,7),'Zarrah-Conversion'!T3:T201,0)),"") | C19: =IF(B19="","",RepName2) | D19: =IFERROR(INDEX('Zarrah-Conversion'!G3:G201,MATCH(LARGE('Zarrah-Conversion'!T3:T201,7),'Zarrah-Conversion'!T3:T201,0)),"") | E19: =IFERROR(LARGE('Zarrah-Conversion'!T3:T201,7),"") | F19: =IFERROR(INDEX('Zarrah-Conversion'!I3:I201,MATCH(LARGE('Zarrah-Conversion'!T3:T201,7),'Zarrah-Conversion'!T3:T201,0)),"") | G19: =IFERROR(INDEX('Zarrah-Conversion'!J3:J201,MATCH(LARGE('Zarrah-Conversion'!T3:T201,7),'Zarrah-Conversion'!T3:T201,0)),"") | H19: =IF(B19="","",IF(D19="Closed Won","✓ WON",IF(D19="Closed Lost","✗ LOST",IF(AND(G19<>"",ISNUMBER(G19),G19<TODAY()),"⚠ PAST DUE",IF(G19="","◔ NO DATE",IF(D19="Negotiation","● NEGOTIATING","○ ACTIVE"))))))
B20: =IFERROR(INDEX('Zarrah-Conversion'!D3:D201,MATCH(LARGE('Zarrah-Conversion'!T3:T201,8),'Zarrah-Conversion'!T3:T201,0)),"") | C20: =IF(B20="","",RepName2) | D20: =IFERROR(INDEX('Zarrah-Conversion'!G3:G201,MATCH(LARGE('Zarrah-Conversion'!T3:T201,8),'Zarrah-Conversion'!T3:T201,0)),"") | E20: =IFERROR(LARGE('Zarrah-Conversion'!T3:T201,8),"") | F20: =IFERROR(INDEX('Zarrah-Conversion'!I3:I201,MATCH(LARGE('Zarrah-Conversion'!T3:T201,8),'Zarrah-Conversion'!T3:T201,0)),"") | G20: =IFERROR(INDEX('Zarrah-Conversion'!J3:J201,MATCH(LARGE('Zarrah-Conversion'!T3:T201,8),'Zarrah-Conversion'!T3:T201,0)),"") | H20: =IF(B20="","",IF(D20="Closed Won","✓ WON",IF(D20="Closed Lost","✗ LOST",IF(AND(G20<>"",ISNUMBER(G20),G20<TODAY()),"⚠ PAST DUE",IF(G20="","◔ NO DATE",IF(D20="Negotiation","● NEGOTIATING","○ ACTIVE"))))))
B21: =IFERROR(INDEX('Madine- Conversion'!D4:D202,MATCH(LARGE('Madine- Conversion'!T4:T202,1),'Madine- Conversion'!T4:T202,0)),"") | C21: =IF(B21="","",RepName1) | D21: =IFERROR(INDEX('Madine- Conversion'!G4:G202,MATCH(LARGE('Madine- Conversion'!T4:T202,1),'Madine- Conversion'!T4:T202,0)),"") | E21: =IFERROR(LARGE('Madine- Conversion'!T4:T202,1),"") | F21: =IFERROR(INDEX('Madine- Conversion'!I4:I202,MATCH(LARGE('Madine- Conversion'!T4:T202,1),'Madine- Conversion'!T4:T202,0)),"") | G21: =IFERROR(INDEX('Madine- Conversion'!J4:J202,MATCH(LARGE('Madine- Conversion'!T4:T202,1),'Madine- Conversion'!T4:T202,0)),"") | H21: =IF(B21="","",IF(D21="Closed Won","✓ WON",IF(D21="Closed Lost","✗ LOST",IF(AND(G21<>"",ISNUMBER(G21),G21<TODAY()),"⚠ PAST DUE",IF(G21="","◔ NO DATE",IF(D21="Negotiation","● NEGOTIATING","○ ACTIVE"))))))
B22: =IFERROR(INDEX('Madine- Conversion'!D4:D202,MATCH(LARGE('Madine- Conversion'!T4:T202,2),'Madine- Conversion'!T4:T202,0)),"") | C22: =IF(B22="","",RepName1) | D22: =IFERROR(INDEX('Madine- Conversion'!G4:G202,MATCH(LARGE('Madine- Conversion'!T4:T202,2),'Madine- Conversion'!T4:T202,0)),"") | E22: =IFERROR(LARGE('Madine- Conversion'!T4:T202,2),"") | F22: =IFERROR(INDEX('Madine- Conversion'!I4:I202,MATCH(LARGE('Madine- Conversion'!T4:T202,2),'Madine- Conversion'!T4:T202,0)),"") | G22: =IFERROR(INDEX('Madine- Conversion'!J4:J202,MATCH(LARGE('Madine- Conversion'!T4:T202,2),'Madine- Conversion'!T4:T202,0)),"") | H22: =IF(B22="","",IF(D22="Closed Won","✓ WON",IF(D22="Closed Lost","✗ LOST",IF(AND(G22<>"",ISNUMBER(G22),G22<TODAY()),"⚠ PAST DUE",IF(G22="","◔ NO DATE",IF(D22="Negotiation","● NEGOTIATING","○ ACTIVE"))))))
B23: =IFERROR(INDEX('Madine- Conversion'!D4:D202,MATCH(LARGE('Madine- Conversion'!T4:T202,3),'Madine- Conversion'!T4:T202,0)),"") | C23: =IF(B23="","",RepName1) | D23: =IFERROR(INDEX('Madine- Conversion'!G4:G202,MATCH(LARGE('Madine- Conversion'!T4:T202,3),'Madine- Conversion'!T4:T202,0)),"") | E23: =IFERROR(LARGE('Madine- Conversion'!T4:T202,3),"") | F23: =IFERROR(INDEX('Madine- Conversion'!I4:I202,MATCH(LARGE('Madine- Conversion'!T4:T202,3),'Madine- Conversion'!T4:T202,0)),"") | G23: =IFERROR(INDEX('Madine- Conversion'!J4:J202,MATCH(LARGE('Madine- Conversion'!T4:T202,3),'Madine- Conversion'!T4:T202,0)),"") | H23: =IF(B23="","",IF(D23="Closed Won","✓ WON",IF(D23="Closed Lost","✗ LOST",IF(AND(G23<>"",ISNUMBER(G23),G23<TODAY()),"⚠ PAST DUE",IF(G23="","◔ NO DATE",IF(D23="Negotiation","● NEGOTIATING","○ ACTIVE"))))))
B24: =IFERROR(INDEX('Madine- Conversion'!D4:D202,MATCH(LARGE('Madine- Conversion'!T4:T202,4),'Madine- Conversion'!T4:T202,0)),"") | C24: =IF(B24="","",RepName1) | D24: =IFERROR(INDEX('Madine- Conversion'!G4:G202,MATCH(LARGE('Madine- Conversion'!T4:T202,4),'Madine- Conversion'!T4:T202,0)),"") | E24: =IFERROR(LARGE('Madine- Conversion'!T4:T202,4),"") | F24: =IFERROR(INDEX('Madine- Conversion'!I4:I202,MATCH(LARGE('Madine- Conversion'!T4:T202,4),'Madine- Conversion'!T4:T202,0)),"") | G24: =IFERROR(INDEX('Madine- Conversion'!J4:J202,MATCH(LARGE('Madine- Conversion'!T4:T202,4),'Madine- Conversion'!T4:T202,0)),"") | H24: =IF(B24="","",IF(D24="Closed Won","✓ WON",IF(D24="Closed Lost","✗ LOST",IF(AND(G24<>"",ISNUMBER(G24),G24<TODAY()),"⚠ PAST DUE",IF(G24="","◔ NO DATE",IF(D24="Negotiation","● NEGOTIATING","○ ACTIVE"))))))
B25: =IFERROR(INDEX('Madine- Conversion'!D4:D202,MATCH(LARGE('Madine- Conversion'!T4:T202,5),'Madine- Conversion'!T4:T202,0)),"") | C25: =IF(B25="","",RepName1) | D25: =IFERROR(INDEX('Madine- Conversion'!G4:G202,MATCH(LARGE('Madine- Conversion'!T4:T202,5),'Madine- Conversion'!T4:T202,0)),"") | E25: =IFERROR(LARGE('Madine- Conversion'!T4:T202,5),"") | F25: =IFERROR(INDEX('Madine- Conversion'!I4:I202,MATCH(LARGE('Madine- Conversion'!T4:T202,5),'Madine- Conversion'!T4:T202,0)),"") | G25: =IFERROR(INDEX('Madine- Conversion'!J4:J202,MATCH(LARGE('Madine- Conversion'!T4:T202,5),'Madine- Conversion'!T4:T202,0)),"") | H25: =IF(B25="","",IF(D25="Closed Won","✓ WON",IF(D25="Closed Lost","✗ LOST",IF(AND(G25<>"",ISNUMBER(G25),G25<TODAY()),"⚠ PAST DUE",IF(G25="","◔ NO DATE",IF(D25="Negotiation","● NEGOTIATING","○ ACTIVE"))))))
B26: =IFERROR(INDEX('Madine- Conversion'!D4:D202,MATCH(LARGE('Madine- Conversion'!T4:T202,6),'Madine- Conversion'!T4:T202,0)),"") | C26: =IF(B26="","",RepName1) | D26: =IFERROR(INDEX('Madine- Conversion'!G4:G202,MATCH(LARGE('Madine- Conversion'!T4:T202,6),'Madine- Conversion'!T4:T202,0)),"") | E26: =IFERROR(LARGE('Madine- Conversion'!T4:T202,6),"") | F26: =IFERROR(INDEX('Madine- Conversion'!I4:I202,MATCH(LARGE('Madine- Conversion'!T4:T202,6),'Madine- Conversion'!T4:T202,0)),"") | G26: =IFERROR(INDEX('Madine- Conversion'!J4:J202,MATCH(LARGE('Madine- Conversion'!T4:T202,6),'Madine- Conversion'!T4:T202,0)),"") | H26: =IF(B26="","",IF(D26="Closed Won","✓ WON",IF(D26="Closed Lost","✗ LOST",IF(AND(G26<>"",ISNUMBER(G26),G26<TODAY()),"⚠ PAST DUE",IF(G26="","◔ NO DATE",IF(D26="Negotiation","● NEGOTIATING","○ ACTIVE"))))))
B27: =IFERROR(INDEX('Madine- Conversion'!D4:D202,MATCH(LARGE('Madine- Conversion'!T4:T202,7),'Madine- Conversion'!T4:T202,0)),"") | C27: =IF(B27="","",RepName1) | D27: =IFERROR(INDEX('Madine- Conversion'!G4:G202,MATCH(LARGE('Madine- Conversion'!T4:T202,7),'Madine- Conversion'!T4:T202,0)),"") | E27: =IFERROR(LARGE('Madine- Conversion'!T4:T202,7),"") | F27: =IFERROR(INDEX('Madine- Conversion'!I4:I202,MATCH(LARGE('Madine- Conversion'!T4:T202,7),'Madine- Conversion'!T4:T202,0)),"") | G27: =IFERROR(INDEX('Madine- Conversion'!J4:J202,MATCH(LARGE('Madine- Conversion'!T4:T202,7),'Madine- Conversion'!T4:T202,0)),"") | H27: =IF(B27="","",IF(D27="Closed Won","✓ WON",IF(D27="Closed Lost","✗ LOST",IF(AND(G27<>"",ISNUMBER(G27),G27<TODAY()),"⚠ PAST DUE",IF(G27="","◔ NO DATE",IF(D27="Negotiation","● NEGOTIATING","○ ACTIVE"))))))
B28: =IFERROR(INDEX('Madine- Conversion'!D4:D202,MATCH(LARGE('Madine- Conversion'!T4:T202,8),'Madine- Conversion'!T4:T202,0)),"") | C28: =IF(B28="","",RepName1) | D28: =IFERROR(INDEX('Madine- Conversion'!G4:G202,MATCH(LARGE('Madine- Conversion'!T4:T202,8),'Madine- Conversion'!T4:T202,0)),"") | E28: =IFERROR(LARGE('Madine- Conversion'!T4:T202,8),"") | F28: =IFERROR(INDEX('Madine- Conversion'!I4:I202,MATCH(LARGE('Madine- Conversion'!T4:T202,8),'Madine- Conversion'!T4:T202,0)),"") | G28: =IFERROR(INDEX('Madine- Conversion'!J4:J202,MATCH(LARGE('Madine- Conversion'!T4:T202,8),'Madine- Conversion'!T4:T202,0)),"") | H28: =IF(B28="","",IF(D28="Closed Won","✓ WON",IF(D28="Closed Lost","✗ LOST",IF(AND(G28<>"",ISNUMBER(G28),G28<TODAY()),"⚠ PAST DUE",IF(G28="","◔ NO DATE",IF(D28="Negotiation","● NEGOTIATING","○ ACTIVE"))))))
B29: =IFERROR(INDEX(INDIRECT("'"&RepPrefix4&"- Conversion'!D4:D202"),MATCH(LARGE(INDIRECT("'"&RepPrefix4&"- Conversion'!T4:T202"),1),INDIRECT("'"&RepPrefix4&"- Conversion'!T4:T202"),0)),"") | C29: =IF(OR(RepPrefix4="",B29=""),"",RepName4) | D29: =IFERROR(INDEX(INDIRECT("'"&RepPrefix4&"- Conversion'!G4:G202"),MATCH(LARGE(INDIRECT("'"&RepPrefix4&"- Conversion'!T4:T202"),1),INDIRECT("'"&RepPrefix4&"- Conversion'!T4:T202"),0)),"") | E29: =IFERROR(LARGE(INDIRECT("'"&RepPrefix4&"- Conversion'!T4:T202"),1),"") | F29: =IFERROR(INDEX(INDIRECT("'"&RepPrefix4&"- Conversion'!I4:I202"),MATCH(LARGE(INDIRECT("'"&RepPrefix4&"- Conversion'!T4:T202"),1),INDIRECT("'"&RepPrefix4&"- Conversion'!T4:T202"),0)),"") | G29: =IFERROR(INDEX(INDIRECT("'"&RepPrefix4&"- Conversion'!J4:J202"),MATCH(LARGE(INDIRECT("'"&RepPrefix4&"- Conversion'!T4:T202"),1),INDIRECT("'"&RepPrefix4&"- Conversion'!T4:T202"),0)),"") | H29: =IF(B29="","",IF(D29="Closed Won","✓ WON",IF(D29="Closed Lost","✗ LOST",IF(AND(G29<>"",ISNUMBER(G29),G29<TODAY()),"⚠ PAST DUE",IF(G29="","◔ NO DATE",IF(D29="Negotiation","● NEGOTIATING","○ ACTIVE"))))))
B30: =IFERROR(INDEX(INDIRECT("'"&RepPrefix4&"- Conversion'!D4:D202"),MATCH(LARGE(INDIRECT("'"&RepPrefix4&"- Conversion'!T4:T202"),2),INDIRECT("'"&RepPrefix4&"- Conversion'!T4:T202"),0)),"") | C30: =IF(OR(RepPrefix4="",B30=""),"",RepName4) | D30: =IFERROR(INDEX(INDIRECT("'"&RepPrefix4&"- Conversion'!G4:G202"),MATCH(LARGE(INDIRECT("'"&RepPrefix4&"- Conversion'!T4:T202"),2),INDIRECT("'"&RepPrefix4&"- Conversion'!T4:T202"),0)),"") | E30: =IFERROR(LARGE(INDIRECT("'"&RepPrefix4&"- Conversion'!T4:T202"),2),"") | F30: =IFERROR(INDEX(INDIRECT("'"&RepPrefix4&"- Conversion'!I4:I202"),MATCH(LARGE(INDIRECT("'"&RepPrefix4&"- Conversion'!T4:T202"),2),INDIRECT("'"&RepPrefix4&"- Conversion'!T4:T202"),0)),"") | G30: =IFERROR(INDEX(INDIRECT("'"&RepPrefix4&"- Conversion'!J4:J202"),MATCH(LARGE(INDIRECT("'"&RepPrefix4&"- Conversion'!T4:T202"),2),INDIRECT("'"&RepPrefix4&"- Conversion'!T4:T202"),0)),"") | H30: =IF(B30="","",IF(D30="Closed Won","✓ WON",IF(D30="Closed Lost","✗ LOST",IF(AND(G30<>"",ISNUMBER(G30),G30<TODAY()),"⚠ PAST DUE",IF(G30="","◔ NO DATE",IF(D30="Negotiation","● NEGOTIATING","○ ACTIVE"))))))
B31: =IFERROR(INDEX(INDIRECT("'"&RepPrefix4&"- Conversion'!D4:D202"),MATCH(LARGE(INDIRECT("'"&RepPrefix4&"- Conversion'!T4:T202"),3),INDIRECT("'"&RepPrefix4&"- Conversion'!T4:T202"),0)),"") | C31: =IF(OR(RepPrefix4="",B31=""),"",RepName4) | D31: =IFERROR(INDEX(INDIRECT("'"&RepPrefix4&"- Conversion'!G4:G202"),MATCH(LARGE(INDIRECT("'"&RepPrefix4&"- Conversion'!T4:T202"),3),INDIRECT("'"&RepPrefix4&"- Conversion'!T4:T202"),0)),"") | E31: =IFERROR(LARGE(INDIRECT("'"&RepPrefix4&"- Conversion'!T4:T202"),3),"") | F31: =IFERROR(INDEX(INDIRECT("'"&RepPrefix4&"- Conversion'!I4:I202"),MATCH(LARGE(INDIRECT("'"&RepPrefix4&"- Conversion'!T4:T202"),3),INDIRECT("'"&RepPrefix4&"- Conversion'!T4:T202"),0)),"") | G31: =IFERROR(INDEX(INDIRECT("'"&RepPrefix4&"- Conversion'!J4:J202"),MATCH(LARGE(INDIRECT("'"&RepPrefix4&"- Conversion'!T4:T202"),3),INDIRECT("'"&RepPrefix4&"- Conversion'!T4:T202"),0)),"") | H31: =IF(B31="","",IF(D31="Closed Won","✓ WON",IF(D31="Closed Lost","✗ LOST",IF(AND(G31<>"",ISNUMBER(G31),G31<TODAY()),"⚠ PAST DUE",IF(G31="","◔ NO DATE",IF(D31="Negotiation","● NEGOTIATING","○ ACTIVE"))))))
B32: =IFERROR(INDEX(INDIRECT("'"&RepPrefix4&"- Conversion'!D4:D202"),MATCH(LARGE(INDIRECT("'"&RepPrefix4&"- Conversion'!T4:T202"),4),INDIRECT("'"&RepPrefix4&"- Conversion'!T4:T202"),0)),"") | C32: =IF(OR(RepPrefix4="",B32=""),"",RepName4) | D32: =IFERROR(INDEX(INDIRECT("'"&RepPrefix4&"- Conversion'!G4:G202"),MATCH(LARGE(INDIRECT("'"&RepPrefix4&"- Conversion'!T4:T202"),4),INDIRECT("'"&RepPrefix4&"- Conversion'!T4:T202"),0)),"") | E32: =IFERROR(LARGE(INDIRECT("'"&RepPrefix4&"- Conversion'!T4:T202"),4),"") | F32: =IFERROR(INDEX(INDIRECT("'"&RepPrefix4&"- Conversion'!I4:I202"),MATCH(LARGE(INDIRECT("'"&RepPrefix4&"- Conversion'!T4:T202"),4),INDIRECT("'"&RepPrefix4&"- Conversion'!T4:T202"),0)),"") | G32: =IFERROR(INDEX(INDIRECT("'"&RepPrefix4&"- Conversion'!J4:J202"),MATCH(LARGE(INDIRECT("'"&RepPrefix4&"- Conversion'!T4:T202"),4),INDIRECT("'"&RepPrefix4&"- Conversion'!T4:T202"),0)),"") | H32: =IF(B32="","",IF(D32="Closed Won","✓ WON",IF(D32="Closed Lost","✗ LOST",IF(AND(G32<>"",ISNUMBER(G32),G32<TODAY()),"⚠ PAST DUE",IF(G32="","◔ NO DATE",IF(D32="Negotiation","● NEGOTIATING","○ ACTIVE"))))))
B33: =IFERROR(INDEX(INDIRECT("'"&RepPrefix4&"- Conversion'!D4:D202"),MATCH(LARGE(INDIRECT("'"&RepPrefix4&"- Conversion'!T4:T202"),5),INDIRECT("'"&RepPrefix4&"- Conversion'!T4:T202"),0)),"") | C33: =IF(OR(RepPrefix4="",B33=""),"",RepName4) | D33: =IFERROR(INDEX(INDIRECT("'"&RepPrefix4&"- Conversion'!G4:G202"),MATCH(LARGE(INDIRECT("'"&RepPrefix4&"- Conversion'!T4:T202"),5),INDIRECT("'"&RepPrefix4&"- Conversion'!T4:T202"),0)),"") | E33: =IFERROR(LARGE(INDIRECT("'"&RepPrefix4&"- Conversion'!T4:T202"),5),"") | F33: =IFERROR(INDEX(INDIRECT("'"&RepPrefix4&"- Conversion'!I4:I202"),MATCH(LARGE(INDIRECT("'"&RepPrefix4&"- Conversion'!T4:T202"),5),INDIRECT("'"&RepPrefix4&"- Conversion'!T4:T202"),0)),"") | G33: =IFERROR(INDEX(INDIRECT("'"&RepPrefix4&"- Conversion'!J4:J202"),MATCH(LARGE(INDIRECT("'"&RepPrefix4&"- Conversion'!T4:T202"),5),INDIRECT("'"&RepPrefix4&"- Conversion'!T4:T202"),0)),"") | H33: =IF(B33="","",IF(D33="Closed Won","✓ WON",IF(D33="Closed Lost","✗ LOST",IF(AND(G33<>"",ISNUMBER(G33),G33<TODAY()),"⚠ PAST DUE",IF(G33="","◔ NO DATE",IF(D33="Negotiation","● NEGOTIATING","○ ACTIVE"))))))
B34: =IFERROR(INDEX(INDIRECT("'"&RepPrefix4&"- Conversion'!D4:D202"),MATCH(LARGE(INDIRECT("'"&RepPrefix4&"- Conversion'!T4:T202"),6),INDIRECT("'"&RepPrefix4&"- Conversion'!T4:T202"),0)),"") | C34: =IF(OR(RepPrefix4="",B34=""),"",RepName4) | D34: =IFERROR(INDEX(INDIRECT("'"&RepPrefix4&"- Conversion'!G4:G202"),MATCH(LARGE(INDIRECT("'"&RepPrefix4&"- Conversion'!T4:T202"),6),INDIRECT("'"&RepPrefix4&"- Conversion'!T4:T202"),0)),"") | E34: =IFERROR(LARGE(INDIRECT("'"&RepPrefix4&"- Conversion'!T4:T202"),6),"") | F34: =IFERROR(INDEX(INDIRECT("'"&RepPrefix4&"- Conversion'!I4:I202"),MATCH(LARGE(INDIRECT("'"&RepPrefix4&"- Conversion'!T4:T202"),6),INDIRECT("'"&RepPrefix4&"- Conversion'!T4:T202"),0)),"") | G34: =IFERROR(INDEX(INDIRECT("'"&RepPrefix4&"- Conversion'!J4:J202"),MATCH(LARGE(INDIRECT("'"&RepPrefix4&"- Conversion'!T4:T202"),6),INDIRECT("'"&RepPrefix4&"- Conversion'!T4:T202"),0)),"") | H34: =IF(B34="","",IF(D34="Closed Won","✓ WON",IF(D34="Closed Lost","✗ LOST",IF(AND(G34<>"",ISNUMBER(G34),G34<TODAY()),"⚠ PAST DUE",IF(G34="","◔ NO DATE",IF(D34="Negotiation","● NEGOTIATING","○ ACTIVE"))))))
B35: =IFERROR(INDEX(INDIRECT("'"&RepPrefix4&"- Conversion'!D4:D202"),MATCH(LARGE(INDIRECT("'"&RepPrefix4&"- Conversion'!T4:T202"),7),INDIRECT("'"&RepPrefix4&"- Conversion'!T4:T202"),0)),"") | C35: =IF(OR(RepPrefix4="",B35=""),"",RepName4) | D35: =IFERROR(INDEX(INDIRECT("'"&RepPrefix4&"- Conversion'!G4:G202"),MATCH(LARGE(INDIRECT("'"&RepPrefix4&"- Conversion'!T4:T202"),7),INDIRECT("'"&RepPrefix4&"- Conversion'!T4:T202"),0)),"") | E35: =IFERROR(LARGE(INDIRECT("'"&RepPrefix4&"- Conversion'!T4:T202"),7),"") | F35: =IFERROR(INDEX(INDIRECT("'"&RepPrefix4&"- Conversion'!I4:I202"),MATCH(LARGE(INDIRECT("'"&RepPrefix4&"- Conversion'!T4:T202"),7),INDIRECT("'"&RepPrefix4&"- Conversion'!T4:T202"),0)),"") | G35: =IFERROR(INDEX(INDIRECT("'"&RepPrefix4&"- Conversion'!J4:J202"),MATCH(LARGE(INDIRECT("'"&RepPrefix4&"- Conversion'!T4:T202"),7),INDIRECT("'"&RepPrefix4&"- Conversion'!T4:T202"),0)),"") | H35: =IF(B35="","",IF(D35="Closed Won","✓ WON",IF(D35="Closed Lost","✗ LOST",IF(AND(G35<>"",ISNUMBER(G35),G35<TODAY()),"⚠ PAST DUE",IF(G35="","◔ NO DATE",IF(D35="Negotiation","● NEGOTIATING","○ ACTIVE"))))))
B36: =IFERROR(INDEX(INDIRECT("'"&RepPrefix4&"- Conversion'!D4:D202"),MATCH(LARGE(INDIRECT("'"&RepPrefix4&"- Conversion'!T4:T202"),8),INDIRECT("'"&RepPrefix4&"- Conversion'!T4:T202"),0)),"") | C36: =IF(OR(RepPrefix4="",B36=""),"",RepName4) | D36: =IFERROR(INDEX(INDIRECT("'"&RepPrefix4&"- Conversion'!G4:G202"),MATCH(LARGE(INDIRECT("'"&RepPrefix4&"- Conversion'!T4:T202"),8),INDIRECT("'"&RepPrefix4&"- Conversion'!T4:T202"),0)),"") | E36: =IFERROR(LARGE(INDIRECT("'"&RepPrefix4&"- Conversion'!T4:T202"),8),"") | F36: =IFERROR(INDEX(INDIRECT("'"&RepPrefix4&"- Conversion'!I4:I202"),MATCH(LARGE(INDIRECT("'"&RepPrefix4&"- Conversion'!T4:T202"),8),INDIRECT("'"&RepPrefix4&"- Conversion'!T4:T202"),0)),"") | G36: =IFERROR(INDEX(INDIRECT("'"&RepPrefix4&"- Conversion'!J4:J202"),MATCH(LARGE(INDIRECT("'"&RepPrefix4&"- Conversion'!T4:T202"),8),INDIRECT("'"&RepPrefix4&"- Conversion'!T4:T202"),0)),"") | H36: =IF(B36="","",IF(D36="Closed Won","✓ WON",IF(D36="Closed Lost","✗ LOST",IF(AND(G36<>"",ISNUMBER(G36),G36<TODAY()),"⚠ PAST DUE",IF(G36="","◔ NO DATE",IF(D36="Negotiation","● NEGOTIATING","○ ACTIVE"))))))
B37: =IFERROR(INDEX(INDIRECT("'"&RepPrefix5&"- Conversion'!D4:D202"),MATCH(LARGE(INDIRECT("'"&RepPrefix5&"- Conversion'!T4:T202"),1),INDIRECT("'"&RepPrefix5&"- Conversion'!T4:T202"),0)),"") | C37: =IF(OR(RepPrefix5="",B37=""),"",RepName5) | D37: =IFERROR(INDEX(INDIRECT("'"&RepPrefix5&"- Conversion'!G4:G202"),MATCH(LARGE(INDIRECT("'"&RepPrefix5&"- Conversion'!T4:T202"),1),INDIRECT("'"&RepPrefix5&"- Conversion'!T4:T202"),0)),"") | E37: =IFERROR(LARGE(INDIRECT("'"&RepPrefix5&"- Conversion'!T4:T202"),1),"") | F37: =IFERROR(INDEX(INDIRECT("'"&RepPrefix5&"- Conversion'!I4:I202"),MATCH(LARGE(INDIRECT("'"&RepPrefix5&"- Conversion'!T4:T202"),1),INDIRECT("'"&RepPrefix5&"- Conversion'!T4:T202"),0)),"") | G37: =IFERROR(INDEX(INDIRECT("'"&RepPrefix5&"- Conversion'!J4:J202"),MATCH(LARGE(INDIRECT("'"&RepPrefix5&"- Conversion'!T4:T202"),1),INDIRECT("'"&RepPrefix5&"- Conversion'!T4:T202"),0)),"") | H37: =IF(B37="","",IF(D37="Closed Won","✓ WON",IF(D37="Closed Lost","✗ LOST",IF(AND(G37<>"",ISNUMBER(G37),G37<TODAY()),"⚠ PAST DUE",IF(G37="","◔ NO DATE",IF(D37="Negotiation","● NEGOTIATING","○ ACTIVE"))))))
B38: =IFERROR(INDEX(INDIRECT("'"&RepPrefix5&"- Conversion'!D4:D202"),MATCH(LARGE(INDIRECT("'"&RepPrefix5&"- Conversion'!T4:T202"),2),INDIRECT("'"&RepPrefix5&"- Conversion'!T4:T202"),0)),"") | C38: =IF(OR(RepPrefix5="",B38=""),"",RepName5) | D38: =IFERROR(INDEX(INDIRECT("'"&RepPrefix5&"- Conversion'!G4:G202"),MATCH(LARGE(INDIRECT("'"&RepPrefix5&"- Conversion'!T4:T202"),2),INDIRECT("'"&RepPrefix5&"- Conversion'!T4:T202"),0)),"") | E38: =IFERROR(LARGE(INDIRECT("'"&RepPrefix5&"- Conversion'!T4:T202"),2),"") | F38: =IFERROR(INDEX(INDIRECT("'"&RepPrefix5&"- Conversion'!I4:I202"),MATCH(LARGE(INDIRECT("'"&RepPrefix5&"- Conversion'!T4:T202"),2),INDIRECT("'"&RepPrefix5&"- Conversion'!T4:T202"),0)),"") | G38: =IFERROR(INDEX(INDIRECT("'"&RepPrefix5&"- Conversion'!J4:J202"),MATCH(LARGE(INDIRECT("'"&RepPrefix5&"- Conversion'!T4:T202"),2),INDIRECT("'"&RepPrefix5&"- Conversion'!T4:T202"),0)),"") | H38: =IF(B38="","",IF(D38="Closed Won","✓ WON",IF(D38="Closed Lost","✗ LOST",IF(AND(G38<>"",ISNUMBER(G38),G38<TODAY()),"⚠ PAST DUE",IF(G38="","◔ NO DATE",IF(D38="Negotiation","● NEGOTIATING","○ ACTIVE"))))))
B39: =IFERROR(INDEX(INDIRECT("'"&RepPrefix5&"- Conversion'!D4:D202"),MATCH(LARGE(INDIRECT("'"&RepPrefix5&"- Conversion'!T4:T202"),3),INDIRECT("'"&RepPrefix5&"- Conversion'!T4:T202"),0)),"") | C39: =IF(OR(RepPrefix5="",B39=""),"",RepName5) | D39: =IFERROR(INDEX(INDIRECT("'"&RepPrefix5&"- Conversion'!G4:G202"),MATCH(LARGE(INDIRECT("'"&RepPrefix5&"- Conversion'!T4:T202"),3),INDIRECT("'"&RepPrefix5&"- Conversion'!T4:T202"),0)),"") | E39: =IFERROR(LARGE(INDIRECT("'"&RepPrefix5&"- Conversion'!T4:T202"),3),"") | F39: =IFERROR(INDEX(INDIRECT("'"&RepPrefix5&"- Conversion'!I4:I202"),MATCH(LARGE(INDIRECT("'"&RepPrefix5&"- Conversion'!T4:T202"),3),INDIRECT("'"&RepPrefix5&"- Conversion'!T4:T202"),0)),"") | G39: =IFERROR(INDEX(INDIRECT("'"&RepPrefix5&"- Conversion'!J4:J202"),MATCH(LARGE(INDIRECT("'"&RepPrefix5&"- Conversion'!T4:T202"),3),INDIRECT("'"&RepPrefix5&"- Conversion'!T4:T202"),0)),"") | H39: =IF(B39="","",IF(D39="Closed Won","✓ WON",IF(D39="Closed Lost","✗ LOST",IF(AND(G39<>"",ISNUMBER(G39),G39<TODAY()),"⚠ PAST DUE",IF(G39="","◔ NO DATE",IF(D39="Negotiation","● NEGOTIATING","○ ACTIVE"))))))
B40: =IFERROR(INDEX(INDIRECT("'"&RepPrefix5&"- Conversion'!D4:D202"),MATCH(LARGE(INDIRECT("'"&RepPrefix5&"- Conversion'!T4:T202"),4),INDIRECT("'"&RepPrefix5&"- Conversion'!T4:T202"),0)),"") | C40: =IF(OR(RepPrefix5="",B40=""),"",RepName5) | D40: =IFERROR(INDEX(INDIRECT("'"&RepPrefix5&"- Conversion'!G4:G202"),MATCH(LARGE(INDIRECT("'"&RepPrefix5&"- Conversion'!T4:T202"),4),INDIRECT("'"&RepPrefix5&"- Conversion'!T4:T202"),0)),"") | E40: =IFERROR(LARGE(INDIRECT("'"&RepPrefix5&"- Conversion'!T4:T202"),4),"") | F40: =IFERROR(INDEX(INDIRECT("'"&RepPrefix5&"- Conversion'!I4:I202"),MATCH(LARGE(INDIRECT("'"&RepPrefix5&"- Conversion'!T4:T202"),4),INDIRECT("'"&RepPrefix5&"- Conversion'!T4:T202"),0)),"") | G40: =IFERROR(INDEX(INDIRECT("'"&RepPrefix5&"- Conversion'!J4:J202"),MATCH(LARGE(INDIRECT("'"&RepPrefix5&"- Conversion'!T4:T202"),4),INDIRECT("'"&RepPrefix5&"- Conversion'!T4:T202"),0)),"") | H40: =IF(B40="","",IF(D40="Closed Won","✓ WON",IF(D40="Closed Lost","✗ LOST",IF(AND(G40<>"",ISNUMBER(G40),G40<TODAY()),"⚠ PAST DUE",IF(G40="","◔ NO DATE",IF(D40="Negotiation","● NEGOTIATING","○ ACTIVE"))))))
B41: =IFERROR(INDEX(INDIRECT("'"&RepPrefix5&"- Conversion'!D4:D202"),MATCH(LARGE(INDIRECT("'"&RepPrefix5&"- Conversion'!T4:T202"),5),INDIRECT("'"&RepPrefix5&"- Conversion'!T4:T202"),0)),"") | C41: =IF(OR(RepPrefix5="",B41=""),"",RepName5) | D41: =IFERROR(INDEX(INDIRECT("'"&RepPrefix5&"- Conversion'!G4:G202"),MATCH(LARGE(INDIRECT("'"&RepPrefix5&"- Conversion'!T4:T202"),5),INDIRECT("'"&RepPrefix5&"- Conversion'!T4:T202"),0)),"") | E41: =IFERROR(LARGE(INDIRECT("'"&RepPrefix5&"- Conversion'!T4:T202"),5),"") | F41: =IFERROR(INDEX(INDIRECT("'"&RepPrefix5&"- Conversion'!I4:I202"),MATCH(LARGE(INDIRECT("'"&RepPrefix5&"- Conversion'!T4:T202"),5),INDIRECT("'"&RepPrefix5&"- Conversion'!T4:T202"),0)),"") | G41: =IFERROR(INDEX(INDIRECT("'"&RepPrefix5&"- Conversion'!J4:J202"),MATCH(LARGE(INDIRECT("'"&RepPrefix5&"- Conversion'!T4:T202"),5),INDIRECT("'"&RepPrefix5&"- Conversion'!T4:T202"),0)),"") | H41: =IF(B41="","",IF(D41="Closed Won","✓ WON",IF(D41="Closed Lost","✗ LOST",IF(AND(G41<>"",ISNUMBER(G41),G41<TODAY()),"⚠ PAST DUE",IF(G41="","◔ NO DATE",IF(D41="Negotiation","● NEGOTIATING","○ ACTIVE"))))))
B42: =IFERROR(INDEX(INDIRECT("'"&RepPrefix5&"- Conversion'!D4:D202"),MATCH(LARGE(INDIRECT("'"&RepPrefix5&"- Conversion'!T4:T202"),6),INDIRECT("'"&RepPrefix5&"- Conversion'!T4:T202"),0)),"") | C42: =IF(OR(RepPrefix5="",B42=""),"",RepName5) | D42: =IFERROR(INDEX(INDIRECT("'"&RepPrefix5&"- Conversion'!G4:G202"),MATCH(LARGE(INDIRECT("'"&RepPrefix5&"- Conversion'!T4:T202"),6),INDIRECT("'"&RepPrefix5&"- Conversion'!T4:T202"),0)),"") | E42: =IFERROR(LARGE(INDIRECT("'"&RepPrefix5&"- Conversion'!T4:T202"),6),"") | F42: =IFERROR(INDEX(INDIRECT("'"&RepPrefix5&"- Conversion'!I4:I202"),MATCH(LARGE(INDIRECT("'"&RepPrefix5&"- Conversion'!T4:T202"),6),INDIRECT("'"&RepPrefix5&"- Conversion'!T4:T202"),0)),"") | G42: =IFERROR(INDEX(INDIRECT("'"&RepPrefix5&"- Conversion'!J4:J202"),MATCH(LARGE(INDIRECT("'"&RepPrefix5&"- Conversion'!T4:T202"),6),INDIRECT("'"&RepPrefix5&"- Conversion'!T4:T202"),0)),"") | H42: =IF(B42="","",IF(D42="Closed Won","✓ WON",IF(D42="Closed Lost","✗ LOST",IF(AND(G42<>"",ISNUMBER(G42),G42<TODAY()),"⚠ PAST DUE",IF(G42="","◔ NO DATE",IF(D42="Negotiation","● NEGOTIATING","○ ACTIVE"))))))
B43: =IFERROR(INDEX(INDIRECT("'"&RepPrefix5&"- Conversion'!D4:D202"),MATCH(LARGE(INDIRECT("'"&RepPrefix5&"- Conversion'!T4:T202"),7),INDIRECT("'"&RepPrefix5&"- Conversion'!T4:T202"),0)),"") | C43: =IF(OR(RepPrefix5="",B43=""),"",RepName5) | D43: =IFERROR(INDEX(INDIRECT("'"&RepPrefix5&"- Conversion'!G4:G202"),MATCH(LARGE(INDIRECT("'"&RepPrefix5&"- Conversion'!T4:T202"),7),INDIRECT("'"&RepPrefix5&"- Conversion'!T4:T202"),0)),"") | E43: =IFERROR(LARGE(INDIRECT("'"&RepPrefix5&"- Conversion'!T4:T202"),7),"") | F43: =IFERROR(INDEX(INDIRECT("'"&RepPrefix5&"- Conversion'!I4:I202"),MATCH(LARGE(INDIRECT("'"&RepPrefix5&"- Conversion'!T4:T202"),7),INDIRECT("'"&RepPrefix5&"- Conversion'!T4:T202"),0)),"") | G43: =IFERROR(INDEX(INDIRECT("'"&RepPrefix5&"- Conversion'!J4:J202"),MATCH(LARGE(INDIRECT("'"&RepPrefix5&"- Conversion'!T4:T202"),7),INDIRECT("'"&RepPrefix5&"- Conversion'!T4:T202"),0)),"") | H43: =IF(B43="","",IF(D43="Closed Won","✓ WON",IF(D43="Closed Lost","✗ LOST",IF(AND(G43<>"",ISNUMBER(G43),G43<TODAY()),"⚠ PAST DUE",IF(G43="","◔ NO DATE",IF(D43="Negotiation","● NEGOTIATING","○ ACTIVE"))))))
B44: =IFERROR(INDEX(INDIRECT("'"&RepPrefix5&"- Conversion'!D4:D202"),MATCH(LARGE(INDIRECT("'"&RepPrefix5&"- Conversion'!T4:T202"),8),INDIRECT("'"&RepPrefix5&"- Conversion'!T4:T202"),0)),"") | C44: =IF(OR(RepPrefix5="",B44=""),"",RepName5) | D44: =IFERROR(INDEX(INDIRECT("'"&RepPrefix5&"- Conversion'!G4:G202"),MATCH(LARGE(INDIRECT("'"&RepPrefix5&"- Conversion'!T4:T202"),8),INDIRECT("'"&RepPrefix5&"- Conversion'!T4:T202"),0)),"") | E44: =IFERROR(LARGE(INDIRECT("'"&RepPrefix5&"- Conversion'!T4:T202"),8),"") | F44: =IFERROR(INDEX(INDIRECT("'"&RepPrefix5&"- Conversion'!I4:I202"),MATCH(LARGE(INDIRECT("'"&RepPrefix5&"- Conversion'!T4:T202"),8),INDIRECT("'"&RepPrefix5&"- Conversion'!T4:T202"),0)),"") | G44: =IFERROR(INDEX(INDIRECT("'"&RepPrefix5&"- Conversion'!J4:J202"),MATCH(LARGE(INDIRECT("'"&RepPrefix5&"- Conversion'!T4:T202"),8),INDIRECT("'"&RepPrefix5&"- Conversion'!T4:T202"),0)),"") | H44: =IF(B44="","",IF(D44="Closed Won","✓ WON",IF(D44="Closed Lost","✗ LOST",IF(AND(G44<>"",ISNUMBER(G44),G44<TODAY()),"⚠ PAST DUE",IF(G44="","◔ NO DATE",IF(D44="Negotiation","● NEGOTIATING","○ ACTIVE"))))))
B45: =IFERROR(INDEX(INDIRECT("'"&RepPrefix6&"- Conversion'!D4:D202"),MATCH(LARGE(INDIRECT("'"&RepPrefix6&"- Conversion'!T4:T202"),1),INDIRECT("'"&RepPrefix6&"- Conversion'!T4:T202"),0)),"") | C45: =IF(OR(RepPrefix6="",B45=""),"",RepName6) | D45: =IFERROR(INDEX(INDIRECT("'"&RepPrefix6&"- Conversion'!G4:G202"),MATCH(LARGE(INDIRECT("'"&RepPrefix6&"- Conversion'!T4:T202"),1),INDIRECT("'"&RepPrefix6&"- Conversion'!T4:T202"),0)),"") | E45: =IFERROR(LARGE(INDIRECT("'"&RepPrefix6&"- Conversion'!T4:T202"),1),"") | F45: =IFERROR(INDEX(INDIRECT("'"&RepPrefix6&"- Conversion'!I4:I202"),MATCH(LARGE(INDIRECT("'"&RepPrefix6&"- Conversion'!T4:T202"),1),INDIRECT("'"&RepPrefix6&"- Conversion'!T4:T202"),0)),"") | G45: =IFERROR(INDEX(INDIRECT("'"&RepPrefix6&"- Conversion'!J4:J202"),MATCH(LARGE(INDIRECT("'"&RepPrefix6&"- Conversion'!T4:T202"),1),INDIRECT("'"&RepPrefix6&"- Conversion'!T4:T202"),0)),"") | H45: =IF(B45="","",IF(D45="Closed Won","✓ WON",IF(D45="Closed Lost","✗ LOST",IF(AND(G45<>"",ISNUMBER(G45),G45<TODAY()),"⚠ PAST DUE",IF(G45="","◔ NO DATE",IF(D45="Negotiation","● NEGOTIATING","○ ACTIVE"))))))
B46: =IFERROR(INDEX(INDIRECT("'"&RepPrefix6&"- Conversion'!D4:D202"),MATCH(LARGE(INDIRECT("'"&RepPrefix6&"- Conversion'!T4:T202"),2),INDIRECT("'"&RepPrefix6&"- Conversion'!T4:T202"),0)),"") | C46: =IF(OR(RepPrefix6="",B46=""),"",RepName6) | D46: =IFERROR(INDEX(INDIRECT("'"&RepPrefix6&"- Conversion'!G4:G202"),MATCH(LARGE(INDIRECT("'"&RepPrefix6&"- Conversion'!T4:T202"),2),INDIRECT("'"&RepPrefix6&"- Conversion'!T4:T202"),0)),"") | E46: =IFERROR(LARGE(INDIRECT("'"&RepPrefix6&"- Conversion'!T4:T202"),2),"") | F46: =IFERROR(INDEX(INDIRECT("'"&RepPrefix6&"- Conversion'!I4:I202"),MATCH(LARGE(INDIRECT("'"&RepPrefix6&"- Conversion'!T4:T202"),2),INDIRECT("'"&RepPrefix6&"- Conversion'!T4:T202"),0)),"") | G46: =IFERROR(INDEX(INDIRECT("'"&RepPrefix6&"- Conversion'!J4:J202"),MATCH(LARGE(INDIRECT("'"&RepPrefix6&"- Conversion'!T4:T202"),2),INDIRECT("'"&RepPrefix6&"- Conversion'!T4:T202"),0)),"") | H46: =IF(B46="","",IF(D46="Closed Won","✓ WON",IF(D46="Closed Lost","✗ LOST",IF(AND(G46<>"",ISNUMBER(G46),G46<TODAY()),"⚠ PAST DUE",IF(G46="","◔ NO DATE",IF(D46="Negotiation","● NEGOTIATING","○ ACTIVE"))))))
B47: =IFERROR(INDEX(INDIRECT("'"&RepPrefix6&"- Conversion'!D4:D202"),MATCH(LARGE(INDIRECT("'"&RepPrefix6&"- Conversion'!T4:T202"),3),INDIRECT("'"&RepPrefix6&"- Conversion'!T4:T202"),0)),"") | C47: =IF(OR(RepPrefix6="",B47=""),"",RepName6) | D47: =IFERROR(INDEX(INDIRECT("'"&RepPrefix6&"- Conversion'!G4:G202"),MATCH(LARGE(INDIRECT("'"&RepPrefix6&"- Conversion'!T4:T202"),3),INDIRECT("'"&RepPrefix6&"- Conversion'!T4:T202"),0)),"") | E47: =IFERROR(LARGE(INDIRECT("'"&RepPrefix6&"- Conversion'!T4:T202"),3),"") | F47: =IFERROR(INDEX(INDIRECT("'"&RepPrefix6&"- Conversion'!I4:I202"),MATCH(LARGE(INDIRECT("'"&RepPrefix6&"- Conversion'!T4:T202"),3),INDIRECT("'"&RepPrefix6&"- Conversion'!T4:T202"),0)),"") | G47: =IFERROR(INDEX(INDIRECT("'"&RepPrefix6&"- Conversion'!J4:J202"),MATCH(LARGE(INDIRECT("'"&RepPrefix6&"- Conversion'!T4:T202"),3),INDIRECT("'"&RepPrefix6&"- Conversion'!T4:T202"),0)),"") | H47: =IF(B47="","",IF(D47="Closed Won","✓ WON",IF(D47="Closed Lost","✗ LOST",IF(AND(G47<>"",ISNUMBER(G47),G47<TODAY()),"⚠ PAST DUE",IF(G47="","◔ NO DATE",IF(D47="Negotiation","● NEGOTIATING","○ ACTIVE"))))))
B48: =IFERROR(INDEX(INDIRECT("'"&RepPrefix6&"- Conversion'!D4:D202"),MATCH(LARGE(INDIRECT("'"&RepPrefix6&"- Conversion'!T4:T202"),4),INDIRECT("'"&RepPrefix6&"- Conversion'!T4:T202"),0)),"") | C48: =IF(OR(RepPrefix6="",B48=""),"",RepName6) | D48: =IFERROR(INDEX(INDIRECT("'"&RepPrefix6&"- Conversion'!G4:G202"),MATCH(LARGE(INDIRECT("'"&RepPrefix6&"- Conversion'!T4:T202"),4),INDIRECT("'"&RepPrefix6&"- Conversion'!T4:T202"),0)),"") | E48: =IFERROR(LARGE(INDIRECT("'"&RepPrefix6&"- Conversion'!T4:T202"),4),"") | F48: =IFERROR(INDEX(INDIRECT("'"&RepPrefix6&"- Conversion'!I4:I202"),MATCH(LARGE(INDIRECT("'"&RepPrefix6&"- Conversion'!T4:T202"),4),INDIRECT("'"&RepPrefix6&"- Conversion'!T4:T202"),0)),"") | G48: =IFERROR(INDEX(INDIRECT("'"&RepPrefix6&"- Conversion'!J4:J202"),MATCH(LARGE(INDIRECT("'"&RepPrefix6&"- Conversion'!T4:T202"),4),INDIRECT("'"&RepPrefix6&"- Conversion'!T4:T202"),0)),"") | H48: =IF(B48="","",IF(D48="Closed Won","✓ WON",IF(D48="Closed Lost","✗ LOST",IF(AND(G48<>"",ISNUMBER(G48),G48<TODAY()),"⚠ PAST DUE",IF(G48="","◔ NO DATE",IF(D48="Negotiation","● NEGOTIATING","○ ACTIVE"))))))
B49: =IFERROR(INDEX(INDIRECT("'"&RepPrefix6&"- Conversion'!D4:D202"),MATCH(LARGE(INDIRECT("'"&RepPrefix6&"- Conversion'!T4:T202"),5),INDIRECT("'"&RepPrefix6&"- Conversion'!T4:T202"),0)),"") | C49: =IF(OR(RepPrefix6="",B49=""),"",RepName6) | D49: =IFERROR(INDEX(INDIRECT("'"&RepPrefix6&"- Conversion'!G4:G202"),MATCH(LARGE(INDIRECT("'"&RepPrefix6&"- Conversion'!T4:T202"),5),INDIRECT("'"&RepPrefix6&"- Conversion'!T4:T202"),0)),"") | E49: =IFERROR(LARGE(INDIRECT("'"&RepPrefix6&"- Conversion'!T4:T202"),5),"") | F49: =IFERROR(INDEX(INDIRECT("'"&RepPrefix6&"- Conversion'!I4:I202"),MATCH(LARGE(INDIRECT("'"&RepPrefix6&"- Conversion'!T4:T202"),5),INDIRECT("'"&RepPrefix6&"- Conversion'!T4:T202"),0)),"") | G49: =IFERROR(INDEX(INDIRECT("'"&RepPrefix6&"- Conversion'!J4:J202"),MATCH(LARGE(INDIRECT("'"&RepPrefix6&"- Conversion'!T4:T202"),5),INDIRECT("'"&RepPrefix6&"- Conversion'!T4:T202"),0)),"") | H49: =IF(B49="","",IF(D49="Closed Won","✓ WON",IF(D49="Closed Lost","✗ LOST",IF(AND(G49<>"",ISNUMBER(G49),G49<TODAY()),"⚠ PAST DUE",IF(G49="","◔ NO DATE",IF(D49="Negotiation","● NEGOTIATING","○ ACTIVE"))))))
B50: =IFERROR(INDEX(INDIRECT("'"&RepPrefix6&"- Conversion'!D4:D202"),MATCH(LARGE(INDIRECT("'"&RepPrefix6&"- Conversion'!T4:T202"),6),INDIRECT("'"&RepPrefix6&"- Conversion'!T4:T202"),0)),"") | C50: =IF(OR(RepPrefix6="",B50=""),"",RepName6) | D50: =IFERROR(INDEX(INDIRECT("'"&RepPrefix6&"- Conversion'!G4:G202"),MATCH(LARGE(INDIRECT("'"&RepPrefix6&"- Conversion'!T4:T202"),6),INDIRECT("'"&RepPrefix6&"- Conversion'!T4:T202"),0)),"") | E50: =IFERROR(LARGE(INDIRECT("'"&RepPrefix6&"- Conversion'!T4:T202"),6),"") | F50: =IFERROR(INDEX(INDIRECT("'"&RepPrefix6&"- Conversion'!I4:I202"),MATCH(LARGE(INDIRECT("'"&RepPrefix6&"- Conversion'!T4:T202"),6),INDIRECT("'"&RepPrefix6&"- Conversion'!T4:T202"),0)),"") | G50: =IFERROR(INDEX(INDIRECT("'"&RepPrefix6&"- Conversion'!J4:J202"),MATCH(LARGE(INDIRECT("'"&RepPrefix6&"- Conversion'!T4:T202"),6),INDIRECT("'"&RepPrefix6&"- Conversion'!T4:T202"),0)),"") | H50: =IF(B50="","",IF(D50="Closed Won","✓ WON",IF(D50="Closed Lost","✗ LOST",IF(AND(G50<>"",ISNUMBER(G50),G50<TODAY()),"⚠ PAST DUE",IF(G50="","◔ NO DATE",IF(D50="Negotiation","● NEGOTIATING","○ ACTIVE"))))))
B51: =IFERROR(INDEX(INDIRECT("'"&RepPrefix6&"- Conversion'!D4:D202"),MATCH(LARGE(INDIRECT("'"&RepPrefix6&"- Conversion'!T4:T202"),7),INDIRECT("'"&RepPrefix6&"- Conversion'!T4:T202"),0)),"") | C51: =IF(OR(RepPrefix6="",B51=""),"",RepName6) | D51: =IFERROR(INDEX(INDIRECT("'"&RepPrefix6&"- Conversion'!G4:G202"),MATCH(LARGE(INDIRECT("'"&RepPrefix6&"- Conversion'!T4:T202"),7),INDIRECT("'"&RepPrefix6&"- Conversion'!T4:T202"),0)),"") | E51: =IFERROR(LARGE(INDIRECT("'"&RepPrefix6&"- Conversion'!T4:T202"),7),"") | F51: =IFERROR(INDEX(INDIRECT("'"&RepPrefix6&"- Conversion'!I4:I202"),MATCH(LARGE(INDIRECT("'"&RepPrefix6&"- Conversion'!T4:T202"),7),INDIRECT("'"&RepPrefix6&"- Conversion'!T4:T202"),0)),"") | G51: =IFERROR(INDEX(INDIRECT("'"&RepPrefix6&"- Conversion'!J4:J202"),MATCH(LARGE(INDIRECT("'"&RepPrefix6&"- Conversion'!T4:T202"),7),INDIRECT("'"&RepPrefix6&"- Conversion'!T4:T202"),0)),"") | H51: =IF(B51="","",IF(D51="Closed Won","✓ WON",IF(D51="Closed Lost","✗ LOST",IF(AND(G51<>"",ISNUMBER(G51),G51<TODAY()),"⚠ PAST DUE",IF(G51="","◔ NO DATE",IF(D51="Negotiation","● NEGOTIATING","○ ACTIVE"))))))
B52: =IFERROR(INDEX(INDIRECT("'"&RepPrefix6&"- Conversion'!D4:D202"),MATCH(LARGE(INDIRECT("'"&RepPrefix6&"- Conversion'!T4:T202"),8),INDIRECT("'"&RepPrefix6&"- Conversion'!T4:T202"),0)),"") | C52: =IF(OR(RepPrefix6="",B52=""),"",RepName6) | D52: =IFERROR(INDEX(INDIRECT("'"&RepPrefix6&"- Conversion'!G4:G202"),MATCH(LARGE(INDIRECT("'"&RepPrefix6&"- Conversion'!T4:T202"),8),INDIRECT("'"&RepPrefix6&"- Conversion'!T4:T202"),0)),"") | E52: =IFERROR(LARGE(INDIRECT("'"&RepPrefix6&"- Conversion'!T4:T202"),8),"") | F52: =IFERROR(INDEX(INDIRECT("'"&RepPrefix6&"- Conversion'!I4:I202"),MATCH(LARGE(INDIRECT("'"&RepPrefix6&"- Conversion'!T4:T202"),8),INDIRECT("'"&RepPrefix6&"- Conversion'!T4:T202"),0)),"") | G52: =IFERROR(INDEX(INDIRECT("'"&RepPrefix6&"- Conversion'!J4:J202"),MATCH(LARGE(INDIRECT("'"&RepPrefix6&"- Conversion'!T4:T202"),8),INDIRECT("'"&RepPrefix6&"- Conversion'!T4:T202"),0)),"") | H52: =IF(B52="","",IF(D52="Closed Won","✓ WON",IF(D52="Closed Lost","✗ LOST",IF(AND(G52<>"",ISNUMBER(G52),G52<TODAY()),"⚠ PAST DUE",IF(G52="","◔ NO DATE",IF(D52="Negotiation","● NEGOTIATING","○ ACTIVE"))))))

Sheet Inputs
A2: DASHBOARD INPUTS · EDIT VALUES IN COLUMN C
B5: Quarterly TCV Quota (₱) | C5: 500000000 | D5: Used to compute Pipeline Coverage Ratio.
B7: Pipeline Coverage Target (×) | C7: 3 | D7: Healthy B2B benchmark: 3-5× quota.
B9: Target GP Margin (%) | C9: 0.2 | D9: Threshold for green/amber on GP%.
B11: Stage-Aging Threshold (days) | C11: 60 | D11: Deals older than this in same stage = at-risk.
B13: At-Risk Deal Size Threshold (₱) | C13: 100000000 | D13: Past-due deals above this auto-flag red.
B15: Dashboard Title | C15: EXECUTIVE SALES DASHBOARD | D15: Edit to rebrand the title strip.
B17: Dashboard Subtitle | C17: Live pipeline · TCV · GP · Stage · Health | D17: Subtitle below the title.
B20: REP SLOTS — Set Sheet Prefix to wire each slot to a Coverage/Conversion sheet pair
B22: Rep 1 Sheet Prefix | C22: Madine | D22: Slot 1 — pre-wired to existing Madine sheets (do not change prefix).
B23: Rep 1 Display Name | C23: Madine | D23: Shown on dashboard. Independent of sheet prefix.
B25: Rep 2 Sheet Prefix | C25: Zarrah | D25: Slot 2 — pre-wired to existing Zarrah sheets (do not change prefix).
B26: Rep 2 Display Name | C26: Zarrah | D26: Shown on dashboard. Independent of sheet prefix.
B28: Rep 3 Sheet Prefix | C28: Home | D28: Slot 3 — pre-wired to existing Home sheets (do not change prefix).
B29: Rep 3 Display Name | C29: Home | D29: Shown on dashboard. Independent of sheet prefix.
B31: Rep 4 Sheet Prefix | D31: Slot 4 — empty. To activate: create '<Prefix>- Coverage' & '<Prefix>- Conversion' sheets, then type prefix here.
B32: Rep 4 Display Name | C32: Rep 4 | D32: Shown on dashboard. Independent of sheet prefix.
B34: Rep 5 Sheet Prefix | D34: Slot 5 — empty. Same activation steps as Slot 4.
B35: Rep 5 Display Name | C35: Rep 5 | D35: Shown on dashboard. Independent of sheet prefix.
B37: Rep 6 Sheet Prefix | D37: Slot 6 — empty. Same activation steps as Slot 4.
B38: Rep 6 Display Name | C38: Rep 6 | D38: Shown on dashboard. Independent of sheet prefix.
B42: HOW TO ADD A NEW REP (Slots 4–6)
B43: 1. Right-click the 'Madine- Coverage' tab → 'Move or Copy' → check 'Create a copy' → OK.
B44: 2. Right-click the new tab → Rename to '<NewName>- Coverage' (must include '- ' with space).
B45: 3. Open the renamed sheet → clear all data rows below the header (keep row 1-3 untouched).
B46: 4. Repeat steps 1–3 for 'Madine- Conversion' → '<NewName>- Conversion'.
B47: 5. Type the new rep's data into both sheets.
B48: 6. Come back to this Inputs sheet → set 'Rep 4 Sheet Prefix' (cell C31) to '<NewName>'.
B49: 7. Optional: set 'Rep 4 Display Name' (cell C32) to a friendlier label.
B50: 8. The Dashboard automatically includes the new rep — no rebuild needed.
B52: ✓ The prefix MUST exactly match the sheet name minus '- Coverage' / '- Conversion'.
B53: ✓ Slots 1-3 are PRE-WIRED to Madine / Zarrah / Home — leave their prefixes alone.
B54: ✓ To remove a slot, simply blank out its prefix → totals exclude it automatically.
... B56: copies along when you duplicate the Madine sheet, so don't worry about it.

Sheet Madine- Coverage
A1: SALES COVERAGE — Person A
A2: ℹ Rows are unlimited. Add as many opportunities as needed. Totals row auto-updates.
A3: 1 | B3: BDM | C3: ACCOUNT NAME | D3: OPPORTUNITY TYPE | E3: OPPORTUNITY DETAILS | F3: AREA (IN SQM) | G3: TCV | H3: GP | I3: CLOSING DATE | J3: REMARKS | K3: PROBABILITY
A4: 2 | B4: Madine | C4: Baishipping | D4: Renovation - Build CAPEX | E4: for scheduling with Sir Jon | J4: For follow up as of 04.07.2026 | K4: 0.9
A5: 3 | B5: Madine | C5: Indus Restaurant | D5: Renovation - D&B CAPEX | J5: Design still not yet done. For bidding as of 04.07.2026 | K5: 0.7
A6: 4 | B6: Madine | C6: Agility | D6: Office Fitout - D&B OPEX | E6: For follow up | J6: For follow up as of 04.07.2026 | K6: 0.1
A7: 5 | B7: Madine | C7: Enov8tive | D7: Office Fitout - D&B CAPEX | J7: For office expansion Q3 | K7: 0.7
A8: 6 | B8: Madine | C8: Dialpad | D8: Office Fitout - D&B OPEX | E8: for scheduling with Sir Jon | F8: 800sqm | J8: For sending of proposal today as of 04.07.2026 | K8: 0.9
A9: 7 | B9: Madine | C9: St. Lukes (QC, Pque & Aseana) | D9: Office Fitout - D&B CAPEX | E9: timing and resource | J9: Done meeting March 11, 2026. Fixing accrediation requirements together with Shimizu. For site visit on April 20/27 as of 04.07.2026 | K9: 0.7
A10: 8 | B10: Madine | C10: Fresenius Medical Care 2 | D10: Renovation - D&B CAPEX | E10: Renovation of old clinics. Right now they have 20 clinics nationwide | J10: For meeting. This is another project as 04.07.2026 | K10: 0.7
A11: 9 | B11: Madine | C11: PGA Cars | D11: Office Fitout - D&B CAPEX | J11: Submitted accreditation requirements on March 12, 2026 as of 03.17.2026 | K11: 0.7
A12: 10 | B12: Madine | C12: Philrealty | D12: Structural D&B | E12: lunch with Sir Jon and Engr Erwin | J12: Done meeting last April 10, 2026 and done accreditation. Waiting for bid requirments | K12: 0.7
A13: 11 | B13: Madine | C13: Manila Polo Club | J13: Submitted accreditation requirements on March 12, 2026 as of 03.17.2026 | K13: 0.7
A14: 12 | B14: Madine | C14: Intercon | D14: Build Only | E14: New hotel building | J14: Done meeting last April 10, 2026 and done accreditation. Waiting for bid requirments | K14: 0.7
A15: 13 | B15: Madine | C15: Netflix | D15: Office Fitout - Build Only | E15: 2 floors in Ayala Triangle | J15: Sent company profile as of 03.26.2026 | K15: 0.1
A16: 14 | B16: Madine | C16: Navegar | D16: Office Fitout - D&B CAPEX | J16: Sent wishlist as of 03.26.2026. For follow up as of 04.07.2026 | K16: 0.7
A17: 15 | B17: Madine | C17: PNB Holdings | D17: Build Only | J17: (Buendia, Pasay and Makati Offices)
A18: 16 | B18: Madine | C18: Full Potentials Solutions | D18: Office Fitout - Build Only | J18: Submission of proposal EOD tom | K18: 0.5
A19: 17 | B19: Madine | C19: Security Bank | D19: Office Fitout - Build Only | J19: Getting Accredited
A20: 18 | B20: Madine | C20: Terminal 5/ SMC | D20: Office Fitout - Build Only | J20: Submitted company profile
A21: 19
A22: 20
A23: 21
A24: 22
A25: 23
A26: 24
A27: 25
A28: 26
A29: 27
A30: 28
A31: 29
A32: 30
... A202: 200
A203: TOTALS | B203: # DEALS: | C203: =COUNTA(C3:C202) | F203: =SUM(F3:F202) | G203: =SUM(G3:G202) | H203: =SUM(H3:H202)

Sheet Madine- Conversion
A1: SALES CONVERSION — Person A | R1: Stage | S1: Prob %
A2: ℹ Rows are unlimited. Add as many opportunities as needed. Totals row auto-updates. | R2: Closed Lost | S2: 0
A3: 1 | B3: Industry Segment | C3: Coverage | D3: ACCOUNT NAME | E3: OPPORTUNITY TYPE | F3: AREA (IN SQM) | G3: OPPORTUNITY STAGE | H3: TCV (VAT EX) | I3: GP (VAT EX) | J3: CLOSING DATE | K3: PROBABILITY (Auto) | L3: Project Start Date | M3: Project Completion | N3: BOM SUBMISSION | O3: REMARKS TO BE UPDATED BY SALES WEEKLY as of April 8, 2026 | P3: REMARKS TO BE UPDATED BY COMMERCIAL | R3: Opportunity Creation | S3: 0.1 | T3: Eligible TCV (helper)
A4: 2 | B4: BPO Third Party | C4: Madine Sta. Cruz | D4: Fresenius Medical Care | E4: Renovation of office in Wfifth | G4: Negotiation | H4: 3745564 | I4: =H4*20% | J4: 46127 | K4: =IFERROR(VLOOKUP(G4,Stage_Lookup!$A$2:$B$8,2,0),"") | N4: 46091 | O4: Awarding by next week | R4: Scoping | S4: 0.3 | T4: =IF(OR(G4="Closed Lost",G4="",NOT(ISNUMBER(H4))),"",H4)
A5: 3 | B5: Captive Shared Services | C5: Madine Sta. Cruz/ House Account | D5: KPMG (KDN) - 4 Neo BGC | E5: Design and Build Project | F5: 2500 | G5: BOM Submission | H5: 105000000 | I5: =H5*18% | J5: 46137 | K5: =IFERROR(VLOOKUP(G5,Stage_Lookup!$A$2:$B$8,2,0),"") | O5: For resubmssion after signing of NTP | R5: BOM Submission | S5: 0.5 | T5: =IF(OR(G5="Closed Lost",G5="",NOT(ISNUMBER(H5))),"",H5)
A6: 4 | B6: Captive Shared Services | C6: Madine Sta Cruz/House Account | D6: BSMH | E6: New Floor (6th and 7th Floor) | F6: 4500 | G6: BOM Submission | H6: =75000*4400 | I6: 52800000 | J6: 46127 | K6: =IFERROR(VLOOKUP(G6,Stage_Lookup!$A$2:$B$8,2,0),"") | R6: Resubmission | S6: 0.7 | T6: =IF(OR(G6="Closed Lost",G6="",NOT(ISNUMBER(H6))),"",H6)
A7: 5 | B7: Enterprise | C7: Madine Sta. Cruz/ House Account | D7: PWC | E7: Renovation works Bulid | G7: BOM Submission | H7: 57507.55 | I7: 9000 | J7: 46127 | K7: =IFERROR(VLOOKUP(G7,Stage_Lookup!$A$2:$B$8,2,0),"") | N7: 46094 | O7: For follow up on the awarding | R7: Negotiation | S7: 0.9 | T7: =IF(OR(G7="Closed Lost",G7="",NOT(ISNUMBER(H7))),"",H7)
A8: 6 | B8: Enterprise | C8: Madine Sta. Cruz | D8: The Moment Group | E8: Project Management | G8: BOM Submission | H8: 2600000 | I8: 1300000 | J8: 46122 | K8: =IFERROR(VLOOKUP(G8,Stage_Lookup!$A$2:$B$8,2,0),"") | N8: 46107 | O8: For follow up on the awarding | R8: Closed Won | S8: 1 | T8: =IF(OR(G8="Closed Lost",G8="",NOT(ISNUMBER(H8))),"",H8)
A9: 7 | B9: Enterprise | C9: Madine Sta. Cruz | D9: Aivee Group | E9: Alabang Commerce Center | F9: 300 sqm | G9: BOM Submission | H9: 9000000 | I9: 1800000 | K9: =IFERROR(VLOOKUP(G9,Stage_Lookup!$A$2:$B$8,2,0),"") | O9: On hold | T9: =IF(OR(G9="Closed Lost",G9="",NOT(ISNUMBER(H9))),"",H9)
A10: 8 | B10: Enterprise | C10: Madine Sta. Cruz | D10: Aivee Group | E10: Forbestowne Clinic | F10: 60.31sqm | G10: Negotiation | H10: 8842687.3 | I10: 2033818.1 | J10: 46127 | K10: =IFERROR(VLOOKUP(G10,Stage_Lookup!$A$2:$B$8,2,0),"") | N10: 46094 | O10: Waiting for negotiation date | T10: =IF(OR(G10="Closed Lost",G10="",NOT(ISNUMBER(H10))),"",H10)
A11: 9 | B11: Enterprise | C11: Madine Sta Cruz/House Account | D11: Monolith Construction | E11: NAI T4 Renovation | F11: 12671.19 | G11: Resubmission | H11: 3.1438005e+08 | I11: 56588409 | J11: 46127 | K11: =IFERROR(VLOOKUP(G11,Stage_Lookup!$A$2:$B$8,2,0),"") | N11: 46109 | O11: For another resubmission of proposal as of 04.10.26 | T11: =IF(OR(G11="Closed Lost",G11="",NOT(ISNUMBER(H11))),"",H11)
A12: 10 | B12: Enterprise | C12: Madine Sta Cruz/House Account | D12: Full Potential Solutions (FPS) | E12: Design and Build Project | F12: 1718 | G12: Resubmission | H12: 90152155 | I12: =H12*23% | J12: 46134 | K12: =IFERROR(VLOOKUP(G12,Stage_Lookup!$A$2:$B$8,2,0),"") | T12: =IF(OR(G12="Closed Lost",G12="",NOT(ISNUMBER(H12))),"",H12)
A13: 11 | B13: Captive Shared Services | C13: Madine Sta. Cruz/ House Account | D13: KPMG (KDN) - 4 Neo BGC | E13: AV and Tech | G13: BOM Submission | H13: =35758968.4+27521045.26 | I13: =H13*20% | J13: 46137 | K13: =IFERROR(VLOOKUP(G13,Stage_Lookup!$A$2:$B$8,2,0),"") | T13: =IF(OR(G13="Closed Lost",G13="",NOT(ISNUMBER(H13))),"",H13)
A14: 12 | B14: Enterprise | C14: Madine Sta. Cruz | D14: President's Hill | E14: AUX | F14: 13700 | G14: BOM Submission | H14: 46136882 | I14: =H14*21% | J14: 46235 | K14: =IFERROR(VLOOKUP(G14,Stage_Lookup!$A$2:$B$8,2,0),"") | T14: =IF(OR(G14="Closed Lost",G14="",NOT(ISNUMBER(H14))),"",H14)
A15: 13 | B15: Enterprise | C15: Madine Sta Cruz/House Account | D15: ClickSpace | E15: Design and Build Project | F15: 850 | G15: Scoping | J15: 46172 | K15: =IFERROR(VLOOKUP(G15,Stage_Lookup!$A$2:$B$8,2,0),"") | T15: =IF(OR(G15="Closed Lost",G15="",NOT(ISNUMBER(H15))),"",H15)
A16: 14 | B16: Enterprise | C16: Madine Sta. Cruz | D16: Skyline | E16: FDAS | G16: Scoping | J16: 46146 | K16: =IFERROR(VLOOKUP(G16,Stage_Lookup!$A$2:$B$8,2,0),"") | T16: =IF(OR(G16="Closed Lost",G16="",NOT(ISNUMBER(H16))),"",H16)
A17: 15 | K17: =IFERROR(VLOOKUP(G17,Stage_Lookup!$A$2:$B$8,2,0),"") | T17: =IF(OR(G17="Closed Lost",G17="",NOT(ISNUMBER(H17))),"",H17)
A18: 16 | K18: =IFERROR(VLOOKUP(G18,Stage_Lookup!$A$2:$B$8,2,0),"") | T18: =IF(OR(G18="Closed Lost",G18="",NOT(ISNUMBER(H18))),"",H18)
A19: 17 | K19: =IFERROR(VLOOKUP(G19,Stage_Lookup!$A$2:$B$8,2,0),"") | T19: =IF(OR(G19="Closed Lost",G19="",NOT(ISNUMBER(H19))),"",H19)
A20: 18 | K20: =IFERROR(VLOOKUP(G20,Stage_Lookup!$A$2:$B$8,2,0),"") | T20: =IF(OR(G20="Closed Lost",G20="",NOT(ISNUMBER(H20))),"",H20)
A21: 19 | K21: =IFERROR(VLOOKUP(G21,Stage_Lookup!$A$2:$B$8,2,0),"") | T21: =IF(OR(G21="Closed Lost",G21="",NOT(ISNUMBER(H21))),"",H21)
A22: 20 | K22: =IFERROR(VLOOKUP(G22,Stage_Lookup!$A$2:$B$8,2,0),"") | T22: =IF(OR(G22="Closed Lost",G22="",NOT(ISNUMBER(H22))),"",H22)
A23: 21 | K23: =IFERROR(VLOOKUP(G23,Stage_Lookup!$A$2:$B$8,2,0),"") | T23: =IF(OR(G23="Closed Lost",G23="",NOT(ISNUMBER(H23))),"",H23)
A24: 22 | K24: =IFERROR(VLOOKUP(G24,Stage_Lookup!$A$2:$B$8,2,0),"") | T24: =IF(OR(G24="Closed Lost",G24="",NOT(ISNUMBER(H24))),"",H24)
A25: 23 | K25: =IFERROR(VLOOKUP(G25,Stage_Lookup!$A$2:$B$8,2,0),"") | T25: =IF(OR(G25="Closed Lost",G25="",NOT(ISNUMBER(H25))),"",H25)
A26: 24 | K26: =IFERROR(VLOOKUP(G26,Stage_Lookup!$A$2:$B$8,2,0),"") | T26: =IF(OR(G26="Closed Lost",G26="",NOT(ISNUMBER(H26))),"",H26)
A27: 25 | K27: =IFERROR(VLOOKUP(G27,Stage_Lookup!$A$2:$B$8,2,0),"") | T27: =IF(OR(G27="Closed Lost",G27="",NOT(ISNUMBER(H27))),"",H27)
A28: 26 | K28: =IFERROR(VLOOKUP(G28,Stage_Lookup!$A$2:$B$8,2,0),"") | T28: =IF(OR(G28="Closed Lost",G28="",NOT(ISNUMBER(H28))),"",H28)
... A202: 200 | K202: =IFERROR(VLOOKUP(G202,Stage_Lookup!$A$2:$B$8,2,0),"") | T202: =IF(OR(G202="Closed Lost",G202="",NOT(ISNUMBER(H202))),"",H202)
A203: TOTALS | C203: # DEALS: | D203: =COUNTA(D3:D202) | F203: =SUM(F3:F202) | H203: =SUM(H3:H202) | I203: =SUM(I3:I202)

Sheet Zarrah- Coverage
A1: SALES COVERAGE — Person B
A2: ℹ Rows are unlimited. Add as many opportunities as needed. Totals row auto-updates.
A3: 1 | B3: BDM | C3: ACCOUNT NAME | D3: OPPORTUNITY TYPE | E3: OPPORTUNITY DETAILS | F3: AREA (IN SQM) | G3: TCV | H3: GP | I3: CLOSING DATE | J3: REMARKS | K3: PROBABILITY
A4: 2 | B4: Zarrah | C4: TDCX | D4: Office Fitout - D&B CAPEX | E4: Expansion Octigas office | J4: Expansion was moved to Q1 2027
A5: 3 | B5: Zarrah | C5: BPI | D5: Office Fitout - D&B CAPEX | E5: Expansion Alabang and BGC | J5: Awarded to Newcore
A6: 4 | B6: Zarrah | C6: HGS | D6: Office Fitout - D&B OPEX | E6: Cebu or Bohol | J6: No movement yet accroding to the client
A7: 5 | B7: Zarrah | C7: Jewelmer/Karamar | D7: Office Fitout - D&B CAPEX | E7: New site in Cebu | J7: Waiting for approval, as they are still negotiating with the landlord.
A8: 6 | B8: Zarrah | C8: EY | D8: Office Fitout - D&B CAPEX
A9: 7 | B9: Zarrah | C9: Clock in | D9: Office Fitout - D&B CAPEX | E9: 3F One Ayala Bldg
A10: 8 | B10: Zarrah | C10: Lexmark | D10: Office Fitout - D&B CAPEX | E10: Cebu
A11: 9 | B11: Zarrah | C11: AFNI | D11: Office Fitout - D&B CAPEX | E11: OFC
A12: 10 | B12: Zarrah | C12: AFNI | D12: Office Fitout - D&B CAPEX | E12: 7F, 8F&9F Tower 3 SM STR
A13: 11 | B13: Zarrah | C13: GC Services/Intelogix | D13: Office Fitout - D&B CAPEX | E13: 6F Cybergate Bacolod 2, Bacolod | J13: According to Wes, theres an onogoing negotitation with the new cleint
A14: 12 | B14: Zarrah | C14: Everise | D14: Office Fitout - D&B CAPEX | J14: For Follow up
A15: 13 | B15: Zarrah | C15: HGS | D15: Office Fitout - D&B CAPEX | E15: 10F The Enterprise Iloilo | J15: According to the client, they are still waiting for approval regarding the timing for the additional space.
A16: 14 | B16: Zarrah | C16: Accenture | D16: Office Fitout - D&B CAPEX | J16: Potential Bridgetown expansion, cover procurement team
A17: 15 | B17: Zarrah | C17: IQOR | D17: Office Fitout - D&B CAPEX | J17: Provincial expansion, cover new Country Head c/o Jon
A18: 16 | B18: Zarrah | C18: Solaire Resort and Casino | D18: Office Fitout - D&B CAPEX | J18: Requested a meeting with Procurement and Facilities week of March 2, 2026
A19: 17 | B19: Zarrah | C19: Ascott | D19: Office Fitout - D&B CAPEX | J19: Accrediation Process- ongoing , waiting for the OR and SI under C2 address
A20: 18 | B20: Zarrah | C20: The Beef Bar | D20: Office Fitout - D&B CAPEX | E20: Design and Build high end restaurant in PSE makati | F20: 583 sqm | J20: For Follow up
A21: 19 | B21: Zarrah | C21: WNS | D21: Maintenance, Office Fit Out D&B | J21: For Follow up
A22: 20
A23: 21
A24: 22
A25: 23
A26: 24
A27: 25
A28: 26
A29: 27
A30: 28
A31: 29
A32: 30
A33: 31
... A202: 200
A203: TOTALS | B203: # DEALS: | C203: =COUNTA(C3:C202) | F203: =SUM(F3:F202) | G203: =SUM(G3:G202) | H203: =SUM(H3:H202)

Sheet Zarrah-Conversion
A1: ℹ Rows are unlimited. Add as many opportunities as needed. Totals row auto-updates. | R1: Closed Lost | S1: 0
A2: 1 | B2: Industry Segment | C2: Coverage | D2: ACCOUNT NAME | E2: OPPORTUNITY TYPE | F2: AREA (IN SQM) | G2: OPPORTUNITY STAGE | H2: TCV (VAT EX) | I2: GP (VAT EX) | J2: CLOSING DATE | K2: PROBABILITY (Auto) | L2: Project Start Date | M2: Project Completion | N2: BOM SUBMISSION | O2: REMARKS TO BE UPDATED BY SALES WEEKLY | P2: REMARKS TO BE UPDATED BY COMMERCIAL | R2: Opportunity Creation | S2: 0.1 | T2: Eligible TCV (helper)
A3: 2 | B3: BPO Third Party | C3: Zarrah | D3: DHL Global Business Services | E3: Design & Build-renovation works | F3: 1500 | G3: Resubmission | H3: 11211946 | I3: 2242389.1 | J3: 46173 | K3: =IFERROR(VLOOKUP(G3,Stage_Lookup!$A$2:$B$8,2,0),"") | O3: Resubmission of proposal-April 10,2026, based on the additional requirements and meetign with the client last March 31,2026 | R3: Scoping | S3: 0.3 | T3: =IF(OR(G3="Closed Lost",G3="",NOT(ISNUMBER(H3))),"",H3)
A4: 3 | B4: Captive Shared Services | C4: Zarrah | D4: JC Pinon Construction Inc | E4: D&B and renovation project | G4: BOM Submission | H4: 15071815 | I4: 3014363.1 | J4: 46172 | K4: =IFERROR(VLOOKUP(G4,Stage_Lookup!$A$2:$B$8,2,0),"") | O4: Based on the last touchpoint with the client, March 26,2026 , proposal is still for evaluation | R4: BOM Submission | S4: 0.5 | T4: =IF(OR(G4="Closed Lost",G4="",NOT(ISNUMBER(H4))),"",H4)
A5: 4 | B5: Captive Shared Services | C5: Zarrah | D5: Regus-Savya | E5: 7F Savya Financial Center -VO#1 | G5: BOM Submission | H5: 5523182.8 | I5: 828477.41 | J5: 46172 | K5: =IFERROR(VLOOKUP(G5,Stage_Lookup!$A$2:$B$8,2,0),"") | O5: Proposal for approval | R5: Resubmission | S5: 0.7 | T5: =IF(OR(G5="Closed Lost",G5="",NOT(ISNUMBER(H5))),"",H5)
A6: 5 | B6: Captive Shared Services | C6: Zarrah | D6: Unilab | E6: FPDI Electrical upgrade and Structural works | G6: Closed Lost | H6: 34000000 | I6: 3400000 | J6: 46142 | K6: =IFERROR(VLOOKUP(G6,Stage_Lookup!$A$2:$B$8,2,0),"") | R6: Negotiation | S6: 0.9 | T6: =IF(OR(G6="Closed Lost",G6="",NOT(ISNUMBER(H6))),"",H6)
A7: 6 | B7: Captive Shared Services | C7: Zarrah | D7: Unilab | E7: VO23 & 24 | G7: Closed Won | H7: 16631368 | I7: 4197757.2 | J7: 46142 | K7: =IFERROR(VLOOKUP(G7,Stage_Lookup!$A$2:$B$8,2,0),"") | O7: waiting for PO | R7: Closed Won | S7: 1 | T7: =IF(OR(G7="Closed Lost",G7="",NOT(ISNUMBER(H7))),"",H7)
A8: 7 | B8: Captive Shared Services | C8: Zarrah | D8: Unilab | E8: VO 25 | G8: BOM Submission | H8: 3418026 | I8: 683605.2 | J8: 46142 | K8: =IFERROR(VLOOKUP(G8,Stage_Lookup!$A$2:$B$8,2,0),"") | T8: =IF(OR(G8="Closed Lost",G8="",NOT(ISNUMBER(H8))),"",H8)
A9: 8 | B9: Government - Large Scale | C9: Zarrah | D9: HGS Iloilo | E9: Interior Fit-out_D&B-OPEX | G9: Closed Won | H9: 136462707 | I9: 21834033 | J9: 45877 | K9: =IFERROR(VLOOKUP(G9,Stage_Lookup!$A$2:$B$8,2,0),"") | T9: =IF(OR(G9="Closed Lost",G9="",NOT(ISNUMBER(H9))),"",H9)
A10: 9 | B10: Government - Large Scale | C10: Zarrah | D10: Regus-Savya | E10: 7F Savya Financial Center | G10: Closed Won | H10: 70000000 | I10: 7080892.5 | J10: 46053 | K10: =IFERROR(VLOOKUP(G10,Stage_Lookup!$A$2:$B$8,2,0),"") | T10: =IF(OR(G10="Closed Lost",G10="",NOT(ISNUMBER(H10))),"",H10)
A11: 10 | B11: Enterprise | C11: Zarrah | D11: Unilab | E11: 2F Executive Lounge Punan, Laguna | G11: Closed Won | H11: 53248566 | I11: 9584741.9 | J11: 46112 | K11: =IFERROR(VLOOKUP(G11,Stage_Lookup!$A$2:$B$8,2,0),"") | T11: =IF(OR(G11="Closed Lost",G11="",NOT(ISNUMBER(H11))),"",H11)
A12: 11 | B12: Enterprise | C12: Zarrah | D12: Unilab | E12: Executive Office VOs 18,19,20&21 | G12: Closed Won | H12: 34319675 | I12: 5147951.3 | J12: 45838 | K12: =IFERROR(VLOOKUP(G12,Stage_Lookup!$A$2:$B$8,2,0),"") | T12: =IF(OR(G12="Closed Lost",G12="",NOT(ISNUMBER(H12))),"",H12)
A13: 12 | B13: Enterprise | C13: Zarrah | D13: Unilab | E13: Executive office VOs 21-22 | G13: Closed Won | H13: 18788933 | I13: 3757786.6 | J13: 45899 | K13: =IFERROR(VLOOKUP(G13,Stage_Lookup!$A$2:$B$8,2,0),"") | T13: =IF(OR(G13="Closed Lost",G13="",NOT(ISNUMBER(H13))),"",H13)
A14: 13 | B14: Enterprise | C14: Zarrah | D14: Unilab | E14: VOs 21-22 | G14: Closed Won | H14: 18788933 | I14: 3757786.6 | J14: 45900 | K14: =IFERROR(VLOOKUP(G14,Stage_Lookup!$A$2:$B$8,2,0),"") | T14: =IF(OR(G14="Closed Lost",G14="",NOT(ISNUMBER(H14))),"",H14)
A15: 14 | B15: BPO Third Party | C15: Zarrah | D15: Savoy Living Concepts, Inc. | E15: Build Only | G15: Closed Won | H15: 14000000 | I15: 1680000 | J15: 46072 | K15: =IFERROR(VLOOKUP(G15,Stage_Lookup!$A$2:$B$8,2,0),"") | T15: =IF(OR(G15="Closed Lost",G15="",NOT(ISNUMBER(H15))),"",H15)
A16: 15 | B16: Enterprise - Large Scale | C16: Zarrah | D16: Jewelmer ATC | E16: Interior Fit-out Works - D&B | G16: Closed Won | H16: 12380832 | I16: 1857124.8 | J16: 46071 | K16: =IFERROR(VLOOKUP(G16,Stage_Lookup!$A$2:$B$8,2,0),"") | T16: =IF(OR(G16="Closed Lost",G16="",NOT(ISNUMBER(H16))),"",H16)
A17: 16 | B17: Enterprise - Large Scale | C17: Zarrah | D17: Jewelmer NAIA T3 | E17: Design and Build | G17: Closed Won | H17: 9632000 | I17: 1733760 | J17: 46072 | K17: =IFERROR(VLOOKUP(G17,Stage_Lookup!$A$2:$B$8,2,0),"") | T17: =IF(OR(G17="Closed Lost",G17="",NOT(ISNUMBER(H17))),"",H17)
A18: 17 | B18: Enterprise - Large Scale | C18: Zarrah | D18: Unilab | E18: VO 22 | G18: Closed Won | H18: 9588932.8 | I18: 2360795.2 | J18: 45901 | K18: =IFERROR(VLOOKUP(G18,Stage_Lookup!$A$2:$B$8,2,0),"") | T18: =IF(OR(G18="Closed Lost",G18="",NOT(ISNUMBER(H18))),"",H18)
A19: 18 | B19: Enterprise | C19: Zarrah | D19: HSP Global Business Services Inc | E19: End-user peripherals | G19: Closed Won | H19: 4852844.9 | I19: 485284.49 | J19: 45746 | K19: =IFERROR(VLOOKUP(G19,Stage_Lookup!$A$2:$B$8,2,0),"") | T19: =IF(OR(G19="Closed Lost",G19="",NOT(ISNUMBER(H19))),"",H19)
... A21: 20 | B21: Enterprise | C21: Zarrah | D21: VO#1 | E21: 10F All CX production | G21: Closed Won | H21: 1000000 | I21: 160000 | J21: 45991 | K21: =IFERROR(VLOOKUP(G21,Stage_Lookup!$A$2:$B$8,2,0),"") | T21: =IF(OR(G21="Closed Lost",G21="",NOT(ISNUMBER(H21))),"",H21)
A22: 21 | B22: Captive Shared Services | C22: Zarrah | D22: AFNI | E22: SMF T 3 D&B- 525 seats | F22: 3000 | G22: Opportunity Creation | H22: 120000000 | I22: 24000000 | J22: 46203 | K22: =IFERROR(VLOOKUP(G22,Stage_Lookup!$A$2:$B$8,2,0),"") | O22: RFP will be released week of May 18,2026 | T22: =IF(OR(G22="Closed Lost",G22="",NOT(ISNUMBER(H22))),"",H22)
A23: 22 | B23: Captive Shared Services | C23: Zarrah | D23: AFNI SMF T3 | E23: Dell - 525 seats | G23: Opportunity Creation | H23: 30000000 | I23: 6000000 | J23: 46203 | K23: =IFERROR(VLOOKUP(G23,Stage_Lookup!$A$2:$B$8,2,0),"") | O23: RFP will be released week of May 18,2026 | T23: =IF(OR(G23="Closed Lost",G23="",NOT(ISNUMBER(H23))),"",H23)
A24: 23 | B24: COPY ROW FOR NEW OPPORTUNITY | C24: Zarrah | D24: AFNI SMF T3 | E24: Cisco | G24: Opportunity Creation | H24: 30000000 | I24: 6000000 | J24: 46203 | K24: =IFERROR(VLOOKUP(G24,Stage_Lookup!$A$2:$B$8,2,0),"") | O24: RFP will be released week of May 18,2026 | T24: =IF(OR(G24="Closed Lost",G24="",NOT(ISNUMBER(H24))),"",H24)
A25: 24 | B25: Enterprise | C25: Zarrah | D25: FLT | E25: Build Only | G25: Closed Lost | H25: 23700228 | I25: 4740045.6 | J25: 46142 | K25: =IFERROR(VLOOKUP(G25,Stage_Lookup!$A$2:$B$8,2,0),"") | T25: =IF(OR(G25="Closed Lost",G25="",NOT(ISNUMBER(H25))),"",H25)
A26: 25 | B26: Captive Shared Services | C26: Zarrah | D26: Health First | E26: Williams Level A Ph2 expansion | G26: BOM Submission | H26: 33209522 | I26: 5977714 | J26: 46173 | K26: =IFERROR(VLOOKUP(G26,Stage_Lookup!$A$2:$B$8,2,0),"") | O26: Based on the last touchpoint with the client on April 15,2026, they are still evaluating all proposals from the bidders. | T26: =IF(OR(G26="Closed Lost",G26="",NOT(ISNUMBER(H26))),"",H26)
A27: 26 | B27: Enterprise | C27: Zarrah | D27: Health First | E27: HDSI Hemodialysis | G27: BOM Submission | H27: 23462869 | I27: 4223316.5 | J27: 46173 | K27: =IFERROR(VLOOKUP(G27,Stage_Lookup!$A$2:$B$8,2,0),"") | O27: Based on the last touchpoint with the client on April 15, 2026, they are still evaluating all proposals from the bidders. | T27: =IF(OR(G27="Closed Lost",G27="",NOT(ISNUMBER(H27))),"",H27)
A28: 27 | B28: Enterprise | C28: Zarrah | D28: HGS | E28: HGS Bridgetowne | G28: BOM Submission | H28: 1404896.9 | I28: 25288145 | J28: 46173 | K28: =IFERROR(VLOOKUP(G28,Stage_Lookup!$A$2:$B$8,2,0),"") | T28: =IF(OR(G28="Closed Lost",G28="",NOT(ISNUMBER(H28))),"",H28)
A29: 28 | B29: Enterprise-Large scale | C29: Zarrah | D29: Acquire | E29: Build-Recruitment Hub | G29: Closed Won | H29: 7423409.2 | I29: 890809.11 | J29: 46142 | K29: =IFERROR(VLOOKUP(G29,Stage_Lookup!$A$2:$B$8,2,0),"") | T29: =IF(OR(G29="Closed Lost",G29="",NOT(ISNUMBER(H29))),"",H29)
A30: 29 | B30: Enterprise-Large scale | C30: Zarrah | D30: Focus Global Inc | E30: Tempur-Maison Mall | G30: Closed Lost | H30: 10000000 | I30: 2000000 | J30: 46142 | K30: =IFERROR(VLOOKUP(G30,Stage_Lookup!$A$2:$B$8,2,0),"") | O30: We were not able to conduct the site inspection or submit our proposal. This was awarded to another vendor. | T30: =IF(OR(G30="Closed Lost",G30="",NOT(ISNUMBER(H30))),"",H30)
A31: 30 | B31: BPO Third Party | C31: Zarrah | D31: Jewelmer Greenbelt 5 | E31: Renovation | G31: Opportunity Creation | H31: 3000000 | I31: 600000 | J31: 46203 | K31: =IFERROR(VLOOKUP(G31,Stage_Lookup!$A$2:$B$8,2,0),"") | O31: According to Diane, all renovation projects are still in the budgeting stage. They are currently prioritizing new retail shops, but the renovations are expected to proceed within the year | T31: =IF(OR(G31="Closed Lost",G31="",NOT(ISNUMBER(H31))),"",H31)
A32: 31 | B32: Enterprise | C32: Zarrah | D32: Jewelmer Shangrila BGC | E32: Design and Build Project | G32: Opportunity Creation | H32: 10000000 | I32: 2000000 | J32: 46203 | K32: =IFERROR(VLOOKUP(G32,Stage_Lookup!$A$2:$B$8,2,0),"") | O32: According to Diane, all renovation projects are still in the budgeting stage. They are currently prioritizing new retail shops, but the renovations are expected to proceed within the year | T32: =IF(OR(G32="Closed Lost",G32="",NOT(ISNUMBER(H32))),"",H32)
A33: 32 | B33: Enterprise | C33: Zarrah | D33: Jewelmer Shangrila EDSA | E33: Design and Build Project | G33: Opportunity Creation | H33: 10000000 | I33: 2000000 | J33: 46203 | K33: =IFERROR(VLOOKUP(G33,Stage_Lookup!$A$2:$B$8,2,0),"") | O33: According to Diane, all renovation projects are still in the budgeting stage. They are currently prioritizing new retail shops, but the renovations are expected to proceed within the year | T33: =IF(OR(G33="Closed Lost",G33="",NOT(ISNUMBER(H33))),"",H33)
A34: 33 | B34: Enterprise-Large scale | C34: Zarrah | D34: PTS Property Ventures , Inc | E34: 4 storey Bldg renovation works | G34: Closed Lost | H34: 30000000 | I34: 6000000 | J34: 46173 | K34: =IFERROR(VLOOKUP(G34,Stage_Lookup!$A$2:$B$8,2,0),"") | O34: We will decline this opportunity. Based on the site inspection report, the scope is purely structural, and the building is already very old. | T34: =IF(OR(G34="Closed Lost",G34="",NOT(ISNUMBER(H34))),"",H34)
A35: 34 | B35: Enterprise | C35: Zarrah | D35: Signature-Entreprise | E35: Renovation works-D&B | G35: Resubmission | H35: 70213261 | I35: 16149050 | J35: 46142 | K35: =IFERROR(VLOOKUP(G35,Stage_Lookup!$A$2:$B$8,2,0),"") | O35: Meeting with Ral on May 7,2026 to discuss this opportunity | T35: =IF(OR(G35="Closed Lost",G35="",NOT(ISNUMBER(H35))),"",H35)
A36: 35 | B36: Captive Shared Services | C36: Zarrah | D36: Sutherland | E36: Cam Sur 2 REnovation works | G36: Opportunity Creation | H36: 20000000 | I36: 4000000 | J36: 46174 | K36: =IFERROR(VLOOKUP(G36,Stage_Lookup!$A$2:$B$8,2,0),"") | O36: According to Ericson Chua, they will release a new RFP since this is a failed bid. | T36: =IF(OR(G36="Closed Lost",G36="",NOT(ISNUMBER(H36))),"",H36)
A37: 36 | B37: BPO Third Party | C37: Zarrah/House Acount | D37: LG Electronics | E37: Silver City T3-Business Innovation Center Build project | F37: 320 | G37: Negotiation | H37: 25789649 | I37: 3094757.9 | J37: 46173 | K37: =IFERROR(VLOOKUP(G37,Stage_Lookup!$A$2:$B$8,2,0),"") | O37: Based on April 27,2026 touchpoint with the client, they are still waiting for approval as they need to secure additional budget. | T37: =IF(OR(G37="Closed Lost",G37="",NOT(ISNUMBER(H37))),"",H37)
A38: 37 | B38: BPO Third Party | C38: Zarrah | D38: AFNI -SM Sta Rosa | E38: Office Fitout 7F Tower 3 | F38: 2500 | G38: Opportunity Creation | H38: 100000000 | I38: 15000000 | J38: 46203 | K38: =IFERROR(VLOOKUP(G38,Stage_Lookup!$A$2:$B$8,2,0),"") | O38: According to Flo, they are still finalizing the RFP | T38: =IF(OR(G38="Closed Lost",G38="",NOT(ISNUMBER(H38))),"",H38)
A39: 38 | B39: BPO Third Party | C39: Zarrah/House Acount | D39: Teleperformance | E39: FUSA/TUSA | G39: BOM Submission | H39: 203000000 | I39: 36540000 | J39: 46203 | K39: =IFERROR(VLOOKUP(G39,Stage_Lookup!$A$2:$B$8,2,0),"") | O39: Our final offer was submitted to the client on April 30, 2026. We are currently awaiting their approval. In the meantime, we will initiate a soft internal kickoff with the commercial and design teams to align on the layout schedule, renders, and bill of materials (BOM), ensuring everything stays within the ₱35K/sqm budget. | T39: =IF(OR(G39="Closed Lost",G39="",NOT(ISNUMBER(H39))),"",H39)
A40: 39 | B40: Shared services | C40: Zarrah/House Acount | D40: ASA Philippines | E40: Design and Build Project | F40: 957 | G40: BOM Submission | H40: 30000000 | I40: 6000000 | J40: 46173 | K40: =IFERROR(VLOOKUP(G40,Stage_Lookup!$A$2:$B$8,2,0),"") | T40: =IF(OR(G40="Closed Lost",G40="",NOT(ISNUMBER(H40))),"",H40)
A41: 40 | K41: =IFERROR(VLOOKUP(G41,Stage_Lookup!$A$2:$B$8,2,0),"") | T41: =IF(OR(G41="Closed Lost",G41="",NOT(ISNUMBER(H41))),"",H41)
A42: 41 | K42: =IFERROR(VLOOKUP(G42,Stage_Lookup!$A$2:$B$8,2,0),"") | T42: =IF(OR(G42="Closed Lost",G42="",NOT(ISNUMBER(H42))),"",H42)
A43: 42 | K43: =IFERROR(VLOOKUP(G43,Stage_Lookup!$A$2:$B$8,2,0),"") | T43: =IF(OR(G43="Closed Lost",G43="",NOT(ISNUMBER(H43))),"",H43)
A44: 43 | K44: =IFERROR(VLOOKUP(G44,Stage_Lookup!$A$2:$B$8,2,0),"") | T44: =IF(OR(G44="Closed Lost",G44="",NOT(ISNUMBER(H44))),"",H44)
A45: 44 | K45: =IFERROR(VLOOKUP(G45,Stage_Lookup!$A$2:$B$8,2,0),"") | T45: =IF(OR(G45="Closed Lost",G45="",NOT(ISNUMBER(H45))),"",H45)
A46: 45 | K46: =IFERROR(VLOOKUP(G46,Stage_Lookup!$A$2:$B$8,2,0),"") | T46: =IF(OR(G46="Closed Lost",G46="",NOT(ISNUMBER(H46))),"",H46)
A47: 46 | K47: =IFERROR(VLOOKUP(G47,Stage_Lookup!$A$2:$B$8,2,0),"") | T47: =IF(OR(G47="Closed Lost",G47="",NOT(ISNUMBER(H47))),"",H47)
A48: 47 | K48: =IFERROR(VLOOKUP(G48,Stage_Lookup!$A$2:$B$8,2,0),"") | T48: =IF(OR(G48="Closed Lost",G48="",NOT(ISNUMBER(H48))),"",H48)
A49: 48 | K49: =IFERROR(VLOOKUP(G49,Stage_Lookup!$A$2:$B$8,2,0),"") | T49: =IF(OR(G49="Closed Lost",G49="",NOT(ISNUMBER(H49))),"",H49)
A50: 49 | K50: =IFERROR(VLOOKUP(G50,Stage_Lookup!$A$2:$B$8,2,0),"") | T50: =IF(OR(G50="Closed Lost",G50="",NOT(ISNUMBER(H50))),"",H50)
A51: 50 | K51: =IFERROR(VLOOKUP(G51,Stage_Lookup!$A$2:$B$8,2,0),"") | T51: =IF(OR(G51="Closed Lost",G51="",NOT(ISNUMBER(H51))),"",H51)
A52: 51 | K52: =IFERROR(VLOOKUP(G52,Stage_Lookup!$A$2:$B$8,2,0),"") | T52: =IF(OR(G52="Closed Lost",G52="",NOT(ISNUMBER(H52))),"",H52)
... A201: 200 | K201: =IFERROR(VLOOKUP(G201,Stage_Lookup!$A$2:$B$8,2,0),"") | T201: =IF(OR(G201="Closed Lost",G201="",NOT(ISNUMBER(H201))),"",H201)
A202: TOTALS | C202: # DEALS: | D202: =COUNTA(D2:D201) | F202: =SUM(F2:F201) | H202: =SUM(H2:H201) | I202: =SUM(I2:I201)

Sheet Home-Coverage
A1: SALES COVERAGE — Person C
A2: ℹ Rows are unlimited. Add as many opportunities as needed. Totals row auto-updates.
A3: 1 | B3: BDM | C3: ACCOUNT NAME | D3: OPPORTUNITY TYPE | E3: OPPORTUNITY DETAILS | F3: AREA (IN SQM) | G3: TCV | H3: GP | I3: CLOSING DATE | J3: REMARKS | K3: PROBABILITY
A4: 2 | B4: Home | C4: EY PH Lead | D4: Fit out | F4: 2500 | G4: 112500000 | H4: =G4*20% | I4: 46203 | J4: EY led opportunity, client Meeting rescheduled
A5: 3 | B5: Home | C5: KPMG Philippines_RG Manabat | D5: Fit out | E5: Expansion | F5: 7500 | G5: =40000*F5 | H5: =G5*20% | I5: 46537 | J5: Meeting May 5
A6: 4 | B6: Home | C6: Fourth Iq | D6: Fit out | J6: Teams Meeting with CEO May 06
A7: 5 | B7: Home | C7: Tata Consultacy | D7: Fit out
A8: 6 | B8: Home | C8: PLDT Filinvest | D8: CSA Fit Out
A9: 7
A10: 8
A11: 9
A12: 10
A13: 11
A14: 12
A15: 13
A16: 14
A17: 15
A18: 16
A19: 17
A20: 18
... A202: 200
A203: TOTALS | B203: # DEALS: | C203: =COUNTA(C3:C202) | F203: =SUM(F3:F202) | G203: =SUM(G3:G202) | H203: =SUM(H3:H202)

Sheet Home-Conversion
A1: SALES CONVERSION — Person C | R1: Stage | S1: Prob %
A2: ℹ Rows are unlimited. Add as many opportunities as needed. Totals row auto-updates. | R2: Closed Lost | S2: 0
A3: 1 | B3: Industry Segment | C3: Coverage | D3: ACCOUNT NAME | E3: OPPORTUNITY TYPE | F3: AREA (IN SQM) | G3: OPPORTUNITY STAGE | H3: TCV (VAT EX) | I3: GP (VAT EX) | J3: CLOSING DATE | K3: PROBABILITY (Auto) | L3: Project Start Date | M3: Project Completion | N3: BOM SUBMISSION | O3: REMARKS TO BE UPDATED BY SALES WEEKLY | P3: REMARKS TO BE UPDATED BY COMMERCIAL | R3: Opportunity Creation | S3: 0.1 | T3: Eligible TCV (helper)
A4: 2 | B4: Government | C4: Home | D4: PCHCC CP12.1 | E4: Fit Out | F4: 41453.21 | G4: Resubmission | H4: 625000000 | I4: =H4*0.23 | J4: 46142 | K4: =IFERROR(VLOOKUP(G4,Stage_Lookup!$A$2:$B$8,2,0),"") | O4: For Clarification Week of April 20 | R4: Scoping | S4: 0.3 | T4: =IF(OR(G4="Closed Lost",G4="",NOT(ISNUMBER(H4))),"",H4)
A5: 3 | B5: Government | C5: Home | D5: PCHCC CP30 | E5: Auxiliary- CCTV&Access | F5: 41453.21 | G5: Resubmission | H5: 14623376 | I5: =H5*0.2 | J5: 46142 | K5: =IFERROR(VLOOKUP(G5,Stage_Lookup!$A$2:$B$8,2,0),"") | R5: BOM Submission | S5: 0.5 | T5: =IF(OR(G5="Closed Lost",G5="",NOT(ISNUMBER(H5))),"",H5)
A6: 4 | B6: Enterprise | C6: Home | D6: Ground Floor Fit Out | E6: Fit Out Finishing | F6: 369.79 | G6: Resubmission | H6: 15613784 | I6: =H6*0.25 | J6: 46142 | K6: =IFERROR(VLOOKUP(G6,Stage_Lookup!$A$2:$B$8,2,0),"") | R6: Resubmission | S6: 0.7 | T6: =IF(OR(G6="Closed Lost",G6="",NOT(ISNUMBER(H6))),"",H6)
A7: 5 | B7: Enterprise | C7: Home | D7: Shimz | E7: Work.Able | F7: 1039 | G7: Resubmission | H7: 47926008 | I7: =H7*0.2 | K7: =IFERROR(VLOOKUP(G7,Stage_Lookup!$A$2:$B$8,2,0),"") | R7: Negotiation | S7: 0.9 | T7: =IF(OR(G7="Closed Lost",G7="",NOT(ISNUMBER(H7))),"",H7)
A8: 6 | B8: Enterprise | C8: Home | D8: Shimz | E8: Nura | F8: 997 | G8: Resubmission | H8: =28475105.12+32184258.84 | I8: =H8*0.2 | K8: =IFERROR(VLOOKUP(G8,Stage_Lookup!$A$2:$B$8,2,0),"") | R8: Closed Won | S8: 1 | T8: =IF(OR(G8="Closed Lost",G8="",NOT(ISNUMBER(H8))),"",H8)
A9: 7 | B9: Enterprise | C9: Home | D9: Shimz | E9: FLT | G9: Scoping | H9: 10000000 | I9: =H9*0.2 | K9: =IFERROR(VLOOKUP(G9,Stage_Lookup!$A$2:$B$8,2,0),"") | T9: =IF(OR(G9="Closed Lost",G9="",NOT(ISNUMBER(H9))),"",H9)
A10: 8 | B10: Enterprise | C10: Home | D10: PCHCC CP10 | E10: Electrical / Aux | F10: 45000 | G10: Closed Won | H10: ₱238,868,273 | I10: 42996289 | J10: 46054 | K10: =IFERROR(VLOOKUP(G10,Stage_Lookup!$A$2:$B$8,2,0),"") | T10: =IF(OR(G10="Closed Lost",G10="",NOT(ISNUMBER(H10))),"",H10)
A11: 9 | B11: Enterprise | C11: Home | D11: CCT_Ivoclar | E11: Fit Out | G11: Closed Won | H11: ₱5,300,000 | I11: 1060000 | J11: 46071 | K11: =IFERROR(VLOOKUP(G11,Stage_Lookup!$A$2:$B$8,2,0),"") | T11: =IF(OR(G11="Closed Lost",G11="",NOT(ISNUMBER(H11))),"",H11)
A12: 10 | B12: Enterprise | C12: Home | D12: PCHCC CP12.A.2 | E12: ICT_AV_Cabling | G12: BOM Submission | H12: 671765762 | I12: =H12*34% | J12: 46188 | K12: =IFERROR(VLOOKUP(G12,Stage_Lookup!$A$2:$B$8,2,0),"") | T12: =IF(OR(G12="Closed Lost",G12="",NOT(ISNUMBER(H12))),"",H12)
A13: 11 | B13: Enterprise | C13: Home | D13: PCHCC CP12.B | E13: Joineries | G13: BOM Submission | H13: 133169354 | I13: =H13*23% | J13: 46249 | K13: =IFERROR(VLOOKUP(G13,Stage_Lookup!$A$2:$B$8,2,0),"") | T13: =IF(OR(G13="Closed Lost",G13="",NOT(ISNUMBER(H13))),"",H13)
A14: 12 | B14: Enterprise | C14: Home | D14: PCHCC CP25 | E14: Sytem Furniture | G14: BOM Submission | H14: 185016573 | I14: =H14*23% | J14: 46219 | K14: =IFERROR(VLOOKUP(G14,Stage_Lookup!$A$2:$B$8,2,0),"") | T14: =IF(OR(G14="Closed Lost",G14="",NOT(ISNUMBER(H14))),"",H14)
A15: 13 | K15: =IFERROR(VLOOKUP(G15,Stage_Lookup!$A$2:$B$8,2,0),"") | T15: =IF(OR(G15="Closed Lost",G15="",NOT(ISNUMBER(H15))),"",H15)
A16: 14 | K16: =IFERROR(VLOOKUP(G16,Stage_Lookup!$A$2:$B$8,2,0),"") | T16: =IF(OR(G16="Closed Lost",G16="",NOT(ISNUMBER(H16))),"",H16)
A17: 15 | K17: =IFERROR(VLOOKUP(G17,Stage_Lookup!$A$2:$B$8,2,0),"") | T17: =IF(OR(G17="Closed Lost",G17="",NOT(ISNUMBER(H17))),"",H17)
A18: 16 | K18: =IFERROR(VLOOKUP(G18,Stage_Lookup!$A$2:$B$8,2,0),"") | T18: =IF(OR(G18="Closed Lost",G18="",NOT(ISNUMBER(H18))),"",H18)
A19: 17 | K19: =IFERROR(VLOOKUP(G19,Stage_Lookup!$A$2:$B$8,2,0),"") | T19: =IF(OR(G19="Closed Lost",G19="",NOT(ISNUMBER(H19))),"",H19)
A20: 18 | K20: =IFERROR(VLOOKUP(G20,Stage_Lookup!$A$2:$B$8,2,0),"") | T20: =IF(OR(G20="Closed Lost",G20="",NOT(ISNUMBER(H20))),"",H20)
A21: 19 | K21: =IFERROR(VLOOKUP(G21,Stage_Lookup!$A$2:$B$8,2,0),"") | T21: =IF(OR(G21="Closed Lost",G21="",NOT(ISNUMBER(H21))),"",H21)
A22: 20 | K22: =IFERROR(VLOOKUP(G22,Stage_Lookup!$A$2:$B$8,2,0),"") | T22: =IF(OR(G22="Closed Lost",G22="",NOT(ISNUMBER(H22))),"",H22)
A23: 21 | K23: =IFERROR(VLOOKUP(G23,Stage_Lookup!$A$2:$B$8,2,0),"") | T23: =IF(OR(G23="Closed Lost",G23="",NOT(ISNUMBER(H23))),"",H23)
A24: 22 | K24: =IFERROR(VLOOKUP(G24,Stage_Lookup!$A$2:$B$8,2,0),"") | T24: =IF(OR(G24="Closed Lost",G24="",NOT(ISNUMBER(H24))),"",H24)
A25: 23 | K25: =IFERROR(VLOOKUP(G25,Stage_Lookup!$A$2:$B$8,2,0),"") | T25: =IF(OR(G25="Closed Lost",G25="",NOT(ISNUMBER(H25))),"",H25)
A26: 24 | K26: =IFERROR(VLOOKUP(G26,Stage_Lookup!$A$2:$B$8,2,0),"") | T26: =IF(OR(G26="Closed Lost",G26="",NOT(ISNUMBER(H26))),"",H26)
... A202: 200 | K202: =IFERROR(VLOOKUP(G202,Stage_Lookup!$A$2:$B$8,2,0),"") | T202: =IF(OR(G202="Closed Lost",G202="",NOT(ISNUMBER(H202))),"",H202)
A203: TOTALS | C203: # DEALS: | D203: =COUNTA(D3:D202) | F203: =SUM(F3:F202) | H203: =SUM(H3:H202) | I203: =SUM(I3:I202)

Sheet Stage_Lookup
A1: Opportunity Stage | B1: Probability
A2: Closed Lost | B2: 0
A3: Opportunity Creation | B3: 0.1
A4: Scoping | B4: 0.3
A5: BOM Submission | B5: 0.5
A6: Resubmission | B6: 0.7
A7: Negotiation | B7: 0.9
A8: Closed Won | B8: 1

Sheet Consolidated Dashboard
A1: CONSOLIDATED SALES MONITORING DASHBOARD
A2: ⚡ All figures are live-linked from individual sheets. Update data in each person's sheet — this dashboard refreshes automatically.
A4: SECTION A — EXECUTIVE COMMITTEE (ExCom) PERFORMANCE SUMMARY
A5: Summary of Coverage and Conversion performance per sales person — for ExCom reporting.
A6: SALES PERSON | B6: TOTAL DEALS (COVERAGE) | C6: TOTAL AREA (SQM) | D6: TOTAL TCV (Coverage) | E6: TOTAL GP (Coverage) | F6: AVG TCV PER DEAL | G6: AVG GP PER DEAL
A7: Madine | B7: =COUNTA('Madine- Coverage'!C3:C202) | C7: ='Madine- Coverage'!F203 | D7: ='Madine- Coverage'!G203 | E7: ='Madine- Coverage'!H203 | F7: =IFERROR('Madine- Coverage'!G203/COUNTA('Madine- Coverage'!C3:C202),0) | G7: =IFERROR('Madine- Coverage'!H203/COUNTA('Madine- Coverage'!C3:C202),0)
A8: Zarrah | B8: =COUNTA('Zarrah- Coverage'!C3:C202) | C8: ='Zarrah- Coverage'!F203 | D8: ='Zarrah- Coverage'!G203 | E8: ='Zarrah- Coverage'!H203 | F8: =IFERROR('Zarrah- Coverage'!G203/COUNTA('Zarrah- Coverage'!C3:C202),0) | G8: =IFERROR('Zarrah- Coverage'!H203/COUNTA('Zarrah- Coverage'!C3:C202),0)
A9: Home | B9: =COUNTA('Home-Coverage'!C3:C202) | C9: ='Home-Coverage'!F203 | D9: ='Home-Coverage'!G203 | E9: ='Home-Coverage'!H203 | F9: =IFERROR('Home-Coverage'!G203/COUNTA('Home-Coverage'!C3:C202),0) | G9: =IFERROR('Home-Coverage'!H203/COUNTA('Home-Coverage'!C3:C202),0)
A10: TOTAL | B10: =SUM(B7:B9) | C10: =SUM(C7:C9) | D10: =SUM(D7:D9) | E10: =SUM(E7:E9) | F10: =IFERROR(D10/B10,0) | G10: =IFERROR(E10/B10,0)
A12: SALES PERSON | B12: TOTAL DEALS (CONVERSION) | C12: TOTAL AREA (SQM) | D12: TOTAL TCV (VAT EX) | E12: TOTAL GP (VAT EX) | F12: AVG TCV PER DEAL | G12: AVG GP PER DEAL | H12: GP MARGIN %
A13: Madine | B13: =COUNTA('Madine- Conversion'!D3:D202) | C13: ='Madine- Conversion'!F203 | D13: ='Madine- Conversion'!H203 | E13: ='Madine- Conversion'!I203 | F13: =IFERROR('Madine- Conversion'!H203/COUNTA('Madine- Conversion'!D3:D202),0) | G13: =IFERROR('Madine- Conversion'!I203/COUNTA('Madine- Conversion'!D3:D202),0) | H13: =IFERROR('Madine- Conversion'!I203/'Madine- Conversion'!H203,0)
A14: Zarrah | B14: =COUNTA('Zarrah-Conversion'!D2:D201) | C14: ='Zarrah-Conversion'!F202 | D14: ='Zarrah-Conversion'!H202 | E14: ='Zarrah-Conversion'!I202 | F14: =IFERROR('Zarrah-Conversion'!H202/COUNTA('Zarrah-Conversion'!D2:D201),0) | G14: =IFERROR('Zarrah-Conversion'!I202/COUNTA('Zarrah-Conversion'!D2:D201),0) | H14: =IFERROR('Zarrah-Conversion'!I202/'Zarrah-Conversion'!H202,0)
A15: Home | B15: =COUNTA('Home-Conversion'!D3:D202) | C15: ='Home-Conversion'!F203 | D15: ='Home-Conversion'!H203 | E15: ='Home-Conversion'!I203 | F15: =IFERROR('Home-Conversion'!H203/COUNTA('Home-Conversion'!D3:D202),0) | G15: =IFERROR('Home-Conversion'!I203/COUNTA('Home-Conversion'!D3:D202),0) | H15: =IFERROR('Home-Conversion'!I203/'Home-Conversion'!H203,0)
A16: TOTAL | B16: =SUM(B13:B15) | C16: =SUM(C13:C15) | D16: =SUM(D13:D15) | E16: =SUM(E13:E15) | F16: =IFERROR(D16/B16,0) | G16: =IFERROR(E16/B16,0) | H16: =IFERROR(E16/D16,0)
A18: CONVERSION PIPELINE BY STAGE — ALL PERSONS
A19: OPPORTUNITY STAGE (PROBABILITY) | B19: PERSON A DEALS | C19: PERSON B DEALS | D19: PERSON C DEALS | E19: TOTAL DEALS | F19: TOTAL TCV (VAT EX) | G19: TOTAL GP (VAT EX) | H19: WEIGHTED TCV (TCV × Prob %)
A20: Closed Lost (0%) | B20: =COUNTIF('Madine- Conversion'!G3:G202,"Closed Lost") | C20: =COUNTIF('Zarrah-Conversion'!G2:G201,"Closed Lost") | D20: =COUNTIF('Home-Conversion'!G3:G202,"Closed Lost") | E20: =SUM(B20:D20) | F20: =SUMIF('Madine- Conversion'!G3:G202,"Closed Lost",'Madine- Conversion'!H3:H202)+SUMIF('Zarrah-Conversion'!G2:G201,"Closed Lost",'Zarrah-Conversion'!H2:H201)+SUMIF('Home-Conversion'!G3:G202,"Closed Lost",'Home-Conversion'!H3:H202) | G20: =SUMIF('Madine- Conversion'!G3:G202,"Closed Lost",'Madine- Conversion'!I3:I202)+SUMIF('Zarrah-Conversion'!G2:G201,"Closed Lost",'Zarrah-Conversion'!I2:I201)+SUMIF('Home-Conversion'!G3:G202,"Closed Lost",'Home-Conversion'!I3:I202) | H20: =F20*0
A21: Opportunity Creation (10%) | B21: =COUNTIF('Madine- Conversion'!G3:G202,"Opportunity Creation") | C21: =COUNTIF('Zarrah-Conversion'!G2:G201,"Opportunity Creation") | D21: =COUNTIF('Home-Conversion'!G3:G202,"Opportunity Creation") | E21: =SUM(B21:D21) | F21: =SUMIF('Madine- Conversion'!G3:G202,"Opportunity Creation",'Madine- Conversion'!H3:H202)+SUMIF('Zarrah-Conversion'!G2:G201,"Opportunity Creation",'Zarrah-Conversion'!H2:H201)+SUMIF('Home-Conversion'!G3:G202,"Opportunity Creation",'Home-Conversion'!H3:H202) | G21: =SUMIF('Madine- Conversion'!G3:G202,"Opportunity Creation",'Madine- Conversion'!I3:I202)+SUMIF('Zarrah-Conversion'!G2:G201,"Opportunity Creation",'Zarrah-Conversion'!I2:I201)+SUMIF('Home-Conversion'!G3:G202,"Opportunity Creation",'Home-Conversion'!I3:I202) | H21: =F21*0.1
A22: Scoping (30%) | B22: =COUNTIF('Madine- Conversion'!G3:G202,"Scoping") | C22: =COUNTIF('Zarrah-Conversion'!G2:G201,"Scoping") | D22: =COUNTIF('Home-Conversion'!G3:G202,"Scoping") | E22: =SUM(B22:D22) | F22: =SUMIF('Madine- Conversion'!G3:G202,"Scoping",'Madine- Conversion'!H3:H202)+SUMIF('Zarrah-Conversion'!G2:G201,"Scoping",'Zarrah-Conversion'!H2:H201)+SUMIF('Home-Conversion'!G3:G202,"Scoping",'Home-Conversion'!H3:H202) | G22: =SUMIF('Madine- Conversion'!G3:G202,"Scoping",'Madine- Conversion'!I3:I202)+SUMIF('Zarrah-Conversion'!G2:G201,"Scoping",'Zarrah-Conversion'!I2:I201)+SUMIF('Home-Conversion'!G3:G202,"Scoping",'Home-Conversion'!I3:I202) | H22: =F22*0.3
A23: BOM Submission (50%) | B23: =COUNTIF('Madine- Conversion'!G3:G202,"BOM Submission") | C23: =COUNTIF('Zarrah-Conversion'!G2:G201,"BOM Submission") | D23: =COUNTIF('Home-Conversion'!G3:G202,"BOM Submission") | E23: =SUM(B23:D23) | F23: =SUMIF('Madine- Conversion'!G3:G202,"BOM Submission",'Madine- Conversion'!H3:H202)+SUMIF('Zarrah-Conversion'!G2:G201,"BOM Submission",'Zarrah-Conversion'!H2:H201)+SUMIF('Home-Conversion'!G3:G202,"BOM Submission",'Home-Conversion'!H3:H202) | G23: =SUMIF('Madine- Conversion'!G3:G202,"BOM Submission",'Madine- Conversion'!I3:I202)+SUMIF('Zarrah-Conversion'!G2:G201,"BOM Submission",'Zarrah-Conversion'!I2:I201)+SUMIF('Home-Conversion'!G3:G202,"BOM Submission",'Home-Conversion'!I3:I202) | H23: =F23*0.5
A24: Resubmission (70%) | B24: =COUNTIF('Madine- Conversion'!G3:G202,"Resubmission") | C24: =COUNTIF('Zarrah-Conversion'!G2:G201,"Resubmission") | D24: =COUNTIF('Home-Conversion'!G3:G202,"Resubmission") | E24: =SUM(B24:D24) | F24: =SUMIF('Madine- Conversion'!G3:G202,"Resubmission",'Madine- Conversion'!H3:H202)+SUMIF('Zarrah-Conversion'!G2:G201,"Resubmission",'Zarrah-Conversion'!H2:H201)+SUMIF('Home-Conversion'!G3:G202,"Resubmission",'Home-Conversion'!H3:H202) | G24: =SUMIF('Madine- Conversion'!G3:G202,"Resubmission",'Madine- Conversion'!I3:I202)+SUMIF('Zarrah-Conversion'!G2:G201,"Resubmission",'Zarrah-Conversion'!I2:I201)+SUMIF('Home-Conversion'!G3:G202,"Resubmission",'Home-Conversion'!I3:I202) | H24: =F24*0.7
A25: Negotiation (90%) | B25: =COUNTIF('Madine- Conversion'!G3:G202,"Negotiation") | C25: =COUNTIF('Zarrah-Conversion'!G2:G201,"Negotiation") | D25: =COUNTIF('Home-Conversion'!G3:G202,"Negotiation") | E25: =SUM(B25:D25) | F25: =SUMIF('Madine- Conversion'!G3:G202,"Negotiation",'Madine- Conversion'!H3:H202)+SUMIF('Zarrah-Conversion'!G2:G201,"Negotiation",'Zarrah-Conversion'!H2:H201)+SUMIF('Home-Conversion'!G3:G202,"Negotiation",'Home-Conversion'!H3:H202) | G25: =SUMIF('Madine- Conversion'!G3:G202,"Negotiation",'Madine- Conversion'!I3:I202)+SUMIF('Zarrah-Conversion'!G2:G201,"Negotiation",'Zarrah-Conversion'!I2:I201)+SUMIF('Home-Conversion'!G3:G202,"Negotiation",'Home-Conversion'!I3:I202) | H25: =F25*0.9
A26: Closed Won (100%) | B26: =COUNTIF('Madine- Conversion'!G3:G202,"Closed Won") | C26: =COUNTIF('Zarrah-Conversion'!G2:G201,"Closed Won") | D26: =COUNTIF('Home-Conversion'!G3:G202,"Closed Won") | E26: =SUM(B26:D26) | F26: =SUMIF('Madine- Conversion'!G3:G202,"Closed Won",'Madine- Conversion'!H3:H202)+SUMIF('Zarrah-Conversion'!G2:G201,"Closed Won",'Zarrah-Conversion'!H2:H201)+SUMIF('Home-Conversion'!G3:G202,"Closed Won",'Home-Conversion'!H3:H202) | G26: =SUMIF('Madine- Conversion'!G3:G202,"Closed Won",'Madine- Conversion'!I3:I202)+SUMIF('Zarrah-Conversion'!G2:G201,"Closed Won",'Zarrah-Conversion'!I2:I201)+SUMIF('Home-Conversion'!G3:G202,"Closed Won",'Home-Conversion'!I3:I202) | H26: =F26*1
A27: TOTAL | B27: =SUM(B20:B26) | C27: =SUM(C20:C26) | D27: =SUM(D20:D26) | E27: =SUM(E20:E26) | F27: =SUM(F20:F26) | G27: =SUM(G20:G26) | H27: =SUM(H20:H26)
A30: SECTION B — SALES COVERAGE DETAIL (ALL PERSONS)
A31: TOTAL GP (VAT EX) | B31: TOTAL GP (VAT EX) | C31: TOTAL GP (VAT EX) | D31: TOTAL GP (VAT EX) | E31: TOTAL GP (VAT EX) | F31: TOTAL GP (VAT EX) | G31: TOTAL GP (VAT EX) | H31: TOTAL GP (VAT EX) | I31: TOTAL GP (VAT EX) | J31: TOTAL GP (VAT EX) | K31: TOTAL GP (VAT EX) | L31: TOTAL GP (VAT EX)
A32: Person A | B32: ='Madine- Coverage'!A3 | C32: ='Madine- Coverage'!A3 | D32: ='Madine- Coverage'!C3 | E32: ='Madine- Coverage'!D3 | F32: ='Madine- Coverage'!E3 | G32: ='Madine- Coverage'!F3 | H32: ='Madine- Coverage'!G3 | I32: ='Madine- Coverage'!H3 | J32: ='Madine- Coverage'!I3 | K32: ='Madine- Coverage'!J3 | L32: ='Madine- Coverage'!K3
A33: Person A | B33: ='Madine- Coverage'!A4 | C33: ='Madine- Coverage'!A4 | D33: ='Madine- Coverage'!C4 | E33: ='Madine- Coverage'!D4 | F33: ='Madine- Coverage'!E4 | G33: ='Madine- Coverage'!F4 | H33: ='Madine- Coverage'!G4 | I33: ='Madine- Coverage'!H4 | J33: ='Madine- Coverage'!I4 | K33: ='Madine- Coverage'!J4 | L33: ='Madine- Coverage'!K4
A34: Person A | B34: ='Madine- Coverage'!A5 | C34: ='Madine- Coverage'!A5 | D34: ='Madine- Coverage'!C5 | E34: ='Madine- Coverage'!D5 | F34: ='Madine- Coverage'!E5 | G34: ='Madine- Coverage'!F5 | H34: ='Madine- Coverage'!G5 | I34: ='Madine- Coverage'!H5 | J34: ='Madine- Coverage'!I5 | K34: ='Madine- Coverage'!J5 | L34: ='Madine- Coverage'!K5
A35: Person A | B35: ='Madine- Coverage'!A6 | C35: ='Madine- Coverage'!A6 | D35: ='Madine- Coverage'!C6 | E35: ='Madine- Coverage'!D6 | F35: ='Madine- Coverage'!E6 | G35: ='Madine- Coverage'!F6 | H35: ='Madine- Coverage'!G6 | I35: ='Madine- Coverage'!H6 | J35: ='Madine- Coverage'!I6 | K35: ='Madine- Coverage'!J6 | L35: ='Madine- Coverage'!K6
A36: Person A | B36: ='Madine- Coverage'!A7 | C36: ='Madine- Coverage'!A7 | D36: ='Madine- Coverage'!C7 | E36: ='Madine- Coverage'!D7 | F36: ='Madine- Coverage'!E7 | G36: ='Madine- Coverage'!F7 | H36: ='Madine- Coverage'!G7 | I36: ='Madine- Coverage'!H7 | J36: ='Madine- Coverage'!I7 | K36: ='Madine- Coverage'!J7 | L36: ='Madine- Coverage'!K7
A37: Person A | B37: ='Madine- Coverage'!A8 | C37: ='Madine- Coverage'!A8 | D37: ='Madine- Coverage'!C8 | E37: ='Madine- Coverage'!D8 | F37: ='Madine- Coverage'!E8 | G37: ='Madine- Coverage'!F8 | H37: ='Madine- Coverage'!G8 | I37: ='Madine- Coverage'!H8 | J37: ='Madine- Coverage'!I8 | K37: ='Madine- Coverage'!J8 | L37: ='Madine- Coverage'!K8
A38: Person A | B38: ='Madine- Coverage'!A9 | C38: ='Madine- Coverage'!A9 | D38: ='Madine- Coverage'!C9 | E38: ='Madine- Coverage'!D9 | F38: ='Madine- Coverage'!E9 | G38: ='Madine- Coverage'!F9 | H38: ='Madine- Coverage'!G9 | I38: ='Madine- Coverage'!H9 | J38: ='Madine- Coverage'!I9 | K38: ='Madine- Coverage'!J9 | L38: ='Madine- Coverage'!K9
A39: Person A | B39: ='Madine- Coverage'!A10 | C39: ='Madine- Coverage'!A10 | D39: ='Madine- Coverage'!C10 | E39: ='Madine- Coverage'!D10 | F39: ='Madine- Coverage'!E10 | G39: ='Madine- Coverage'!F10 | H39: ='Madine- Coverage'!G10 | I39: ='Madine- Coverage'!H10 | J39: ='Madine- Coverage'!I10 | K39: ='Madine- Coverage'!J10 | L39: ='Madine- Coverage'!K10
A40: Person A | B40: ='Madine- Coverage'!A11 | C40: ='Madine- Coverage'!A11 | D40: ='Madine- Coverage'!C11 | E40: ='Madine- Coverage'!D11 | F40: ='Madine- Coverage'!E11 | G40: ='Madine- Coverage'!F11 | H40: ='Madine- Coverage'!G11 | I40: ='Madine- Coverage'!H11 | J40: ='Madine- Coverage'!I11 | K40: ='Madine- Coverage'!J11 | L40: ='Madine- Coverage'!K11
A41: Person A | B41: ='Madine- Coverage'!A12 | C41: ='Madine- Coverage'!A12 | D41: ='Madine- Coverage'!C12 | E41: ='Madine- Coverage'!D12 | F41: ='Madine- Coverage'!E12 | G41: ='Madine- Coverage'!F12 | H41: ='Madine- Coverage'!G12 | I41: ='Madine- Coverage'!H12 | J41: ='Madine- Coverage'!I12 | K41: ='Madine- Coverage'!J12 | L41: ='Madine- Coverage'!K12
A42: Person A | B42: ='Madine- Coverage'!A13 | C42: ='Madine- Coverage'!A13 | D42: ='Madine- Coverage'!C13 | E42: ='Madine- Coverage'!D13 | F42: ='Madine- Coverage'!E13 | G42: ='Madine- Coverage'!F13 | H42: ='Madine- Coverage'!G13 | I42: ='Madine- Coverage'!H13 | J42: ='Madine- Coverage'!I13 | K42: ='Madine- Coverage'!J13 | L42: ='Madine- Coverage'!K13
A43: Person A | B43: ='Madine- Coverage'!A14 | C43: ='Madine- Coverage'!A14 | D43: ='Madine- Coverage'!C14 | E43: ='Madine- Coverage'!D14 | F43: ='Madine- Coverage'!E14 | G43: ='Madine- Coverage'!F14 | H43: ='Madine- Coverage'!G14 | I43: ='Madine- Coverage'!H14 | J43: ='Madine- Coverage'!I14 | K43: ='Madine- Coverage'!J14 | L43: ='Madine- Coverage'!K14
... A231: Person A | B231: ='Madine- Coverage'!A202 | C231: ='Madine- Coverage'!A202 | D231: ='Madine- Coverage'!C202 | E231: ='Madine- Coverage'!D202 | F231: ='Madine- Coverage'!E202 | G231: ='Madine- Coverage'!F202 | H231: ='Madine- Coverage'!G202 | I231: ='Madine- Coverage'!H202 | J231: ='Madine- Coverage'!I202 | K231: ='Madine- Coverage'!J202 | L231: ='Madine- Coverage'!K202
A232: Person B | B232: ='Zarrah- Coverage'!A3 | C232: ='Zarrah- Coverage'!A3 | D232: ='Zarrah- Coverage'!C3 | E232: ='Zarrah- Coverage'!D3 | F232: ='Zarrah- Coverage'!E3 | G232: ='Zarrah- Coverage'!F3 | H232: ='Zarrah- Coverage'!G3 | I232: ='Zarrah- Coverage'!H3 | J232: ='Zarrah- Coverage'!I3 | K232: ='Zarrah- Coverage'!J3 | L232: ='Zarrah- Coverage'!K3
A233: Person B | B233: ='Zarrah- Coverage'!A4 | C233: ='Zarrah- Coverage'!A4 | D233: ='Zarrah- Coverage'!C4 | E233: ='Zarrah- Coverage'!D4 | F233: ='Zarrah- Coverage'!E4 | G233: ='Zarrah- Coverage'!F4 | H233: ='Zarrah- Coverage'!G4 | I233: ='Zarrah- Coverage'!H4 | J233: ='Zarrah- Coverage'!I4 | K233: ='Zarrah- Coverage'!J4 | L233: ='Zarrah- Coverage'!K4
A234: Person B | B234: ='Zarrah- Coverage'!A5 | C234: ='Zarrah- Coverage'!A5 | D234: ='Zarrah- Coverage'!C5 | E234: ='Zarrah- Coverage'!D5 | F234: ='Zarrah- Coverage'!E5 | G234: ='Zarrah- Coverage'!F5 | H234: ='Zarrah- Coverage'!G5 | I234: ='Zarrah- Coverage'!H5 | J234: ='Zarrah- Coverage'!I5 | K234: ='Zarrah- Coverage'!J5 | L234: ='Zarrah- Coverage'!K5
A235: Person B | B235: ='Zarrah- Coverage'!A6 | C235: ='Zarrah- Coverage'!A6 | D235: ='Zarrah- Coverage'!C6 | E235: ='Zarrah- Coverage'!D6 | F235: ='Zarrah- Coverage'!E6 | G235: ='Zarrah- Coverage'!F6 | H235: ='Zarrah- Coverage'!G6 | I235: ='Zarrah- Coverage'!H6 | J235: ='Zarrah- Coverage'!I6 | K235: ='Zarrah- Coverage'!J6 | L235: ='Zarrah- Coverage'!K6
A236: Person B | B236: ='Zarrah- Coverage'!A7 | C236: ='Zarrah- Coverage'!A7 | D236: ='Zarrah- Coverage'!C7 | E236: ='Zarrah- Coverage'!D7 | F236: ='Zarrah- Coverage'!E7 | G236: ='Zarrah- Coverage'!F7 | H236: ='Zarrah- Coverage'!G7 | I236: ='Zarrah- Coverage'!H7 | J236: ='Zarrah- Coverage'!I7 | K236: ='Zarrah- Coverage'!J7 | L236: ='Zarrah- Coverage'!K7
A237: Person B | B237: ='Zarrah- Coverage'!A8 | C237: ='Zarrah- Coverage'!A8 | D237: ='Zarrah- Coverage'!C8 | E237: ='Zarrah- Coverage'!D8 | F237: ='Zarrah- Coverage'!E8 | G237: ='Zarrah- Coverage'!F8 | H237: ='Zarrah- Coverage'!G8 | I237: ='Zarrah- Coverage'!H8 | J237: ='Zarrah- Coverage'!I8 | K237: ='Zarrah- Coverage'!J8 | L237: ='Zarrah- Coverage'!K8
A238: Person B | B238: ='Zarrah- Coverage'!A9 | C238: ='Zarrah- Coverage'!A9 | D238: ='Zarrah- Coverage'!C9 | E238: ='Zarrah- Coverage'!D9 | F238: ='Zarrah- Coverage'!E9 | G238: ='Zarrah- Coverage'!F9 | H238: ='Zarrah- Coverage'!G9 | I238: ='Zarrah- Coverage'!H9 | J238: ='Zarrah- Coverage'!I9 | K238: ='Zarrah- Coverage'!J9 | L238: ='Zarrah- Coverage'!K9
A239: Person B | B239: ='Zarrah- Coverage'!A10 | C239: ='Zarrah- Coverage'!A10 | D239: ='Zarrah- Coverage'!C10 | E239: ='Zarrah- Coverage'!D10 | F239: ='Zarrah- Coverage'!E10 | G239: ='Zarrah- Coverage'!F10 | H239: ='Zarrah- Coverage'!G10 | I239: ='Zarrah- Coverage'!H10 | J239: ='Zarrah- Coverage'!I10 | K239: ='Zarrah- Coverage'!J10 | L239: ='Zarrah- Coverage'!K10
A240: Person B | B240: ='Zarrah- Coverage'!A11 | C240: ='Zarrah- Coverage'!A11 | D240: ='Zarrah- Coverage'!C11 | E240: ='Zarrah- Coverage'!D11 | F240: ='Zarrah- Coverage'!E11 | G240: ='Zarrah- Coverage'!F11 | H240: ='Zarrah- Coverage'!G11 | I240: ='Zarrah- Coverage'!H11 | J240: ='Zarrah- Coverage'!I11 | K240: ='Zarrah- Coverage'!J11 | L240: ='Zarrah- Coverage'!K11
A241: Person B | B241: ='Zarrah- Coverage'!A12 | C241: ='Zarrah- Coverage'!A12 | D241: ='Zarrah- Coverage'!C12 | E241: ='Zarrah- Coverage'!D12 | F241: ='Zarrah- Coverage'!E12 | G241: ='Zarrah- Coverage'!F12 | H241: ='Zarrah- Coverage'!G12 | I241: ='Zarrah- Coverage'!H12 | J241: ='Zarrah- Coverage'!I12 | K241: ='Zarrah- Coverage'!J12 | L241: ='Zarrah- Coverage'!K12
A242: Person B | B242: ='Zarrah- Coverage'!A13 | C242: ='Zarrah- Coverage'!A13 | D242: ='Zarrah- Coverage'!C13 | E242: ='Zarrah- Coverage'!D13 | F242: ='Zarrah- Coverage'!E13 | G242: ='Zarrah- Coverage'!F13 | H242: ='Zarrah- Coverage'!G13 | I242: ='Zarrah- Coverage'!H13 | J242: ='Zarrah- Coverage'!I13 | K242: ='Zarrah- Coverage'!J13 | L242: ='Zarrah- Coverage'!K13
A243: Person B | B243: ='Zarrah- Coverage'!A14 | C243: ='Zarrah- Coverage'!A14 | D243: ='Zarrah- Coverage'!C14 | E243: ='Zarrah- Coverage'!D14 | F243: ='Zarrah- Coverage'!E14 | G243: ='Zarrah- Coverage'!F14 | H243: ='Zarrah- Coverage'!G14 | I243: ='Zarrah- Coverage'!H14 | J243: ='Zarrah- Coverage'!I14 | K243: ='Zarrah- Coverage'!J14 | L243: ='Zarrah- Coverage'!K14
... A431: Person B | B431: ='Zarrah- Coverage'!A202 | C431: ='Zarrah- Coverage'!A202 | D431: ='Zarrah- Coverage'!C202 | E431: ='Zarrah- Coverage'!D202 | F431: ='Zarrah- Coverage'!E202 | G431: ='Zarrah- Coverage'!F202 | H431: ='Zarrah- Coverage'!G202 | I431: ='Zarrah- Coverage'!H202 | J431: ='Zarrah- Coverage'!I202 | K431: ='Zarrah- Coverage'!J202 | L431: ='Zarrah- Coverage'!K202
A432: Person C | B432: ='Home-Coverage'!A3 | C432: ='Home-Coverage'!A3 | D432: ='Home-Coverage'!C3 | E432: ='Home-Coverage'!D3 | F432: ='Home-Coverage'!E3 | G432: ='Home-Coverage'!F3 | H432: ='Home-Coverage'!G3 | I432: ='Home-Coverage'!H3 | J432: ='Home-Coverage'!I3 | K432: ='Home-Coverage'!J3 | L432: ='Home-Coverage'!K3
A433: Person C | B433: ='Home-Coverage'!A4 | C433: ='Home-Coverage'!A4 | D433: ='Home-Coverage'!C4 | E433: ='Home-Coverage'!D4 | F433: ='Home-Coverage'!E4 | G433: ='Home-Coverage'!F4 | H433: ='Home-Coverage'!G4 | I433: ='Home-Coverage'!H4 | J433: ='Home-Coverage'!I4 | K433: ='Home-Coverage'!J4 | L433: ='Home-Coverage'!K4
A434: Person C | B434: ='Home-Coverage'!A5 | C434: ='Home-Coverage'!A5 | D434: ='Home-Coverage'!C5 | E434: ='Home-Coverage'!D5 | F434: ='Home-Coverage'!E5 | G434: ='Home-Coverage'!F5 | H434: ='Home-Coverage'!G5 | I434: ='Home-Coverage'!H5 | J434: ='Home-Coverage'!I5 | K434: ='Home-Coverage'!J5 | L434: ='Home-Coverage'!K5
A435: Person C | B435: ='Home-Coverage'!A6 | C435: ='Home-Coverage'!A6 | D435: ='Home-Coverage'!C6 | E435: ='Home-Coverage'!D6 | F435: ='Home-Coverage'!E6 | G435: ='Home-Coverage'!F6 | H435: ='Home-Coverage'!G6 | I435: ='Home-Coverage'!H6 | J435: ='Home-Coverage'!I6 | K435: ='Home-Coverage'!J6 | L435: ='Home-Coverage'!K6
A436: Person C | B436: ='Home-Coverage'!A7 | C436: ='Home-Coverage'!A7 | D436: ='Home-Coverage'!C7 | E436: ='Home-Coverage'!D7 | F436: ='Home-Coverage'!E7 | G436: ='Home-Coverage'!F7 | H436: ='Home-Coverage'!G7 | I436: ='Home-Coverage'!H7 | J436: ='Home-Coverage'!I7 | K436: ='Home-Coverage'!J7 | L436: ='Home-Coverage'!K7
A437: Person C | B437: ='Home-Coverage'!A8 | C437: ='Home-Coverage'!A8 | D437: ='Home-Coverage'!C8 | E437: ='Home-Coverage'!D8 | F437: ='Home-Coverage'!E8 | G437: ='Home-Coverage'!F8 | H437: ='Home-Coverage'!G8 | I437: ='Home-Coverage'!H8 | J437: ='Home-Coverage'!I8 | K437: ='Home-Coverage'!J8 | L437: ='Home-Coverage'!K8
A438: Person C | B438: ='Home-Coverage'!A9 | C438: ='Home-Coverage'!A9 | D438: ='Home-Coverage'!C9 | E438: ='Home-Coverage'!D9 | F438: ='Home-Coverage'!E9 | G438: ='Home-Coverage'!F9 | H438: ='Home-Coverage'!G9 | I438: ='Home-Coverage'!H9 | J438: ='Home-Coverage'!I9 | K438: ='Home-Coverage'!J9 | L438: ='Home-Coverage'!K9
A439: Person C | B439: ='Home-Coverage'!A10 | C439: ='Home-Coverage'!A10 | D439: ='Home-Coverage'!C10 | E439: ='Home-Coverage'!D10 | F439: ='Home-Coverage'!E10 | G439: ='Home-Coverage'!F10 | H439: ='Home-Coverage'!G10 | I439: ='Home-Coverage'!H10 | J439: ='Home-Coverage'!I10 | K439: ='Home-Coverage'!J10 | L439: ='Home-Coverage'!K10
A440: Person C | B440: ='Home-Coverage'!A11 | C440: ='Home-Coverage'!A11 | D440: ='Home-Coverage'!C11 | E440: ='Home-Coverage'!D11 | F440: ='Home-Coverage'!E11 | G440: ='Home-Coverage'!F11 | H440: ='Home-Coverage'!G11 | I440: ='Home-Coverage'!H11 | J440: ='Home-Coverage'!I11 | K440: ='Home-Coverage'!J11 | L440: ='Home-Coverage'!K11
A441: Person C | B441: ='Home-Coverage'!A12 | C441: ='Home-Coverage'!A12 | D441: ='Home-Coverage'!C12 | E441: ='Home-Coverage'!D12 | F441: ='Home-Coverage'!E12 | G441: ='Home-Coverage'!F12 | H441: ='Home-Coverage'!G12 | I441: ='Home-Coverage'!H12 | J441: ='Home-Coverage'!I12 | K441: ='Home-Coverage'!J12 | L441: ='Home-Coverage'!K12
A442: Person C | B442: ='Home-Coverage'!A13 | C442: ='Home-Coverage'!A13 | D442: ='Home-Coverage'!C13 | E442: ='Home-Coverage'!D13 | F442: ='Home-Coverage'!E13 | G442: ='Home-Coverage'!F13 | H442: ='Home-Coverage'!G13 | I442: ='Home-Coverage'!H13 | J442: ='Home-Coverage'!I13 | K442: ='Home-Coverage'!J13 | L442: ='Home-Coverage'!K13
A443: Person C | B443: ='Home-Coverage'!A14 | C443: ='Home-Coverage'!A14 | D443: ='Home-Coverage'!C14 | E443: ='Home-Coverage'!D14 | F443: ='Home-Coverage'!E14 | G443: ='Home-Coverage'!F14 | H443: ='Home-Coverage'!G14 | I443: ='Home-Coverage'!H14 | J443: ='Home-Coverage'!I14 | K443: ='Home-Coverage'!J14 | L443: ='Home-Coverage'!K14
... A630: Person C | B630: ='Home-Coverage'!A201 | C630: ='Home-Coverage'!A201 | D630: ='Home-Coverage'!C201 | E630: ='Home-Coverage'!D201 | F630: ='Home-Coverage'!E201 | G630: ='Home-Coverage'!F201 | H630: ='Home-Coverage'!G201 | I630: ='Home-Coverage'!H201 | J630: ='Home-Coverage'!I201 | K630: ='Home-Coverage'!J201 | L630: ='Home-Coverage'!K201
A631: Person C | H631: ='Home-Coverage'!G202 | I631: ='Home-Coverage'!H202 | J631: ='Home-Coverage'!I202 | K631: ='Home-Coverage'!J202 | L631: ='Home-Coverage'!K202
A632: GRAND TOTAL — ALL COVERAGE | H632: ='Madine- Coverage'!G203+'Zarrah- Coverage'!G203+'Home-Coverage'!G203 | I632: ='Madine- Coverage'!H203+'Zarrah- Coverage'!H203+'Home-Coverage'!H203
A635: SECTION C — SALES CONVERSION DETAIL (ALL PERSONS)
A636: TOTAL GP (VAT EX) | B636: TOTAL GP (VAT EX) | C636: TOTAL GP (VAT EX) | D636: TOTAL GP (VAT EX) | E636: TOTAL GP (VAT EX) | F636: TOTAL GP (VAT EX) | G636: TOTAL GP (VAT EX) | H636: TOTAL GP (VAT EX) | I636: TOTAL GP (VAT EX) | J636: TOTAL GP (VAT EX) | K636: TOTAL GP (VAT EX) | L636: TOTAL GP (VAT EX) | M636: TOTAL GP (VAT EX) | N636: TOTAL GP (VAT EX) | O636: TOTAL GP (VAT EX)
A637: Person A | B637: ='Madine- Conversion'!A3 | C637: ='Madine- Conversion'!B3 | D637: ='Madine- Conversion'!C3 | E637: ='Madine- Conversion'!D3 | F637: ='Madine- Conversion'!E3 | G637: ='Madine- Conversion'!F3 | H637: ='Madine- Conversion'!G3 | I637: ='Madine- Conversion'!H3 | ... L637: ='Madine- Conversion'!K3 | M637: ='Madine- Conversion'!N3 | N637: ='Madine- Conversion'!O3 | O637: ='Madine- Conversion'!P3
A638: Person A | B638: ='Madine- Conversion'!A4 | C638: ='Madine- Conversion'!B4 | D638: ='Madine- Conversion'!C4 | E638: ='Madine- Conversion'!D4 | F638: ='Madine- Conversion'!E4 | G638: ='Madine- Conversion'!F4 | H638: ='Madine- Conversion'!G4 | I638: ='Madine- Conversion'!H4 | ... L638: ='Madine- Conversion'!K4 | M638: ='Madine- Conversion'!N4 | N638: ='Madine- Conversion'!O4 | O638: ='Madine- Conversion'!P4
A639: Person A | B639: ='Madine- Conversion'!A5 | C639: ='Madine- Conversion'!B5 | D639: ='Madine- Conversion'!C5 | E639: ='Madine- Conversion'!D5 | F639: ='Madine- Conversion'!E5 | G639: ='Madine- Conversion'!F5 | H639: ='Madine- Conversion'!G5 | I639: ='Madine- Conversion'!H5 | ... L639: ='Madine- Conversion'!K5 | M639: ='Madine- Conversion'!N5 | N639: ='Madine- Conversion'!O5 | O639: ='Madine- Conversion'!P5
A640: Person A | B640: ='Madine- Conversion'!A6 | C640: ='Madine- Conversion'!B6 | D640: ='Madine- Conversion'!C6 | E640: ='Madine- Conversion'!D6 | F640: ='Madine- Conversion'!E6 | G640: ='Madine- Conversion'!F6 | H640: ='Madine- Conversion'!G6 | I640: ='Madine- Conversion'!H6 | ... L640: ='Madine- Conversion'!K6 | M640: ='Madine- Conversion'!N6 | N640: ='Madine- Conversion'!O6 | O640: ='Madine- Conversion'!P6
A641: Person A | B641: ='Madine- Conversion'!A7 | C641: ='Madine- Conversion'!B7 | D641: ='Madine- Conversion'!C7 | E641: ='Madine- Conversion'!D7 | F641: ='Madine- Conversion'!E7 | G641: ='Madine- Conversion'!F7 | H641: ='Madine- Conversion'!G7 | I641: ='Madine- Conversion'!H7 | ... L641: ='Madine- Conversion'!K7 | M641: ='Madine- Conversion'!N7 | N641: ='Madine- Conversion'!O7 | O641: ='Madine- Conversion'!P7
A642: Person A | B642: ='Madine- Conversion'!A8 | C642: ='Madine- Conversion'!B8 | D642: ='Madine- Conversion'!C8 | E642: ='Madine- Conversion'!D8 | F642: ='Madine- Conversion'!E8 | G642: ='Madine- Conversion'!F8 | H642: ='Madine- Conversion'!G8 | I642: ='Madine- Conversion'!H8 | ... L642: ='Madine- Conversion'!K8 | M642: ='Madine- Conversion'!N8 | N642: ='Madine- Conversion'!O8 | O642: ='Madine- Conversion'!P8
A643: Person A | B643: ='Madine- Conversion'!A9 | C643: ='Madine- Conversion'!B9 | D643: ='Madine- Conversion'!C9 | E643: ='Madine- Conversion'!D9 | F643: ='Madine- Conversion'!E9 | G643: ='Madine- Conversion'!F9 | H643: ='Madine- Conversion'!G9 | I643: ='Madine- Conversion'!H9 | ... L643: ='Madine- Conversion'!K9 | M643: ='Madine- Conversion'!N9 | N643: ='Madine- Conversion'!O9 | O643: ='Madine- Conversion'!P9
A644: Person A | B644: ='Madine- Conversion'!A10 | C644: ='Madine- Conversion'!B10 | D644: ='Madine- Conversion'!C10 | E644: ='Madine- Conversion'!D10 | F644: ='Madine- Conversion'!E10 | G644: ='Madine- Conversion'!F10 | H644: ='Madine- Conversion'!G10 | I644: ='Madine- Conversion'!H10 | ... L644: ='Madine- Conversion'!K10 | M644: ='Madine- Conversion'!N10 | N644: ='Madine- Conversion'!O10 | O644: ='Madine- Conversion'!P10
A645: Person A | B645: ='Madine- Conversion'!A11 | C645: ='Madine- Conversion'!B11 | D645: ='Madine- Conversion'!C11 | E645: ='Madine- Conversion'!D11 | F645: ='Madine- Conversion'!E11 | G645: ='Madine- Conversion'!F11 | H645: ='Madine- Conversion'!G11 | I645: ='Madine- Conversion'!H11 | ... L645: ='Madine- Conversion'!K11 | M645: ='Madine- Conversion'!N11 | N645: ='Madine- Conversion'!O11 | O645: ='Madine- Conversion'!P11
A646: Person A | B646: ='Madine- Conversion'!A12 | C646: ='Madine- Conversion'!B12 | D646: ='Madine- Conversion'!C12 | E646: ='Madine- Conversion'!D12 | F646: ='Madine- Conversion'!E12 | G646: ='Madine- Conversion'!F12 | H646: ='Madine- Conversion'!G12 | I646: ='Madine- Conversion'!H12 | ... L646: ='Madine- Conversion'!K12 | M646: ='Madine- Conversion'!N12 | N646: ='Madine- Conversion'!O12 | O646: ='Madine- Conversion'!P12
A647: Person A | B647: ='Madine- Conversion'!A13 | C647: ='Madine- Conversion'!B13 | D647: ='Madine- Conversion'!C13 | E647: ='Madine- Conversion'!D13 | F647: ='Madine- Conversion'!E13 | G647: ='Madine- Conversion'!F13 | H647: ='Madine- Conversion'!G13 | I647: ='Madine- Conversion'!H13 | ... L647: ='Madine- Conversion'!K13 | M647: ='Madine- Conversion'!N13 | N647: ='Madine- Conversion'!O13 | O647: ='Madine- Conversion'!P13
A648: Person A | B648: ='Madine- Conversion'!A14 | C648: ='Madine- Conversion'!B14 | D648: ='Madine- Conversion'!C14 | E648: ='Madine- Conversion'!D14 | F648: ='Madine- Conversion'!E14 | G648: ='Madine- Conversion'!F14 | H648: ='Madine- Conversion'!G14 | I648: ='Madine- Conversion'!H14 | ... L648: ='Madine- Conversion'!K14 | M648: ='Madine- Conversion'!N14 | N648: ='Madine- Conversion'!O14 | O648: ='Madine- Conversion'!P14
... A836: Person A | B836: ='Madine- Conversion'!A202 | C836: ='Madine- Conversion'!B202 | D836: ='Madine- Conversion'!C202 | E836: ='Madine- Conversion'!D202 | F836: ='Madine- Conversion'!E202 | G836: ='Madine- Conversion'!F202 | H836: ='Madine- Conversion'!G202 | I836: ='Madine- Conversion'!H202 | ... L836: ='Madine- Conversion'!K202 | M836: ='Madine- Conversion'!N202 | N836: ='Madine- Conversion'!O202 | O836: ='Madine- Conversion'!P202
A837: Person B | B837: ='Zarrah-Conversion'!A2 | C837: ='Zarrah-Conversion'!B2 | D837: ='Zarrah-Conversion'!C2 | E837: ='Zarrah-Conversion'!D2 | F837: ='Zarrah-Conversion'!E2 | G837: ='Zarrah-Conversion'!F2 | H837: ='Zarrah-Conversion'!G2 | I837: ='Zarrah-Conversion'!H2 | ... L837: ='Zarrah-Conversion'!K2 | M837: ='Zarrah-Conversion'!N2 | N837: ='Zarrah-Conversion'!O2 | O837: ='Zarrah-Conversion'!P2
A838: Person B | B838: ='Zarrah-Conversion'!A3 | C838: ='Zarrah-Conversion'!B3 | D838: ='Zarrah-Conversion'!C3 | E838: ='Zarrah-Conversion'!D3 | F838: ='Zarrah-Conversion'!E3 | G838: ='Zarrah-Conversion'!F3 | H838: ='Zarrah-Conversion'!G3 | I838: ='Zarrah-Conversion'!H3 | ... L838: ='Zarrah-Conversion'!K3 | M838: ='Zarrah-Conversion'!N3 | N838: ='Zarrah-Conversion'!O3 | O838: ='Zarrah-Conversion'!P3
A839: Person B | B839: ='Zarrah-Conversion'!A4 | C839: ='Zarrah-Conversion'!B4 | D839: ='Zarrah-Conversion'!C4 | E839: ='Zarrah-Conversion'!D4 | F839: ='Zarrah-Conversion'!E4 | G839: ='Zarrah-Conversion'!F4 | H839: ='Zarrah-Conversion'!G4 | I839: ='Zarrah-Conversion'!H4 | ... L839: ='Zarrah-Conversion'!K4 | M839: ='Zarrah-Conversion'!N4 | N839: ='Zarrah-Conversion'!O4 | O839: ='Zarrah-Conversion'!P4
A840: Person B | B840: ='Zarrah-Conversion'!A5 | C840: ='Zarrah-Conversion'!B5 | D840: ='Zarrah-Conversion'!C5 | E840: ='Zarrah-Conversion'!D5 | F840: ='Zarrah-Conversion'!E5 | G840: ='Zarrah-Conversion'!F5 | H840: ='Zarrah-Conversion'!G5 | I840: ='Zarrah-Conversion'!H5 | ... L840: ='Zarrah-Conversion'!K5 | M840: ='Zarrah-Conversion'!N5 | N840: ='Zarrah-Conversion'!O5 | O840: ='Zarrah-Conversion'!P5
A841: Person B | B841: ='Zarrah-Conversion'!A6 | C841: ='Zarrah-Conversion'!B6 | D841: ='Zarrah-Conversion'!C6 | E841: ='Zarrah-Conversion'!D6 | F841: ='Zarrah-Conversion'!E6 | G841: ='Zarrah-Conversion'!F6 | H841: ='Zarrah-Conversion'!G6 | I841: ='Zarrah-Conversion'!H6 | ... L841: ='Zarrah-Conversion'!K6 | M841: ='Zarrah-Conversion'!N6 | N841: ='Zarrah-Conversion'!O6 | O841: ='Zarrah-Conversion'!P6
A842: Person B | B842: ='Zarrah-Conversion'!A7 | C842: ='Zarrah-Conversion'!B7 | D842: ='Zarrah-Conversion'!C7 | E842: ='Zarrah-Conversion'!D7 | F842: ='Zarrah-Conversion'!E7 | G842: ='Zarrah-Conversion'!F7 | H842: ='Zarrah-Conversion'!G7 | I842: ='Zarrah-Conversion'!H7 | ... L842: ='Zarrah-Conversion'!K7 | M842: ='Zarrah-Conversion'!N7 | N842: ='Zarrah-Conversion'!O7 | O842: ='Zarrah-Conversion'!P7
A843: Person B | B843: ='Zarrah-Conversion'!A8 | C843: ='Zarrah-Conversion'!B8 | D843: ='Zarrah-Conversion'!C8 | E843: ='Zarrah-Conversion'!D8 | F843: ='Zarrah-Conversion'!E8 | G843: ='Zarrah-Conversion'!F8 | H843: ='Zarrah-Conversion'!G8 | I843: ='Zarrah-Conversion'!H8 | ... L843: ='Zarrah-Conversion'!K8 | M843: ='Zarrah-Conversion'!N8 | N843: ='Zarrah-Conversion'!O8 | O843: ='Zarrah-Conversion'!P8
A844: Person B | B844: ='Zarrah-Conversion'!A9 | C844: ='Zarrah-Conversion'!B9 | D844: ='Zarrah-Conversion'!C9 | E844: ='Zarrah-Conversion'!D9 | F844: ='Zarrah-Conversion'!E9 | G844: ='Zarrah-Conversion'!F9 | H844: ='Zarrah-Conversion'!G9 | I844: ='Zarrah-Conversion'!H9 | ... L844: ='Zarrah-Conversion'!K9 | M844: ='Zarrah-Conversion'!N9 | N844: ='Zarrah-Conversion'!O9 | O844: ='Zarrah-Conversion'!P9
A845: Person B | B845: ='Zarrah-Conversion'!A10 | C845: ='Zarrah-Conversion'!B10 | D845: ='Zarrah-Conversion'!C10 | E845: ='Zarrah-Conversion'!D10 | F845: ='Zarrah-Conversion'!E10 | G845: ='Zarrah-Conversion'!F10 | H845: ='Zarrah-Conversion'!G10 | I845: ='Zarrah-Conversion'!H10 | ... L845: ='Zarrah-Conversion'!K10 | M845: ='Zarrah-Conversion'!N10 | N845: ='Zarrah-Conversion'!O10 | O845: ='Zarrah-Conversion'!P10
A846: Person B | B846: ='Zarrah-Conversion'!A11 | C846: ='Zarrah-Conversion'!B11 | D846: ='Zarrah-Conversion'!C11 | E846: ='Zarrah-Conversion'!D11 | F846: ='Zarrah-Conversion'!E11 | G846: ='Zarrah-Conversion'!F11 | H846: ='Zarrah-Conversion'!G11 | I846: ='Zarrah-Conversion'!H11 | ... L846: ='Zarrah-Conversion'!K11 | M846: ='Zarrah-Conversion'!N11 | N846: ='Zarrah-Conversion'!O11 | O846: ='Zarrah-Conversion'!P11
A847: Person B | B847: ='Zarrah-Conversion'!A12 | C847: ='Zarrah-Conversion'!B12 | D847: ='Zarrah-Conversion'!C12 | E847: ='Zarrah-Conversion'!D12 | F847: ='Zarrah-Conversion'!E12 | G847: ='Zarrah-Conversion'!F12 | H847: ='Zarrah-Conversion'!G12 | I847: ='Zarrah-Conversion'!H12 | ... L847: ='Zarrah-Conversion'!K12 | M847: ='Zarrah-Conversion'!N12 | N847: ='Zarrah-Conversion'!O12 | O847: ='Zarrah-Conversion'!P12
A848: Person B | B848: ='Zarrah-Conversion'!A13 | C848: ='Zarrah-Conversion'!B13 | D848: ='Zarrah-Conversion'!C13 | E848: ='Zarrah-Conversion'!D13 | F848: ='Zarrah-Conversion'!E13 | G848: ='Zarrah-Conversion'!F13 | H848: ='Zarrah-Conversion'!G13 | I848: ='Zarrah-Conversion'!H13 | ... L848: ='Zarrah-Conversion'!K13 | M848: ='Zarrah-Conversion'!N13 | N848: ='Zarrah-Conversion'!O13 | O848: ='Zarrah-Conversion'!P13
... A1036: Person B | B1036: ='Zarrah-Conversion'!A201 | C1036: ='Zarrah-Conversion'!B201 | D1036: ='Zarrah-Conversion'!C201 | E1036: ='Zarrah-Conversion'!D201 | F1036: ='Zarrah-Conversion'!E201 | G1036: ='Zarrah-Conversion'!F201 | H1036: ='Zarrah-Conversion'!G201 | I1036: ='Zarrah-Conversion'!H201 | ... L1036: ='Zarrah-Conversion'!K201 | M1036: ='Zarrah-Conversion'!N201 | N1036: ='Zarrah-Conversion'!O201 | O1036: ='Zarrah-Conversion'!P201
A1037: Person C | B1037: ='Home-Conversion'!A3 | C1037: ='Home-Conversion'!B3 | D1037: ='Home-Conversion'!C3 | E1037: ='Home-Conversion'!D3 | F1037: ='Home-Conversion'!E3 | G1037: ='Home-Conversion'!F3 | H1037: ='Home-Conversion'!G3 | I1037: ='Home-Conversion'!H3 | ... L1037: ='Home-Conversion'!K3 | M1037: ='Home-Conversion'!N3 | N1037: ='Home-Conversion'!O3 | O1037: ='Home-Conversion'!P3
A1038: Person C | B1038: ='Home-Conversion'!A4 | C1038: ='Home-Conversion'!B4 | D1038: ='Home-Conversion'!C4 | E1038: ='Home-Conversion'!D4 | F1038: ='Home-Conversion'!E4 | G1038: ='Home-Conversion'!F4 | H1038: ='Home-Conversion'!G4 | I1038: ='Home-Conversion'!H4 | ... L1038: ='Home-Conversion'!K4 | M1038: ='Home-Conversion'!N4 | N1038: ='Home-Conversion'!O4 | O1038: ='Home-Conversion'!P4
A1039: Person C | B1039: ='Home-Conversion'!A5 | C1039: ='Home-Conversion'!B5 | D1039: ='Home-Conversion'!C5 | E1039: ='Home-Conversion'!D5 | F1039: ='Home-Conversion'!E5 | G1039: ='Home-Conversion'!F5 | H1039: ='Home-Conversion'!G5 | I1039: ='Home-Conversion'!H5 | ... L1039: ='Home-Conversion'!K5 | M1039: ='Home-Conversion'!N5 | N1039: ='Home-Conversion'!O5 | O1039: ='Home-Conversion'!P5
A1040: Person C | B1040: ='Home-Conversion'!A6 | C1040: ='Home-Conversion'!B6 | D1040: ='Home-Conversion'!C6 | E1040: ='Home-Conversion'!D6 | F1040: ='Home-Conversion'!E6 | G1040: ='Home-Conversion'!F6 | H1040: ='Home-Conversion'!G6 | I1040: ='Home-Conversion'!H6 | ... L1040: ='Home-Conversion'!K6 | M1040: ='Home-Conversion'!N6 | N1040: ='Home-Conversion'!O6 | O1040: ='Home-Conversion'!P6
A1041: Person C | B1041: ='Home-Conversion'!A7 | C1041: ='Home-Conversion'!B7 | D1041: ='Home-Conversion'!C7 | E1041: ='Home-Conversion'!D7 | F1041: ='Home-Conversion'!E7 | G1041: ='Home-Conversion'!F7 | H1041: ='Home-Conversion'!G7 | I1041: ='Home-Conversion'!H7 | ... L1041: ='Home-Conversion'!K7 | M1041: ='Home-Conversion'!N7 | N1041: ='Home-Conversion'!O7 | O1041: ='Home-Conversion'!P7
...
